practice/Lab03_priority_encoder/priority_encoder.v
module priority_encoder (
    input      [7:0] in,
    output reg [2:0] out
);

// TODO:
// Implement an 8-to-3 priority encoder.
// Higher input bit has higher priority.
always @(*) begin
    out = 3'd0;

    casez (in)
        8'b1???_????: out = 3'd7;
        8'b01??_????: out = 3'd6;
        8'b001?_????: out = 3'd5;
        8'b0001_????: ...; // To be completed
        8'b0000_1???: ...; // To be completed
        8'b0000_01??: ...; // To be completed
        8'b0000_001?: ...; // To be completed
        8'b0000_0001: ...; // To be completed
        default:      out = 3'd0;
    endcase
end

endmodule

practice/Lab03_priority_encoder/tb.v
`timescale 1ns/1ps
module tb_priority_encoder;
    reg [7:0] in;
    wire [2:0] out;
    integer errors, log_fd, result_fd, pattern;

    priority_encoder dut (.in(in), .out(out));

    task check;
        input [7:0] value;
        input [2:0] expected;
        begin
            in = value;
            pattern = pattern + 1;
            #1;
            if (out !== expected) begin
                if (errors == 0) $display("[ERROR] pattern %0d: in=%b expected out=%0d got=%0d", pattern, value, expected, out);
                if (errors == 0) $fdisplay(log_fd, "[ERROR] pattern %0d: in=%b expected out=%0d got=%0d", pattern, value, expected, out);
                errors = errors + 1;
            end
        end
    endtask

    initial begin
        log_fd = $fopen("sim/log.txt", "w");
        result_fd = $fopen("sim/result.txt", "w");
        $dumpfile("sim/wave.vcd");
        $dumpvars(0, tb_priority_encoder);
        $display("##SEC_STUDENT_CAN_SEE");
        $fdisplay(log_fd, "##SEC_STUDENT_CAN_SEE");
        // GOLDEN_CASE_SUMMARY_BEGIN
        $display("[CASE 1] checks zero input");
        $fdisplay(log_fd,"[CASE 1] checks zero input");
        $display("[CASE 2-9] checks priority branches and multi-bit inputs");
        $fdisplay(log_fd,"[CASE 2-9] checks priority branches and multi-bit inputs");
        // GOLDEN_CASE_SUMMARY_END


        errors = 0; pattern = 0;

        check(8'b0000_0000, 3'd0);
        check(8'b0000_0001, 3'd0);
        check(8'b0000_0010, 3'd1);
        check(8'b0000_0101, 3'd2);
        check(8'b0000_1000, 3'd3);
        check(8'b0001_0010, 3'd4);
        check(8'b0010_0010, 3'd5);
        check(8'b1010_0000, 3'd7);
        check(8'b0100_1111, 3'd6);

        if (errors == 0) begin
            $display("[PASS] priority_encoder");
            $fdisplay(log_fd, "[PASS] priority_encoder");
            $fdisplay(result_fd, "pass");
        end else begin
            $display("[FAIL] priority_encoder, errors = %0d", errors);
            $fdisplay(log_fd, "[FAIL] priority_encoder, errors = %0d", errors);
            $fdisplay(result_fd, "fail");
        end
        $display("##END_STUDENT_CAN_SEE");
        $fdisplay(log_fd, "##END_STUDENT_CAN_SEE");
        $fclose(log_fd); $fclose(result_fd);
        $finish;
    end
endmodule

practice/Lab03_priority_encoder/golden/golden_wave.vcd
$date
	Mon May 11 15:57:58 2026
$end
$version
	Icarus Verilog
$end
$timescale
	1ps
$end
$scope module tb_priority_encoder $end
$var wire 3 ! out [2:0] $end
$var reg 8 " in [7:0] $end
$var integer 32 # errors [31:0] $end
$var integer 32 $ log_fd [31:0] $end
$var integer 32 % pattern [31:0] $end
$var integer 32 & result_fd [31:0] $end
$scope module dut $end
$var wire 8 ' in [7:0] $end
$var reg 3 ( out [2:0] $end
$upscope $end
$scope task check $end
$var reg 3 ) expected [2:0] $end
$var reg 8 * value [7:0] $end
$upscope $end
$upscope $end
$enddefinitions $end
$comment Show the parameter values. $end
$dumpall
$end
#0
$dumpvars
b0 *
b0 )
b0 (
b0 '
b10000000000000000000000000000100 &
b1 %
b10000000000000000000000000000011 $
b0 #
b0 "
b0 !
$end
#1000
b10 %
b1 "
b1 '
b1 *
#2000
b1 !
b1 (
b11 %
b10 "
b10 '
b1 )
b10 *
#3000
b10 !
b10 (
b100 %
b101 "
b101 '
b10 )
b101 *
#4000
b11 !
b11 (
b101 %
b1000 "
b1000 '
b11 )
b1000 *
#5000
b100 !
b100 (
b110 %
b10010 "
b10010 '
b100 )
b10010 *
#6000
b101 !
b101 (
b111 %
b100010 "
b100010 '
b101 )
b100010 *
#7000
b111 !
b111 (
b1000 %
b10100000 "
b10100000 '
b111 )
b10100000 *
#8000
b110 !
b110 (
b1001 %
b1001111 "
b1001111 '
b110 )
b1001111 *
