fpga_lab/Lab05_pulse_detector/pulse_detector.v
module pulse_detector (
    input  clk,
    input  rst,
    input  in,
    output reg pulse
);

reg in_r;

always @(posedge clk or posedge rst) begin
    if (rst) begin
        in_r  <= 1'b0;
        pulse <= 1'b0;
    end else begin
        in_r  <= ...; // register the input signal
        pulse <= in & ~in_r;
    end
end

endmodule

fpga_lab/Lab03_pulse_detector/tb.v
`timescale 1ns/1ps
module tb_pulse_detector;
    reg clk,rst,in;
    wire pulse;
    integer errors,log_fd,result_fd,pattern;

    pulse_detector dut(.clk(clk),.rst(rst),.in(in),.pulse(pulse));
    initial begin clk=0; forever #5 clk=~clk; end

    task check;
        input [8*32-1:0] name;
        input exp;
        begin
            pattern = pattern + 1;
            #1;
            if(pulse!==exp) begin
                if (errors == 0) $display("[ERROR] pattern %0d (%0s): in=%b expected pulse=%b got=%b", pattern, name, in, exp, pulse);
                if (errors == 0) $fdisplay(log_fd,"[ERROR] pattern %0d (%0s): in=%b expected pulse=%b got=%b", pattern, name, in, exp, pulse);
                errors=errors+1;
            end
        end
    endtask

    initial begin
        log_fd=$fopen("sim/log.txt","w"); result_fd=$fopen("sim/result.txt","w");
        $dumpfile("sim/wave.vcd"); $dumpvars(0,tb_pulse_detector);
        $display("##SEC_STUDENT_CAN_SEE"); $fdisplay(log_fd,"##SEC_STUDENT_CAN_SEE");
        // GOLDEN_CASE_SUMMARY_BEGIN
        $display("[CASE 1] checks idle low");
        $fdisplay(log_fd,"[CASE 1] checks idle low");
        $display("[CASE 2] checks first rising edge pulse");
        $fdisplay(log_fd,"[CASE 2] checks first rising edge pulse");
        $display("[CASE 3] checks no repeated pulse while held high");
        $fdisplay(log_fd,"[CASE 3] checks no repeated pulse while held high");
        $display("[CASE 4] checks return low");
        $fdisplay(log_fd,"[CASE 4] checks return low");
        $display("[CASE 5] checks second rising edge pulse");
        $fdisplay(log_fd,"[CASE 5] checks second rising edge pulse");
        // GOLDEN_CASE_SUMMARY_END


        errors=0; pattern=0; rst=1; in=0;
        repeat(2) @(posedge clk); @(negedge clk); rst=0;
        @(posedge clk); check("idle low", 1'b0);
        @(negedge clk); in=1; @(posedge clk); check("first rising edge", 1'b1);
        @(posedge clk); check("hold high no repeat", 1'b0);
        @(negedge clk); in=0; @(posedge clk); check("return low", 1'b0);
        @(negedge clk); in=1; @(posedge clk); check("second rising edge", 1'b1);
        if(errors==0) begin $display("[PASS] pulse_detector"); $fdisplay(log_fd,"[PASS] pulse_detector"); $fdisplay(result_fd,"pass"); end
        else begin $display("[FAIL] pulse_detector, errors = %0d",errors); $fdisplay(log_fd,"[FAIL] pulse_detector, errors = %0d",errors); $fdisplay(result_fd,"fail"); end
        $display("##END_STUDENT_CAN_SEE"); $fdisplay(log_fd,"##END_STUDENT_CAN_SEE");
        $fclose(log_fd); $fclose(result_fd); $finish;
    end
endmodule

fpga_lab/Lab05_pulse_detector/golden/golden_wave.vcd
$date
	Mon May 11 09:39:55 2026
$end
$version
	Icarus Verilog
$end
$timescale
	1ps
$end
$scope module tb_pulse_detector $end
$var wire 1 ! pulse $end
$var reg 1 " clk $end
$var reg 1 # in $end
$var reg 1 $ rst $end
$var integer 32 % errors [31:0] $end
$var integer 32 & log_fd [31:0] $end
$var integer 32 ' pattern [31:0] $end
$var integer 32 ( result_fd [31:0] $end
$scope module dut $end
$var wire 1 " clk $end
$var wire 1 # in $end
$var wire 1 $ rst $end
$var reg 1 ) in_r $end
$var reg 1 ! pulse $end
$upscope $end
$scope task check $end
$var reg 1 * exp $end
$var reg 256 + name [255:0] $end
$upscope $end
$upscope $end
$enddefinitions $end
$comment Show the parameter values. $end
$dumpall
$end
#0
$dumpvars
bx +
x*
0)
b10000000000000000000000000000100 (
b0 '
b10000000000000000000000000000011 &
b0 %
1$
0#
0"
0!
$end
#5000
1"
#10000
0"
#15000
1"
#20000
0$
0"
#25000
b1 '
0*
b110100101100100011011000110010100100000011011000110111101110111 +
1"
#30000
1#
0"
#35000
1!
1)
b10 '
1*
b110011001101001011100100111001101110100001000000111001001101001011100110110100101101110011001110010000001100101011001000110011101100101 +
1"
#40000
0"
#45000
0!
b11 '
0*
b1101000011011110110110001100100001000000110100001101001011001110110100000100000011011100110111100100000011100100110010101110000011001010110000101110100 +
1"
#50000
0#
0"
#55000
0)
b100 '
b1110010011001010111010001110101011100100110111000100000011011000110111101110111 +
1"
#60000
1#
0"
#65000
1!
1)
b101 '
1*
b11100110110010101100011011011110110111001100100001000000111001001101001011100110110100101101110011001110010000001100101011001000110011101100101 +
1"
