fpga_lab/Lab02_counter/golden/counter.v
module counter #(
    parameter MAX_COUNT   = 9,
    parameter COUNT_WIDTH = $clog2(MAX_COUNT + 1)
) (
    input  wire       clk,
    input  wire       rst,
    input  wire       clr,
    input  wire       en,
    input  wire       up,         // 1: count up, 0: hold (or you can extend to count down)
    output reg  [COUNT_WIDTH-1:0] count
);

always @(posedge clk or posedge rst) begin
    if (rst) begin
        count <= 0;
    end else if (clr) begin
        count <= 0;
    end else if (en) begin
        if (up) begin
            count <= (count == MAX_COUNT) ? 0 : (count + 1);
        end
    end
end

endmodule

fpga_lab/Lab02_counter/tb.v
`timescale 1ns/1ps
module tb_counter;
    reg clk,rst,clr,en,up;
    wire [3:0] count;
    wire [2:0] count_mod6;
    integer errors,log_fd,result_fd,i,pattern;

    counter dut(.clk(clk),.rst(rst),.clr(clr),.en(en),.up(up),.count(count));
    counter #(.MAX_COUNT(5)) dut_mod6(.clk(clk),.rst(rst),.clr(clr),.en(en),.up(up),.count(count_mod6));
    initial begin clk=0; forever #5 clk=~clk; end

    task check_count;
        input [8*32-1:0] name;
        input [3:0] expected;
        begin
            pattern = pattern + 1;
            #1;
            if(count!==expected) begin
                if (errors == 0) $display("[ERROR] pattern %0d (%0s): en=%b up=%b clr=%b expected count=%0d got=%0d", pattern, name, en, up, clr, expected, count);
                if (errors == 0) $fdisplay(log_fd,"[ERROR] pattern %0d (%0s): en=%b up=%b clr=%b expected count=%0d got=%0d", pattern, name, en, up, clr, expected, count);
                errors=errors+1;
            end
        end
    endtask

    task check_mod6;
        input [8*32-1:0] name;
        input [2:0] expected;
        begin
            pattern = pattern + 1;
            #1;
            if(count_mod6!==expected) begin
                if (errors == 0) $display("[ERROR] pattern %0d (%0s): MAX_COUNT=5 expected count=%0d got count=%0d", pattern, name, expected, count_mod6);
                if (errors == 0) $fdisplay(log_fd,"[ERROR] pattern %0d (%0s): MAX_COUNT=5 expected count=%0d got count=%0d", pattern, name, expected, count_mod6);
                errors=errors+1;
            end
        end
    endtask

    initial begin
        log_fd=$fopen("sim/log.txt","w"); result_fd=$fopen("sim/result.txt","w");
        $dumpfile("sim/wave.vcd"); $dumpvars(0,tb_counter);
        $display("##SEC_STUDENT_CAN_SEE"); $fdisplay(log_fd,"##SEC_STUDENT_CAN_SEE");
        // GOLDEN_CASE_SUMMARY_BEGIN
        $display("[CASE 1] checks reset release");
        $fdisplay(log_fd,"[CASE 1] checks reset release");
        $display("[CASE 2-10] checks count-up sequence");
        $fdisplay(log_fd,"[CASE 2-10] checks count-up sequence");
        $display("[CASE 11] checks rollover");
        $fdisplay(log_fd,"[CASE 11] checks rollover");
        $display("[CASE 12] checks clear");
        $fdisplay(log_fd,"[CASE 12] checks clear");
        $display("[CASE 13] checks hold when disabled");
        $fdisplay(log_fd,"[CASE 13] checks hold when disabled");
        $display("[CASE 14] checks hold when up is low");
        $fdisplay(log_fd,"[CASE 14] checks hold when up is low");
        $display("[CASE 15-20] checks parameterized MAX_COUNT=5 rollover");
        $fdisplay(log_fd,"[CASE 15-20] checks parameterized MAX_COUNT=5 rollover");
        // GOLDEN_CASE_SUMMARY_END


        errors=0; pattern=0; rst=1; clr=0; en=0; up=1;
        repeat(2) @(posedge clk); @(negedge clk); rst=0; check_count("reset release", 4'd0);
        @(negedge clk); en=1;
        for(i=1;i<=9;i=i+1) begin @(posedge clk); check_count("count up", i[3:0]); end
        @(posedge clk); check_count("rollover 9 to 0", 4'd0);
        @(negedge clk); clr=1; @(posedge clk); check_count("clear", 4'd0);
        @(negedge clk); clr=0; en=0; @(posedge clk); check_count("hold when en=0", 4'd0);
        @(negedge clk); en=1; up=0; @(posedge clk); check_count("hold when up=0", 4'd0);

        @(negedge clk); rst=1; clr=0; en=0; up=1;
        @(posedge clk); @(negedge clk); rst=0; en=1;
        for(i=1;i<=5;i=i+1) begin @(posedge clk); check_mod6("parameterized count", i[2:0]); end
        @(posedge clk); check_mod6("parameterized rollover", 3'd0);
        @(negedge clk); en=0;
        repeat(5) @(posedge clk);
        if(errors==0) begin $display("[PASS] counter"); $fdisplay(log_fd,"[PASS] counter"); $fdisplay(result_fd,"pass"); end
        else begin $display("[FAIL] counter, errors = %0d",errors); $fdisplay(log_fd,"[FAIL] counter, errors = %0d",errors); $fdisplay(result_fd,"fail"); end
        $display("##END_STUDENT_CAN_SEE"); $fdisplay(log_fd,"##END_STUDENT_CAN_SEE");
        $fclose(log_fd); $fclose(result_fd); $finish;
    end
endmodule

fpga_lab/Lab02_counter/golden/golden_wave.vcd
$date
	Fri Jun 26 12:50:12 2026
$end
$version
	Icarus Verilog
$end
$timescale
	1ps
$end
$scope module tb_counter $end
$var wire 3 ! count_mod6 [2:0] $end
$var wire 4 " count [3:0] $end
$var reg 1 # clk $end
$var reg 1 $ clr $end
$var reg 1 % en $end
$var reg 1 & rst $end
$var reg 1 ' up $end
$var integer 32 ( errors [31:0] $end
$var integer 32 ) i [31:0] $end
$var integer 32 * log_fd [31:0] $end
$var integer 32 + pattern [31:0] $end
$var integer 32 , result_fd [31:0] $end
$scope module dut $end
$var wire 1 # clk $end
$var wire 1 $ clr $end
$var wire 1 % en $end
$var wire 1 & rst $end
$var wire 1 ' up $end
$var parameter 32 - COUNT_WIDTH $end
$var parameter 32 . MAX_COUNT $end
$var reg 4 / count [3:0] $end
$upscope $end
$scope module dut_mod6 $end
$var wire 1 # clk $end
$var wire 1 $ clr $end
$var wire 1 % en $end
$var wire 1 & rst $end
$var wire 1 ' up $end
$var parameter 32 0 COUNT_WIDTH $end
$var parameter 32 1 MAX_COUNT $end
$var reg 3 2 count [2:0] $end
$upscope $end
$scope task check_count $end
$var reg 4 3 expected [3:0] $end
$var reg 256 4 name [255:0] $end
$upscope $end
$scope task check_mod6 $end
$var reg 3 5 expected [2:0] $end
$var reg 256 6 name [255:0] $end
$upscope $end
$upscope $end
$enddefinitions $end
$comment Show the parameter values. $end
$dumpall
b101 1
b11 0
b1001 .
b100 -
$end
#0
$dumpvars
bx 6
bx 5
bx 4
bx 3
b0 2
b0 /
b10000000000000000000000000000100 ,
b0 +
b10000000000000000000000000000011 *
bx )
b0 (
1'
1&
0%
0$
0#
b0 "
b0 !
$end
#5000
1#
#10000
0#
#15000
1#
#20000
b1 +
b0 3
b1110010011001010111001101100101011101000010000001110010011001010110110001100101011000010111001101100101 4
0&
0#
#25000
1#
#30000
b1 )
1%
0#
#35000
b1 "
b1 /
b1 !
b1 2
b10 +
b1 3
b110001101101111011101010110111001110100001000000111010101110000 4
1#
#36000
b10 )
#40000
0#
#45000
b10 !
b10 2
b10 "
b10 /
b11 +
b10 3
1#
#46000
b11 )
#50000
0#
#55000
b11 "
b11 /
b11 !
b11 2
b100 +
b11 3
1#
#56000
b100 )
#60000
0#
#65000
b100 !
b100 2
b100 "
b100 /
b101 +
b100 3
1#
#66000
b101 )
#70000
0#
#75000
b101 "
b101 /
b101 !
b101 2
b110 +
b101 3
1#
#76000
b110 )
#80000
0#
#85000
b0 !
b0 2
b110 "
b110 /
b111 +
b110 3
1#
#86000
b111 )
#90000
0#
#95000
b111 "
b111 /
b1 !
b1 2
b1000 +
b111 3
1#
#96000
b1000 )
#100000
0#
#105000
b10 !
b10 2
b1000 "
b1000 /
b1001 +
b1000 3
1#
#106000
b1001 )
#110000
0#
#115000
b1001 "
b1001 /
b11 !
b11 2
b1010 +
b1001 3
1#
#116000
b1010 )
#120000
0#
#125000
b100 !
b100 2
b0 "
b0 /
b1011 +
b0 3
b11100100110111101101100011011000110111101110110011001010111001000100000001110010010000001110100011011110010000000110000 4
1#
#130000
1$
0#
#135000
b0 !
b0 2
b1100 +
b110001101101100011001010110000101110010 4
1#
#140000
0%
0$
0#
#145000
b1101 +
b110100001101111011011000110010000100000011101110110100001100101011011100010000001100101011011100011110100110000 4
1#
#150000
0'
1%
0#
#155000
b1110 +
b110100001101111011011000110010000100000011101110110100001100101011011100010000001110101011100000011110100110000 4
1#
#160000
1'
0%
1&
0#
#165000
1#
#170000
b1 )
1%
0&
0#
#175000
b1 !
b1 2
b1 "
b1 /
b1111 +
b1 5
b1110000011000010111001001100001011011010110010101110100011001010111001001101001011110100110010101100100001000000110001101101111011101010110111001110100 6
1#
#176000
b10 )
#180000
0#
#185000
b10 "
b10 /
b10 !
b10 2
b10000 +
b10 5
1#
#186000
b11 )
#190000
0#
#195000
b11 !
b11 2
b11 "
b11 /
b10001 +
b11 5
1#
#196000
b100 )
#200000
0#
#205000
b100 "
b100 /
b100 !
b100 2
b10010 +
b100 5
1#
#206000
b101 )
#210000
0#
#215000
b101 !
b101 2
b101 "
b101 /
b10011 +
b101 5
1#
#216000
b110 )
#220000
0#
#225000
b110 "
b110 /
b0 !
b0 2
b10100 +
b0 5
b1110000011000010111001001100001011011010110010101110100011001010111001001101001011110100110010101100100001000000111001001101111011011000110110001101111011101100110010101110010 6
1#
#230000
0%
0#
