fpga_lab/Lab00_seg7/golden/seg7_dec.v
module seg7_dec (
    input      [3:0] value,
    output reg [6:0] seg
);

// Active-low 7-seg encoding: {a,b,c,d,e,f,g}
always @(*) begin
    case (value)
        4'h0: seg = 7'b0000001;
        4'h1: seg = 7'b1001111;
        4'h2: seg = 7'b0010010;
        4'h3: seg = 7'b0000110;
        4'h4: seg = 7'b1001100;
        4'h5: seg = 7'b0100100;
        4'h6: seg = 7'b0100000;
        4'h7: seg = 7'b0001111;
        4'h8: seg = 7'b0000000;
        4'h9: seg = 7'b0000100;
        default: seg = 7'b1111111;
    endcase
end

endmodule

fpga_lab/Lab00_seg7/tb.v
`timescale 1ns/1ps
module tb_seg7_dec;
    reg [3:0] value;
    wire [6:0] seg;
    integer errors, log_fd, result_fd, pattern;

    seg7_dec dut (.value(value), .seg(seg));

    task check;
        input [3:0] v;
        input [6:0] exp;
        begin
            value = v;
            pattern = pattern + 1;
            #1;
            if (seg !== exp) begin
                if (errors == 0) $display("[ERROR] pattern %0d: value=%h expected seg=%b got=%b", pattern, v, exp, seg);
                if (errors == 0) $fdisplay(log_fd,"[ERROR] pattern %0d: value=%h expected seg=%b got=%b", pattern, v, exp, seg);
                errors = errors + 1;
            end
        end
    endtask

    initial begin
        log_fd=$fopen("sim/log.txt","w"); result_fd=$fopen("sim/result.txt","w");
        $dumpfile("sim/wave.vcd"); $dumpvars(0,tb_seg7_dec);
        $display("##SEC_STUDENT_CAN_SEE"); $fdisplay(log_fd,"##SEC_STUDENT_CAN_SEE");
        // GOLDEN_CASE_SUMMARY_BEGIN
        $display("[CASE 1-10] checks decimal digit encodings");
        $fdisplay(log_fd,"[CASE 1-10] checks decimal digit encodings");
        $display("[CASE 11] checks one default-code input");
        $fdisplay(log_fd,"[CASE 11] checks one default-code input");
        // GOLDEN_CASE_SUMMARY_END


        errors=0; pattern=0;
        check(4'h0,7'b0000001); check(4'h1,7'b1001111); check(4'h2,7'b0010010); check(4'h3,7'b0000110);
        check(4'h4,7'b1001100); check(4'h5,7'b0100100); check(4'h6,7'b0100000); check(4'h7,7'b0001111);
        check(4'h8,7'b0000000); check(4'h9,7'b0000100); check(4'hA,7'b1111111);
        if(errors==0) begin $display("[PASS] seg7_dec"); $fdisplay(log_fd,"[PASS] seg7_dec"); $fdisplay(result_fd,"pass"); end
        else begin $display("[FAIL] seg7_dec, errors = %0d",errors); $fdisplay(log_fd,"[FAIL] seg7_dec, errors = %0d",errors); $fdisplay(result_fd,"fail"); end
        $display("##END_STUDENT_CAN_SEE"); $fdisplay(log_fd,"##END_STUDENT_CAN_SEE");
        $fclose(log_fd); $fclose(result_fd); $finish;
    end
endmodule

fpga_lab/Lab00_seg7/golden/golden_wave.vcd
$date
	Mon May 11 09:39:55 2026
$end
$version
	Icarus Verilog
$end
$timescale
	1ps
$end
$scope module tb_seg7_dec $end
$var wire 7 ! seg [6:0] $end
$var reg 4 " value [3:0] $end
$var integer 32 # errors [31:0] $end
$var integer 32 $ log_fd [31:0] $end
$var integer 32 % pattern [31:0] $end
$var integer 32 & result_fd [31:0] $end
$scope module dut $end
$var wire 4 ' value [3:0] $end
$var reg 7 ( seg [6:0] $end
$upscope $end
$scope task check $end
$var reg 7 ) exp [6:0] $end
$var reg 4 * v [3:0] $end
$upscope $end
$upscope $end
$enddefinitions $end
$comment Show the parameter values. $end
$dumpall
$end
#0
$dumpvars
b0 *
b1 )
b1 (
b0 '
b10000000000000000000000000000100 &
b1 %
b10000000000000000000000000000011 $
b0 #
b0 "
b1 !
$end
#1000
b1001111 !
b1001111 (
b10 %
b1 "
b1 '
b1001111 )
b1 *
#2000
b10010 !
b10010 (
b11 %
b10 "
b10 '
b10010 )
b10 *
#3000
b110 !
b110 (
b100 %
b11 "
b11 '
b110 )
b11 *
#4000
b1001100 !
b1001100 (
b101 %
b100 "
b100 '
b1001100 )
b100 *
#5000
b100100 !
b100100 (
b110 %
b101 "
b101 '
b100100 )
b101 *
#6000
b100000 !
b100000 (
b111 %
b110 "
b110 '
b100000 )
b110 *
#7000
b1111 !
b1111 (
b1000 %
b111 "
b111 '
b1111 )
b111 *
#8000
b0 !
b0 (
b1001 %
b1000 "
b1000 '
b0 )
b1000 *
#9000
b100 !
b100 (
b1010 %
b1001 "
b1001 '
b100 )
b1001 *
#10000
b1111111 !
b1111111 (
b1011 %
b1010 "
b1010 '
b1111111 )
b1010 *
