fpga_lab/Lab06_lfsr_3bits/golden/lfsr_3bits.v
module lfsr_3bits (
	input        clk,
	input        rst,
	input        en,
	output [2:0] lfsr_out
);

parameter LFSR_INIT = 3'b101;
reg [2:0] lfsr, lfsr_nxt;

always @(posedge clk or posedge rst) begin
    if (rst) begin
        lfsr <= LFSR_INIT;
    end else begin
        lfsr <= lfsr_nxt;
    end
end

always @(*) begin
    if (en) begin
        lfsr_nxt = {lfsr[1:0], lfsr[2] ^ lfsr[0]};
    end else begin
        lfsr_nxt = lfsr;
    end
end

assign lfsr_out = lfsr;

endmodule

fpga_lab/Lab06_lfsr_3bits/tb.v
`timescale 1ns/1ps
module tb_lfsr_3bits;
    reg clk,rst,en;
    wire [2:0] lfsr_out;
    integer errors,log_fd,result_fd,i,pattern;
    reg [2:0] exp [0:6];

    lfsr_3bits dut(.clk(clk),.rst(rst),.en(en),.lfsr_out(lfsr_out));
    initial begin clk=0; forever #5 clk=~clk; end
    initial begin exp[0]=3'b101; exp[1]=3'b010; exp[2]=3'b100; exp[3]=3'b001; exp[4]=3'b011; exp[5]=3'b111; exp[6]=3'b110; end

    task check;
        input [8*32-1:0] name;
        input [2:0] expected;
        begin
            pattern = pattern + 1;
            #1;
            if(lfsr_out!==expected) begin
                if (errors == 0) $display("[ERROR] pattern %0d (%0s): en=%b expected lfsr_out=%b got=%b", pattern, name, en, expected, lfsr_out);
                if (errors == 0) $fdisplay(log_fd,"[ERROR] pattern %0d (%0s): en=%b expected lfsr_out=%b got=%b", pattern, name, en, expected, lfsr_out);
                errors=errors+1;
            end
        end
    endtask

    initial begin
        log_fd=$fopen("sim/log.txt","w"); result_fd=$fopen("sim/result.txt","w");
        $dumpfile("sim/wave.vcd"); $dumpvars(0,tb_lfsr_3bits);
        $display("##SEC_STUDENT_CAN_SEE"); $fdisplay(log_fd,"##SEC_STUDENT_CAN_SEE");
        // GOLDEN_CASE_SUMMARY_BEGIN
        $display("[CASE 1] checks reset seed");
        $fdisplay(log_fd,"[CASE 1] checks reset seed");
        $display("[CASE 2-7] checks enabled LFSR sequence");
        $fdisplay(log_fd,"[CASE 2-7] checks enabled LFSR sequence");
        $display("[CASE 8] checks hold when disabled");
        $fdisplay(log_fd,"[CASE 8] checks hold when disabled");
        // GOLDEN_CASE_SUMMARY_END


        errors=0; pattern=0; rst=1; en=0;
        repeat(2) @(posedge clk); @(negedge clk); rst=0; check("reset release", exp[0]);
        @(negedge clk); en=1;
        for(i=1;i<=6;i=i+1) begin @(posedge clk); check("lfsr sequence", exp[i]); end
        @(negedge clk); en=0; @(posedge clk); check("hold when en=0", exp[6]);
        if(errors==0) begin $display("[PASS] lfsr_3bits"); $fdisplay(log_fd,"[PASS] lfsr_3bits"); $fdisplay(result_fd,"pass"); end
        else begin $display("[FAIL] lfsr_3bits, errors = %0d",errors); $fdisplay(log_fd,"[FAIL] lfsr_3bits, errors = %0d",errors); $fdisplay(result_fd,"fail"); end
        $display("##END_STUDENT_CAN_SEE"); $fdisplay(log_fd,"##END_STUDENT_CAN_SEE");
        $fclose(log_fd); $fclose(result_fd); $finish;
    end
endmodule

fpga_lab/Lab06_lfsr_3bits/golden/golden_wave.vcd
$date
	Mon May 11 09:39:56 2026
$end
$version
	Icarus Verilog
$end
$timescale
	1ps
$end
$scope module tb_lfsr_3bits $end
$var wire 3 ! lfsr_out [2:0] $end
$var reg 1 " clk $end
$var reg 1 # en $end
$var reg 1 $ rst $end
$var integer 32 % errors [31:0] $end
$var integer 32 & i [31:0] $end
$var integer 32 ' log_fd [31:0] $end
$var integer 32 ( pattern [31:0] $end
$var integer 32 ) result_fd [31:0] $end
$scope module dut $end
$var wire 1 " clk $end
$var wire 1 # en $end
$var wire 3 * lfsr_out [2:0] $end
$var wire 1 $ rst $end
$var parameter 3 + LFSR_INIT $end
$var reg 3 , lfsr [2:0] $end
$var reg 3 - lfsr_nxt [2:0] $end
$upscope $end
$scope task check $end
$var reg 3 . expected [2:0] $end
$var reg 256 / name [255:0] $end
$upscope $end
$upscope $end
$enddefinitions $end
$comment Show the parameter values. $end
$dumpall
b101 +
$end
#0
$dumpvars
bx /
bx .
b101 -
b101 ,
b101 *
b10000000000000000000000000000100 )
b0 (
b10000000000000000000000000000011 '
bx &
b0 %
1$
0#
0"
b101 !
$end
#5000
1"
#10000
0"
#15000
1"
#20000
b1 (
b101 .
b1110010011001010111001101100101011101000010000001110010011001010110110001100101011000010111001101100101 /
0$
0"
#25000
1"
#30000
b10 -
b1 &
1#
0"
#35000
b100 -
b10 !
b10 *
b10 ,
b10 (
b10 .
b1101100011001100111001101110010001000000111001101100101011100010111010101100101011011100110001101100101 /
1"
#36000
b10 &
#40000
0"
#45000
b1 -
b100 !
b100 *
b100 ,
b11 (
b100 .
1"
#46000
b11 &
#50000
0"
#55000
b11 -
b1 !
b1 *
b1 ,
b100 (
b1 .
1"
#56000
b100 &
#60000
0"
#65000
b111 -
b11 !
b11 *
b11 ,
b101 (
b11 .
1"
#66000
b101 &
#70000
0"
#75000
b110 -
b111 !
b111 *
b111 ,
b110 (
b111 .
1"
#76000
b110 &
#80000
0"
#85000
b101 -
b110 !
b110 *
b110 ,
b111 (
b110 .
1"
#86000
b111 &
#90000
b110 -
0#
0"
#95000
b1000 (
b110100001101111011011000110010000100000011101110110100001100101011011100010000001100101011011100011110100110000 /
1"
