practice/Lab06_ALUComp/golden/alu_comp.v
module alu_comp (
    input         clk,
    input         rst_n,

    input         wen,
    input  [1:0]  waddr,
    input  [7:0]  wdata,

    input  [1:0]  src_a,
    input  [1:0]  src_b,
    input  [1:0]  op,

    output [7:0]  reg0,
    output [7:0]  reg1,
    output [7:0]  reg2,
    output [7:0]  reg3,
    output reg [15:0] result
);

localparam OP_ADD  = 2'd0;
localparam OP_SUB  = 2'd1;
localparam OP_MUL  = 2'd2;
localparam OP_DIV2 = 2'd3;

reg [7:0] regs [0:3];
reg [7:0] a_val;
reg [7:0] b_val;

// ** register set write **
// Four 8-bit registers can be updated by wen, waddr, and wdata.
integer i;
always @(posedge clk or negedge rst_n) begin
    if (!rst_n) begin
        for (i = 0; i < 4; i = i + 1) begin
            regs[i] <= 8'd0;
        end
    end
    else if (wen) begin
        regs[waddr] <= wdata;
    end
end

// ** expose all registers for direct read **
assign reg0 = regs[0];
assign reg1 = regs[1];
assign reg2 = regs[2];
assign reg3 = regs[3];

// ** register source selection **
always @(*) begin
    a_val = regs[src_a];
    b_val = regs[src_b];
end

// ** ALU operations **
// ADD/SUB/MUL use src_a and src_b. DIV2 uses only src_a.
always @(*) begin
    case (op)
        OP_ADD: begin
            result = a_val + b_val;
        end
        OP_SUB: begin
            result = a_val - b_val;
        end
        OP_MUL: begin
            result = a_val * b_val;
        end
        OP_DIV2: begin
            result = a_val >> 1;
        end
        default: begin
            result = 16'd0;
        end
    endcase
end

endmodule

advanced/Lab00_ALUcomp/tb.v
`timescale 1ns/1ps
module tb_alu_comp;
    reg clk, rst_n, wen;
    reg [1:0] waddr, src_a, src_b, op;
    reg [7:0] wdata;
    wire [7:0] reg0, reg1, reg2, reg3;
    wire [15:0] result;
    integer errors, log_fd, result_fd, pattern;

    alu_comp dut (
        .clk(clk), .rst_n(rst_n), .wen(wen), .waddr(waddr), .wdata(wdata),
        .src_a(src_a), .src_b(src_b), .op(op),
        .reg0(reg0), .reg1(reg1), .reg2(reg2), .reg3(reg3), .result(result)
    );
    initial begin clk = 0; forever #5 clk = ~clk; end

    function [7:0] reg_value;
        input [1:0] sel;
        begin
            case (sel)
                2'd0: reg_value = reg0;
                2'd1: reg_value = reg1;
                2'd2: reg_value = reg2;
                default: reg_value = reg3;
            endcase
        end
    endfunction

    task write_reg;
        input [1:0] addr;
        input [7:0] data;
        begin
            @(negedge clk); waddr = addr; wdata = data; wen = 1'b1;
            @(posedge clk);
            @(negedge clk); wen = 1'b0; wdata = 8'd0; waddr = 2'd0;
            #1;
        end
    endtask

    task check_alu;
        input [8*16-1:0] name;
        input [1:0] a_sel, b_sel, op_sel;
        input [15:0] expected;
        reg [7:0] a_value, b_value;
        begin
            @(negedge clk); src_a = a_sel; src_b = b_sel; op = op_sel;
            a_value = reg_value(a_sel);
            b_value = reg_value(b_sel);
            pattern = pattern + 1;
            #1;
            if (result !== expected) begin
                if (errors == 0) $display("[ERROR] pattern %0d (%0s): op=%0d src_a=r%0d(%0d) src_b=r%0d(%0d) expected=%0d got=%0d", pattern, name, op_sel, a_sel, a_value, b_sel, b_value, expected, result);
                if (errors == 0) $fdisplay(log_fd, "[ERROR] pattern %0d (%0s): op=%0d src_a=r%0d(%0d) src_b=r%0d(%0d) expected=%0d got=%0d", pattern, name, op_sel, a_sel, a_value, b_sel, b_value, expected, result);
                errors = errors + 1;
            end
        end
    endtask

    initial begin
        log_fd = $fopen("sim/log.txt", "w");
        result_fd = $fopen("sim/result.txt", "w");
        $dumpfile("sim/wave.vcd");
        $dumpvars(0, tb_alu_comp);
        $display("##SEC_STUDENT_CAN_SEE");
        $fdisplay(log_fd, "##SEC_STUDENT_CAN_SEE");
        // GOLDEN_CASE_SUMMARY_BEGIN
        $display("[CASE 1] checks register write/readback");
        $fdisplay(log_fd,"[CASE 1] checks register write/readback");
        $display("[CASE 2-5] checks each ALU operation");
        $fdisplay(log_fd,"[CASE 2-5] checks each ALU operation");
        // GOLDEN_CASE_SUMMARY_END


        errors = 0; pattern = 0; rst_n = 0; wen = 0; waddr = 0; wdata = 0; src_a = 0; src_b = 0; op = 0;
        repeat (2) @(posedge clk); @(negedge clk); rst_n = 1; #1;
        write_reg(2'd0, 8'd20);
        write_reg(2'd1, 8'd7);
        write_reg(2'd2, 8'd3);
        write_reg(2'd3, 8'd12);
        pattern = pattern + 1;
        if (reg0 !== 8'd20 || reg1 !== 8'd7 || reg2 !== 8'd3 || reg3 !== 8'd12) begin
            if (errors == 0) $display("[ERROR] pattern %0d (register write/readback): expected r0=20 r1=7 r2=3 r3=12 got r0=%0d r1=%0d r2=%0d r3=%0d", pattern, reg0, reg1, reg2, reg3);
            if (errors == 0) $fdisplay(log_fd, "[ERROR] pattern %0d (register write/readback): expected r0=20 r1=7 r2=3 r3=12 got r0=%0d r1=%0d r2=%0d r3=%0d", pattern, reg0, reg1, reg2, reg3);
            errors = errors + 1;
        end
        check_alu("add",  2'd0, 2'd1, 2'd0, 16'd27);
        check_alu("sub",  2'd0, 2'd1, 2'd1, 16'd13);
        check_alu("mul",  2'd1, 2'd2, 2'd2, 16'd21);
        check_alu("div2", 2'd3, 2'd0, 2'd3, 16'd6);
        if (errors == 0) begin
            $display("[PASS] alu_comp");
            $fdisplay(log_fd, "[PASS] alu_comp");
            $fdisplay(result_fd, "pass");
        end else begin
            $display("[FAIL] alu_comp, errors = %0d", errors);
            $fdisplay(log_fd, "[FAIL] alu_comp, errors = %0d", errors);
            $fdisplay(result_fd, "fail");
        end
        $display("##END_STUDENT_CAN_SEE");
        $fdisplay(log_fd, "##END_STUDENT_CAN_SEE");
        $fclose(log_fd); $fclose(result_fd);
        $finish;
    end
endmodule

practice/Lab06_ALUComp/golden/golden_wave.vcd
$date
	Mon May 11 15:57:59 2026
$end
$version
	Icarus Verilog
$end
$timescale
	1ps
$end
$scope module tb_alu_comp $end
$var wire 16 ! result [15:0] $end
$var wire 8 " reg3 [7:0] $end
$var wire 8 # reg2 [7:0] $end
$var wire 8 $ reg1 [7:0] $end
$var wire 8 % reg0 [7:0] $end
$var reg 1 & clk $end
$var reg 2 ' op [1:0] $end
$var reg 1 ( rst_n $end
$var reg 2 ) src_a [1:0] $end
$var reg 2 * src_b [1:0] $end
$var reg 2 + waddr [1:0] $end
$var reg 8 , wdata [7:0] $end
$var reg 1 - wen $end
$var integer 32 . errors [31:0] $end
$var integer 32 / log_fd [31:0] $end
$var integer 32 0 pattern [31:0] $end
$var integer 32 1 result_fd [31:0] $end
$scope function reg_value $end
$var reg 2 2 sel [1:0] $end
$upscope $end
$scope module dut $end
$var wire 1 & clk $end
$var wire 2 3 op [1:0] $end
$var wire 8 4 reg0 [7:0] $end
$var wire 8 5 reg1 [7:0] $end
$var wire 8 6 reg2 [7:0] $end
$var wire 8 7 reg3 [7:0] $end
$var wire 1 ( rst_n $end
$var wire 2 8 src_a [1:0] $end
$var wire 2 9 src_b [1:0] $end
$var wire 2 : waddr [1:0] $end
$var wire 8 ; wdata [7:0] $end
$var wire 1 - wen $end
$var parameter 2 < OP_ADD $end
$var parameter 2 = OP_DIV2 $end
$var parameter 2 > OP_MUL $end
$var parameter 2 ? OP_SUB $end
$var reg 8 @ a_val [7:0] $end
$var reg 8 A b_val [7:0] $end
$var reg 16 B result [15:0] $end
$var integer 32 C i [31:0] $end
$upscope $end
$scope task check_alu $end
$var reg 2 D a_sel [1:0] $end
$var reg 8 E a_value [7:0] $end
$var reg 2 F b_sel [1:0] $end
$var reg 8 G b_value [7:0] $end
$var reg 16 H expected [15:0] $end
$var reg 128 I name [127:0] $end
$var reg 2 J op_sel [1:0] $end
$upscope $end
$scope task write_reg $end
$var reg 2 K addr [1:0] $end
$var reg 8 L data [7:0] $end
$upscope $end
$upscope $end
$enddefinitions $end
$comment Show the parameter values. $end
$dumpall
b1 ?
b10 >
b11 =
b0 <
$end
#0
$dumpvars
bx L
bx K
bx J
bx I
bx H
bx G
bx F
bx E
bx D
b100 C
b0 B
b0 A
b0 @
b0 ;
b0 :
b0 9
b0 8
b0 7
b0 6
b0 5
b0 4
b0 3
bx 2
b10000000000000000000000000000100 1
b0 0
b10000000000000000000000000000011 /
b0 .
0-
b0 ,
b0 +
b0 *
b0 )
0(
b0 '
0&
b0 %
b0 $
b0 #
b0 "
b0 !
$end
#5000
b100 C
1&
#10000
0&
#15000
b100 C
1&
#20000
1(
0&
#21000
b10100 L
b0 K
#25000
1&
#30000
1-
b10100 ,
b10100 ;
0&
#35000
b101000 !
b101000 B
b10100 A
b10100 @
b10100 %
b10100 4
1&
#40000
b0 ,
b0 ;
0-
0&
#41000
b111 L
b1 K
#45000
1&
#50000
1-
b111 ,
b111 ;
b1 +
b1 :
0&
#55000
b111 $
b111 5
1&
#60000
b0 +
b0 :
b0 ,
b0 ;
0-
0&
#61000
b11 L
b10 K
#65000
1&
#70000
1-
b11 ,
b11 ;
b10 +
b10 :
0&
#75000
b11 #
b11 6
1&
#80000
b0 +
b0 :
b0 ,
b0 ;
0-
0&
#81000
b1100 L
b11 K
#85000
1&
#90000
1-
b1100 ,
b1100 ;
b11 +
b11 :
0&
#95000
b1100 "
b1100 7
1&
#100000
b0 +
b0 :
b0 ,
b0 ;
0-
0&
#101000
b11011 H
b0 J
b1 F
b0 D
b11000010110010001100100 I
b1 0
#105000
1&
#110000
b11011 !
b11011 B
b111 A
b10 0
b111 G
b10100 E
b1 2
b1 *
b1 9
0&
#111000
b1101 H
b1 J
b11100110111010101100010 I
#115000
1&
#120000
b1101 !
b1101 B
b11 0
b1 2
b1 '
b1 3
0&
#121000
b10101 H
b10 J
b10 F
b1 D
b11011010111010101101100 I
#125000
1&
#130000
b10101 !
b10101 B
b11 A
b111 @
b100 0
b11 G
b10 2
b111 E
b10 '
b10 3
b10 *
b10 9
b1 )
b1 8
0&
#131000
b110 H
b11 J
b0 F
b11 D
b1100100011010010111011000110010 I
#135000
1&
#140000
b110 !
b110 B
b10100 A
b1100 @
b101 0
b10100 G
b1100 E
b0 2
b11 '
b11 3
b0 *
b0 9
b11 )
b11 8
0&
