tutorial/Ex07_advanced_seq/vending_machine.v
module Ex07_VendingMachine (
    input        clk,
    input        rst_n,
    input        coin_5,
    input        coin_10,
    output reg   vend,
    output reg   change_5,
    output reg [3:0] amount
);

localparam S0  = 2'd0;
localparam S5  = 2'd1;
localparam S10 = 2'd2;

reg [1:0] S, S_nxt;

reg       vend_nxt;
reg       change_5_nxt;
reg [3:0] amount_nxt;

// ** state and output register **
always @(posedge clk or negedge rst_n) begin
    if (!rst_n) begin
        S        <= S0;
        vend     <= 1'b0;
        change_5 <= 1'b0;
        amount   <= 4'd0;
    end else begin
        S        <= S_nxt;
        vend     <= vend_nxt;
        change_5 <= change_5_nxt;
        amount   <= amount_nxt;
    end
end

// ** next state and next output logic **
// Price is 15. The machine accepts 5 and 10 coins.
// coin_10 has higher priority than coin_5.
always @(*) begin
    S_nxt        = S;
    vend_nxt     = 1'b0;
    change_5_nxt = 1'b0;

    case (S)
        S0: begin
            if (coin_10) begin
                S_nxt = S10;
            end else if (coin_5) begin
                S_nxt = S5;
            end
        end

        S5: begin
            if (coin_10) begin
                // 5 + 10 = 15
                vend_nxt = 1'b1;
                S_nxt    = S0;
            end else if (coin_5) begin
                // 5 + 5 = 10
                S_nxt = S10;
            end
        end

        S10: begin
            if (coin_10) begin
                // 10 + 10 = 20, return 5
                vend_nxt     = 1'b1;
                change_5_nxt = 1'b1;
                S_nxt        = S0;
            end else if (coin_5) begin
                // 10 + 5 = 15
                vend_nxt = 1'b1;
                S_nxt    = S0;
            end
        end

        default: begin
            S_nxt = S0;
        end
    endcase

    case (S_nxt)
        S0:      amount_nxt = 4'd0;
        S5:      amount_nxt = 4'd5;
        S10:     amount_nxt = 4'd10;
        default: amount_nxt = 4'd0;
    endcase
end

endmodule

tutorial/Ex07_advanced_seq/hello_world.v
module Ex07_HelloWorld (
    input        clk,
    input        rst_n,
    output reg [7:0] char
);

localparam MSG_LEN = 14;

reg [3:0] index;
reg [7:0] message [0:MSG_LEN-1];

// ** Array as a small ROM **
initial begin
    message[0]  = 8'h48; // H
    message[1]  = 8'h65; // e
    message[2]  = 8'h6c; // l
    message[3]  = 8'h6c; // l
    message[4]  = 8'h6f; // o
    message[5]  = 8'h20; // space
    message[6]  = 8'h57; // W
    message[7]  = 8'h6f; // o
    message[8]  = 8'h72; // r
    message[9]  = 8'h6c; // l
    message[10] = 8'h64; // d
    message[11] = 8'h20; // space
    message[12] = 8'h21; // !
    message[13] = 8'h20; // space
end

// ** sequential index counter **
// index advances every cycle and wraps around
always @(posedge clk or negedge rst_n) begin
    if (!rst_n) begin
        index <= 4'd0;
    end else begin
        if (index == MSG_LEN - 1) begin
            index <= 4'd0;
        end else begin
            index <= index + 4'd1;
        end
    end
end

// ** array read **
// char is the ASCII character selected by the current index
always @(*) begin
    char = message[index];
end

endmodule

tutorial/Ex07_advanced_seq/tb.v
`timescale 1ns/1ps
module tb_ex06_advanced_seq;
    reg clk, rst_n;
    reg coin_5, coin_10;
    wire [7:0] char;
    wire vend, change_5;
    wire [3:0] amount;
    integer errors, log_fd, result_fd, pattern;

    Ex07_HelloWorld u_hello(.clk(clk), .rst_n(rst_n), .char(char));
    Ex07_VendingMachine u_vending(.clk(clk), .rst_n(rst_n), .coin_5(coin_5), .coin_10(coin_10), .vend(vend), .change_5(change_5), .amount(amount));

    initial begin clk = 0; forever #5 clk = ~clk; end

    task check_hello;
        input [8*16-1:0] name;
        input [7:0] expected;
        begin
            pattern = pattern + 1;
            #1;
            if (char !== expected) begin
                $display("[ERROR] pattern %0d (%0s): expected char=%h got=%h", pattern, name, expected, char);
                $fdisplay(log_fd,"[ERROR] pattern %0d (%0s): expected char=%h got=%h", pattern, name, expected, char);
                errors = errors + 1;
            end
        end
    endtask

    task set_coins;
        input c5;
        input c10;
        begin
            @(negedge clk); coin_5 = c5; coin_10 = c10;
        end
    endtask

    task check_vending;
        input [8*24-1:0] name;
        input exp_vend;
        input exp_change_5;
        input [3:0] exp_amount;
        begin
            pattern = pattern + 1;
            #1;
            if (vend !== exp_vend || change_5 !== exp_change_5 || amount !== exp_amount) begin
                $display("[ERROR] pattern %0d (%0s): expected vend=%b change=%b amount=%0d got vend=%b change=%b amount=%0d", pattern, name, exp_vend, exp_change_5, exp_amount, vend, change_5, amount);
                $fdisplay(log_fd,"[ERROR] pattern %0d (%0s): expected vend=%b change=%b amount=%0d got vend=%b change=%b amount=%0d", pattern, name, exp_vend, exp_change_5, exp_amount, vend, change_5, amount);
                errors = errors + 1;
            end
        end
    endtask

    initial begin
        log_fd=$fopen("sim/log.txt","w"); result_fd=$fopen("sim/result.txt","w");
        $dumpfile("sim/wave.vcd"); $dumpvars(0,tb_ex06_advanced_seq);
        $display("##SEC_STUDENT_CAN_SEE"); $fdisplay(log_fd,"##SEC_STUDENT_CAN_SEE");
        errors=0; pattern=0; rst_n=0; coin_5=0; coin_10=0;
        repeat(2) @(posedge clk); @(negedge clk); rst_n=1;

        #1; check_hello("H", 8'h48);
        @(posedge clk); check_hello("e", 8'h65);
        @(posedge clk); check_hello("l", 8'h6c);
        @(posedge clk); check_hello("l", 8'h6c);
        @(posedge clk); check_hello("o", 8'h6f);

        set_coins(1'b1, 1'b0); @(posedge clk); check_vending("insert 5", 1'b0, 1'b0, 4'd5);
        set_coins(1'b0, 1'b1); @(posedge clk); check_vending("5 plus 10 vend", 1'b1, 1'b0, 4'd0);
        set_coins(1'b0, 1'b0); @(posedge clk); check_vending("idle after vend", 1'b0, 1'b0, 4'd0);
        set_coins(1'b0, 1'b1); @(posedge clk); check_vending("insert 10", 1'b0, 1'b0, 4'd10);
        set_coins(1'b0, 1'b1); @(posedge clk); check_vending("10 plus 10 vend change", 1'b1, 1'b1, 4'd0);
        set_coins(1'b0, 1'b0); @(posedge clk); check_vending("idle final", 1'b0, 1'b0, 4'd0);

        if(errors==0) begin $display("[PASS] Ex07_advanced_seq"); $fdisplay(log_fd,"[PASS] Ex07_advanced_seq"); $fdisplay(result_fd,"pass"); end
        else begin $display("[FAIL] Ex07_advanced_seq, errors = %0d", errors); $fdisplay(log_fd,"[FAIL] Ex07_advanced_seq, errors = %0d", errors); $fdisplay(result_fd,"fail"); end
        $display("##END_STUDENT_CAN_SEE"); $fdisplay(log_fd,"##END_STUDENT_CAN_SEE");
        $fclose(log_fd); $fclose(result_fd); $finish;
    end
endmodule

tutorial/Ex07_advanced_seq/sim/wave.vcd
$date
	Mon May 11 16:48:15 2026
$end
$version
	Icarus Verilog
$end
$timescale
	1ps
$end
$scope module tb_ex06_advanced_seq $end
$var wire 1 ! vend $end
$var wire 8 " char [7:0] $end
$var wire 1 # change_5 $end
$var wire 4 $ amount [3:0] $end
$var reg 1 % clk $end
$var reg 1 & coin_10 $end
$var reg 1 ' coin_5 $end
$var reg 1 ( rst_n $end
$var integer 32 ) errors [31:0] $end
$var integer 32 * log_fd [31:0] $end
$var integer 32 + pattern [31:0] $end
$var integer 32 , result_fd [31:0] $end
$scope module u_hello $end
$var wire 1 % clk $end
$var wire 1 ( rst_n $end
$var parameter 32 - MSG_LEN $end
$var reg 8 . char [7:0] $end
$var reg 4 / index [3:0] $end
$upscope $end
$scope module u_vending $end
$var wire 1 % clk $end
$var wire 1 & coin_10 $end
$var wire 1 ' coin_5 $end
$var wire 1 ( rst_n $end
$var parameter 2 0 S0 $end
$var parameter 2 1 S10 $end
$var parameter 2 2 S5 $end
$var reg 2 3 S [1:0] $end
$var reg 2 4 S_nxt [1:0] $end
$var reg 4 5 amount [3:0] $end
$var reg 4 6 amount_nxt [3:0] $end
$var reg 1 # change_5 $end
$var reg 1 7 change_5_nxt $end
$var reg 1 ! vend $end
$var reg 1 8 vend_nxt $end
$upscope $end
$scope task check_hello $end
$var reg 8 9 expected [7:0] $end
$var reg 128 : name [127:0] $end
$upscope $end
$scope task check_vending $end
$var reg 4 ; exp_amount [3:0] $end
$var reg 1 < exp_change_5 $end
$var reg 1 = exp_vend $end
$var reg 192 > name [191:0] $end
$upscope $end
$scope task set_coins $end
$var reg 1 ? c10 $end
$var reg 1 @ c5 $end
$upscope $end
$upscope $end
$enddefinitions $end
$comment Show the parameter values. $end
$dumpall
b1 2
b10 1
b0 0
b1110 -
$end
#0
$dumpvars
x@
x?
bx >
x=
x<
bx ;
bx :
bx 9
08
07
b0 6
b0 5
b0 4
b0 3
b0 /
b1001000 .
b10000000000000000000000000000100 ,
b0 +
b10000000000000000000000000000011 *
b0 )
0(
0'
0&
0%
b0 $
0#
b1001000 "
0!
$end
#5000
1%
#10000
0%
#15000
1%
#20000
1(
0%
#21000
b1 +
b1001000 9
b1001000 :
#25000
b1100101 "
b1100101 .
b1 /
b10 +
b1100101 9
b1100101 :
1%
#30000
0%
#35000
b1101100 "
b1101100 .
b10 /
b11 +
b1101100 9
b1101100 :
1%
#40000
0%
#45000
b11 /
b100 +
1%
#50000
0%
#55000
b1101111 "
b1101111 .
b100 /
b101 +
b1101111 9
b1101111 :
1%
#56000
0?
1@
#60000
b101 6
b1 4
1'
0%
#65000
b1010 6
b10 4
b100000 "
b100000 .
b101 $
b101 5
b1 3
b101 /
b110 +
b101 ;
0<
0=
b110100101101110011100110110010101110010011101000010000000110101 >
1%
#66000
1?
0@
#70000
b0 6
18
b0 4
1&
0'
0%
#75000
b1010111 "
b1010111 .
b1010 6
b10 4
08
b110 /
b0 $
b0 5
1!
b0 3
b111 +
b0 ;
1=
b11010100100000011100000110110001110101011100110010000000110001001100000010000001110110011001010110111001100100 >
1%
#76000
0?
#80000
b0 6
b0 4
0&
0%
#85000
b1101111 "
b1101111 .
0!
b111 /
b1000 +
0=
b11010010110010001101100011001010010000001100001011001100111010001100101011100100010000001110110011001010110111001100100 >
1%
#86000
1?
#90000
b1010 6
b10 4
1&
0%
#95000
b1110010 "
b1110010 .
b0 6
b0 4
17
18
b1000 /
b1010 $
b1010 5
b10 3
b1001 +
b1010 ;
b11010010110111001110011011001010111001001110100001000000011000100110000 >
1%
#100000
0%
#105000
b1010 6
b10 4
07
08
b1101100 "
b1101100 .
b0 $
b0 5
1#
1!
b0 3
b1001 /
b1010 +
b0 ;
1<
1=
b110001001100000010000001110000011011000111010101110011001000000011000100110000001000000111011001100101011011100110010000100000011000110110100001100001011011100110011101100101 >
1%
#106000
0?
#110000
b0 6
b0 4
0&
0%
#115000
b1100100 "
b1100100 .
b1010 /
0#
0!
b1011 +
0<
0=
b1101001011001000110110001100101001000000110011001101001011011100110000101101100 >
1%
