fpga_lab/Lab04_lfsr_4bits/lfsr_4bits.v
module lfsr_4bits (
	input        clk,
	input        rst,
	input        en,
	output [3:0] lfsr_out
);

parameter LFSR_INIT = 4'b1011;
reg [3:0] lfsr, lfsr_nxt;

always @(posedge clk or posedge rst) begin
    if (rst) begin
        lfsr <= LFSR_INIT;
    end else begin
        lfsr <= lfsr_nxt;
    end
end

always @(*) begin
    if (en) begin
        // LFSR logic: shift left and feed in the XOR of the first and last bits
        lfsr_nxt = {lfsr[...], lfsr[...] ^ lfsr[...]}; // To be completed
    end else begin
        lfsr_nxt = lfsr;
    end
end

assign lfsr_out = lfsr;

endmodule

fpga_lab/Lab06_lfsr_4bits/tb.v
`timescale 1ns/1ps
module tb_lfsr_4bits;
    reg clk,rst,en;
    wire [3:0] lfsr_out;
    integer errors,log_fd,result_fd,i,pattern;
    reg [3:0] exp [0:8];

    lfsr_4bits dut(.clk(clk),.rst(rst),.en(en),.lfsr_out(lfsr_out));
    initial begin clk=0; forever #5 clk=~clk; end
    initial begin
        exp[0]=4'b1011; exp[1]=4'b0110; exp[2]=4'b1100; exp[3]=4'b1001; exp[4]=4'b0010;
        exp[5]=4'b0100; exp[6]=4'b1000; exp[7]=4'b0001; exp[8]=4'b0011;
    end

    task check;
        input [8*32-1:0] name;
        input [3:0] expected;
        begin
            pattern = pattern + 1;
            #1;
            if(lfsr_out!==expected) begin
                if (errors == 0) $display("[ERROR] pattern %0d (%0s): en=%b expected lfsr_out=%b got=%b", pattern, name, en, expected, lfsr_out);
                if (errors == 0) $fdisplay(log_fd,"[ERROR] pattern %0d (%0s): en=%b expected lfsr_out=%b got=%b", pattern, name, en, expected, lfsr_out);
                errors=errors+1;
            end
        end
    endtask

    initial begin
        log_fd=$fopen("sim/log.txt","w"); result_fd=$fopen("sim/result.txt","w");
        $dumpfile("sim/wave.vcd"); $dumpvars(0,tb_lfsr_4bits);
        $display("##SEC_STUDENT_CAN_SEE"); $fdisplay(log_fd,"##SEC_STUDENT_CAN_SEE");
        // GOLDEN_CASE_SUMMARY_BEGIN
        $display("[CASE 1] checks reset seed");
        $fdisplay(log_fd,"[CASE 1] checks reset seed");
        $display("[CASE 2-9] checks enabled 4-bit LFSR sequence");
        $fdisplay(log_fd,"[CASE 2-9] checks enabled 4-bit LFSR sequence");
        $display("[CASE 10] checks hold when disabled");
        $fdisplay(log_fd,"[CASE 10] checks hold when disabled");
        // GOLDEN_CASE_SUMMARY_END


        errors=0; pattern=0; rst=1; en=0;
        repeat(2) @(posedge clk); @(negedge clk); rst=0; check("reset release", exp[0]);
        @(negedge clk); en=1;
        for(i=1;i<=8;i=i+1) begin @(posedge clk); check("lfsr sequence", exp[i]); end
        @(negedge clk); en=0; @(posedge clk); check("hold when en=0", exp[8]);
        if(errors==0) begin $display("[PASS] lfsr_4bits"); $fdisplay(log_fd,"[PASS] lfsr_4bits"); $fdisplay(result_fd,"pass"); end
        else begin $display("[FAIL] lfsr_4bits, errors = %0d",errors); $fdisplay(log_fd,"[FAIL] lfsr_4bits, errors = %0d",errors); $fdisplay(result_fd,"fail"); end
        $display("##END_STUDENT_CAN_SEE"); $fdisplay(log_fd,"##END_STUDENT_CAN_SEE");
        $fclose(log_fd); $fclose(result_fd); $finish;
    end
endmodule

fpga_lab/Lab04_lfsr_4bits/golden/golden_wave.vcd
$date
	Fri Jun 26 12:53:18 2026
$end
$version
	Icarus Verilog
$end
$timescale
	1ps
$end
$scope module tb_lfsr_4bits $end
$var wire 4 ! lfsr_out [3:0] $end
$var reg 1 " clk $end
$var reg 1 # en $end
$var reg 1 $ rst $end
$var integer 32 % errors [31:0] $end
$var integer 32 & i [31:0] $end
$var integer 32 ' log_fd [31:0] $end
$var integer 32 ( pattern [31:0] $end
$var integer 32 ) result_fd [31:0] $end
$scope module dut $end
$var wire 1 " clk $end
$var wire 1 # en $end
$var wire 4 * lfsr_out [3:0] $end
$var wire 1 $ rst $end
$var parameter 4 + LFSR_INIT $end
$var reg 4 , lfsr [3:0] $end
$var reg 4 - lfsr_nxt [3:0] $end
$upscope $end
$scope task check $end
$var reg 4 . expected [3:0] $end
$var reg 256 / name [255:0] $end
$upscope $end
$upscope $end
$enddefinitions $end
$comment Show the parameter values. $end
$dumpall
b1011 +
$end
#0
$dumpvars
bx /
bx .
b1011 -
b1011 ,
b1011 *
b10000000000000000000000000000100 )
b0 (
b10000000000000000000000000000011 '
bx &
b0 %
1$
0#
0"
b1011 !
$end
#5000
1"
#10000
0"
#15000
1"
#20000
b1 (
b1011 .
b1110010011001010111001101100101011101000010000001110010011001010110110001100101011000010111001101100101 /
0$
0"
#25000
1"
#30000
b110 -
b1 &
1#
0"
#35000
b1100 -
b110 !
b110 *
b110 ,
b10 (
b110 .
b1101100011001100111001101110010001000000111001101100101011100010111010101100101011011100110001101100101 /
1"
#36000
b10 &
#40000
0"
#45000
b1001 -
b1100 !
b1100 *
b1100 ,
b11 (
b1100 .
1"
#46000
b11 &
#50000
0"
#55000
b10 -
b1001 !
b1001 *
b1001 ,
b100 (
b1001 .
1"
#56000
b100 &
#60000
0"
#65000
b100 -
b10 !
b10 *
b10 ,
b101 (
b10 .
1"
#66000
b101 &
#70000
0"
#75000
b1000 -
b100 !
b100 *
b100 ,
b110 (
b100 .
1"
#76000
b110 &
#80000
0"
#85000
b1 -
b1000 !
b1000 *
b1000 ,
b111 (
b1000 .
1"
#86000
b111 &
#90000
0"
#95000
b11 -
b1 !
b1 *
b1 ,
b1000 (
b1 .
1"
#96000
b1000 &
#100000
0"
#105000
b111 -
b11 !
b11 *
b11 ,
b1001 (
b11 .
1"
#106000
b1001 &
#110000
b11 -
0#
0"
#115000
b1010 (
b110100001101111011011000110010000100000011101110110100001100101011011100010000001100101011011100011110100110000 /
1"
