practice/Lab06_traffic_light/traffic_light.v
module traffic_light (
    input        clk,
    input        rst_n,
    output reg   red,
    output reg   yellow,
    output reg   green,
    output reg [3:0] timer
);

localparam S_GREEN  = 2'd0;
localparam S_YELLOW = 2'd1;
localparam S_RED    = 2'd2;

localparam GREEN_TIME  = 4'd5;
localparam YELLOW_TIME = 4'd2;
localparam RED_TIME    = 4'd5;

reg [1:0] S, S_nxt;
reg [3:0] timer_nxt;

// ** state register and timer register **
always @(posedge clk or negedge rst_n) begin
    if (!rst_n) begin
        S     <= S_GREEN;
        timer <= 4'd0;
    end else begin
        S     <= S_nxt;
        timer <= timer_nxt;
    end
end

// ** state transition and timer update **
always @(*) begin
    // default behavior:
    // stay in the same state and count up
    S_nxt     = S;
    timer_nxt = timer + 4'd1;

    case (S)
        S_GREEN: begin
            if (timer == GREEN_TIME - 1) begin
                S_nxt     = S_YELLOW;
                timer_nxt = 4'd0;
            end
        end

        S_YELLOW: begin
            ...; // To be completed
        end

        S_RED: begin
            ...; // To be completed
        end

        default: begin
            S_nxt     = S_GREEN;
            timer_nxt = 4'd0;
        end
    endcase
end

// ** output decoder **
always @(*) begin
    red    = 1'b0;
    yellow = 1'b0;
    green  = 1'b0;

    case (S)
        S_GREEN:  ...; // To be completed
        S_YELLOW: ...; // To be completed
        S_RED:    ...; // To be completed
        default:  green  = 1'b1;
    endcase
end

endmodule

practice/Lab04_traffic_light/tb.v
`timescale 1ns/1ps
module tb_traffic_light;
    reg clk, rst_n;
    wire red, yellow, green;
    wire [3:0] timer;
    integer errors, log_fd, result_fd, cycle;

    traffic_light dut (.clk(clk), .rst_n(rst_n), .red(red), .yellow(yellow), .green(green), .timer(timer));

    initial begin clk = 0; forever #5 clk = ~clk; end

    task check;
        input exp_r, exp_y, exp_g;
        input [3:0] exp_timer;
        begin
            #1;
            if (red !== exp_r || yellow !== exp_y || green !== exp_g || timer !== exp_timer) begin
                if (errors == 0) $display("[ERROR] pattern cycle=%0d: expected r/y/g=%b%b%b timer=%0d got r/y/g=%b%b%b timer=%0d", cycle, exp_r, exp_y, exp_g, exp_timer, red, yellow, green, timer);
                if (errors == 0) $fdisplay(log_fd, "[ERROR] pattern cycle=%0d: expected r/y/g=%b%b%b timer=%0d got r/y/g=%b%b%b timer=%0d", cycle, exp_r, exp_y, exp_g, exp_timer, red, yellow, green, timer);
                errors = errors + 1;
            end
            cycle = cycle + 1;
        end
    endtask

    initial begin
        log_fd = $fopen("sim/log.txt", "w");
        result_fd = $fopen("sim/result.txt", "w");
        $dumpfile("sim/wave.vcd");
        $dumpvars(0, tb_traffic_light);
        $display("##SEC_STUDENT_CAN_SEE");
        $fdisplay(log_fd, "##SEC_STUDENT_CAN_SEE");
        // GOLDEN_CASE_SUMMARY_BEGIN
        $display("[CASE 1-5] checks green phase");
        $fdisplay(log_fd,"[CASE 1-5] checks green phase");
        $display("[CASE 6-7] checks yellow phase");
        $fdisplay(log_fd,"[CASE 6-7] checks yellow phase");
        $display("[CASE 8-12] checks red phase");
        $fdisplay(log_fd,"[CASE 8-12] checks red phase");
        $display("[CASE 13] checks wraparound");
        $fdisplay(log_fd,"[CASE 13] checks wraparound");
        // GOLDEN_CASE_SUMMARY_END


        errors = 0; cycle = 0; rst_n = 0;
        repeat (2) @(posedge clk);
        @(negedge clk); rst_n = 1;
        check(1'b0, 1'b0, 1'b1, 4'd0);
        @(posedge clk); check(1'b0, 1'b0, 1'b1, 4'd1);
        @(posedge clk); check(1'b0, 1'b0, 1'b1, 4'd2);
        @(posedge clk); check(1'b0, 1'b0, 1'b1, 4'd3);
        @(posedge clk); check(1'b0, 1'b0, 1'b1, 4'd4);
        @(posedge clk); check(1'b0, 1'b1, 1'b0, 4'd0);
        @(posedge clk); check(1'b0, 1'b1, 1'b0, 4'd1);
        @(posedge clk); check(1'b1, 1'b0, 1'b0, 4'd0);
        @(posedge clk); check(1'b1, 1'b0, 1'b0, 4'd1);
        @(posedge clk); check(1'b1, 1'b0, 1'b0, 4'd2);
        @(posedge clk); check(1'b1, 1'b0, 1'b0, 4'd3);
        @(posedge clk); check(1'b1, 1'b0, 1'b0, 4'd4);
        @(posedge clk); check(1'b0, 1'b0, 1'b1, 4'd0);
        if (errors == 0) begin
            $display("[PASS] traffic_light");
            $fdisplay(log_fd, "[PASS] traffic_light");
            $fdisplay(result_fd, "pass");
        end else begin
            $display("[FAIL] traffic_light, errors = %0d", errors);
            $fdisplay(log_fd, "[FAIL] traffic_light, errors = %0d", errors);
            $fdisplay(result_fd, "fail");
        end
        $display("##END_STUDENT_CAN_SEE");
        $fdisplay(log_fd, "##END_STUDENT_CAN_SEE");
        $fclose(log_fd); $fclose(result_fd);
        $finish;
    end
endmodule

practice/Lab04_traffic_light/golden/golden_wave.vcd
$date
	Mon May 11 15:57:59 2026
$end
$version
	Icarus Verilog
$end
$timescale
	1ps
$end
$scope module tb_traffic_light $end
$var wire 1 ! yellow $end
$var wire 4 " timer [3:0] $end
$var wire 1 # red $end
$var wire 1 $ green $end
$var reg 1 % clk $end
$var reg 1 & rst_n $end
$var integer 32 ' cycle [31:0] $end
$var integer 32 ( errors [31:0] $end
$var integer 32 ) log_fd [31:0] $end
$var integer 32 * result_fd [31:0] $end
$scope module dut $end
$var wire 1 % clk $end
$var wire 1 & rst_n $end
$var parameter 4 + GREEN_TIME $end
$var parameter 4 , RED_TIME $end
$var parameter 2 - S_GREEN $end
$var parameter 2 . S_RED $end
$var parameter 2 / S_YELLOW $end
$var parameter 4 0 YELLOW_TIME $end
$var reg 2 1 S [1:0] $end
$var reg 2 2 S_nxt [1:0] $end
$var reg 1 $ green $end
$var reg 1 # red $end
$var reg 4 3 timer [3:0] $end
$var reg 4 4 timer_nxt [3:0] $end
$var reg 1 ! yellow $end
$upscope $end
$scope task check $end
$var reg 1 5 exp_g $end
$var reg 1 6 exp_r $end
$var reg 4 7 exp_timer [3:0] $end
$var reg 1 8 exp_y $end
$upscope $end
$upscope $end
$enddefinitions $end
$comment Show the parameter values. $end
$dumpall
b10 0
b1 /
b10 .
b0 -
b101 ,
b101 +
$end
#0
$dumpvars
x8
bx 7
x6
x5
b1 4
b0 3
b0 2
b0 1
b10000000000000000000000000000100 *
b10000000000000000000000000000011 )
b0 (
b0 '
0&
0%
1$
0#
b0 "
0!
$end
#5000
1%
#10000
0%
#15000
1%
#20000
b0 7
15
08
06
1&
0%
#21000
b1 '
#25000
b10 4
b1 "
b1 3
b1 7
1%
#26000
b10 '
#30000
0%
#35000
b11 4
b10 "
b10 3
b10 7
1%
#36000
b11 '
#40000
0%
#45000
b100 4
b11 "
b11 3
b11 7
1%
#46000
b100 '
#50000
0%
#55000
b1 2
b0 4
b100 "
b100 3
b100 7
1%
#56000
b101 '
#60000
0%
#65000
1!
0$
b1 4
b0 "
b0 3
b1 1
b0 7
05
18
1%
#66000
b110 '
#70000
0%
#75000
b10 2
b0 4
b1 "
b1 3
b1 7
1%
#76000
b111 '
#80000
0%
#85000
1#
0!
b1 4
b0 "
b0 3
b10 1
b0 7
08
16
1%
#86000
b1000 '
#90000
0%
#95000
b10 4
b1 "
b1 3
b1 7
1%
#96000
b1001 '
#100000
0%
#105000
b11 4
b10 "
b10 3
b10 7
1%
#106000
b1010 '
#110000
0%
#115000
b100 4
b11 "
b11 3
b11 7
1%
#116000
b1011 '
#120000
0%
#125000
b0 2
b0 4
b100 "
b100 3
b100 7
1%
#126000
b1100 '
#130000
0%
#135000
1$
0#
b1 4
b0 "
b0 3
b0 1
b0 7
15
06
1%
#136000
b1101 '
