fpga_lab/Lab02_debounce/debounce.v
module debounce #(
    parameter N = 5 // Number of samples for debouncing
)(
    input clk,      // slow clock, e.g. 1kHz
    input rst,
    input btn_in,
    output btn_db
);

reg [N-1:0] shift_reg;

assign btn_db = ...; // btn_db is 1 if all bits in shift_reg are 1

always @(posedge clk or posedge rst) begin
    if (rst) begin
        shift_reg <= 0;
    end else begin
        shift_reg <= ...; // Shift in the btn_in into shift_reg
    end
end

endmodule

fpga_lab/Lab02_debounce/tb.v
`timescale 1ns/1ps
module tb_debounce;
    reg clk,rst,btn_in;
    wire btn_db;
    integer errors,log_fd,result_fd,pattern;

    debounce #(.N(3)) dut(.clk(clk),.rst(rst),.btn_in(btn_in),.btn_db(btn_db));
    initial begin clk=0; forever #5 clk=~clk; end

    task step; input v; begin @(negedge clk); btn_in=v; @(posedge clk); #1; end endtask
    task check;
        input [8*32-1:0] name;
        input expected;
        begin
            pattern = pattern + 1;
            if(btn_db!==expected) begin
                if (errors == 0) $display("[ERROR] pattern %0d (%0s): btn_in=%b expected btn_db=%b got=%b", pattern, name, btn_in, expected, btn_db);
                if (errors == 0) $fdisplay(log_fd,"[ERROR] pattern %0d (%0s): btn_in=%b expected btn_db=%b got=%b", pattern, name, btn_in, expected, btn_db);
                errors=errors+1;
            end
        end
    endtask

    initial begin
        log_fd=$fopen("sim/log.txt","w"); result_fd=$fopen("sim/result.txt","w");
        $dumpfile("sim/wave.vcd"); $dumpvars(0,tb_debounce);
        $display("##SEC_STUDENT_CAN_SEE"); $fdisplay(log_fd,"##SEC_STUDENT_CAN_SEE");
        // GOLDEN_CASE_SUMMARY_BEGIN
        $display("[CASE 1] checks reset release");
        $fdisplay(log_fd,"[CASE 1] checks reset release");
        $display("[CASE 2-4] checks consecutive high samples");
        $fdisplay(log_fd,"[CASE 2-4] checks consecutive high samples");
        $display("[CASE 5] checks low sample behavior");
        $fdisplay(log_fd,"[CASE 5] checks low sample behavior");
        // GOLDEN_CASE_SUMMARY_END


        errors=0; pattern=0; rst=1; btn_in=0;
        repeat(2) @(posedge clk); @(negedge clk); rst=0; #1; check("reset release", 1'b0);
        step(1); check("first high sample", 1'b0);
        step(1); check("second high sample", 1'b0);
        step(1); check("third high sample", 1'b1);
        step(0); check("drop after low sample", 1'b0);
        if(errors==0) begin $display("[PASS] debounce"); $fdisplay(log_fd,"[PASS] debounce"); $fdisplay(result_fd,"pass"); end
        else begin $display("[FAIL] debounce, errors = %0d",errors); $fdisplay(log_fd,"[FAIL] debounce, errors = %0d",errors); $fdisplay(result_fd,"fail"); end
        $display("##END_STUDENT_CAN_SEE"); $fdisplay(log_fd,"##END_STUDENT_CAN_SEE");
        $fclose(log_fd); $fclose(result_fd); $finish;
    end
endmodule

fpga_lab/Lab02_debounce/golden/golden_wave.vcd
$date
	Mon May 11 09:39:55 2026
$end
$version
	Icarus Verilog
$end
$timescale
	1ps
$end
$scope module tb_debounce $end
$var wire 1 ! btn_db $end
$var reg 1 " btn_in $end
$var reg 1 # clk $end
$var reg 1 $ rst $end
$var integer 32 % errors [31:0] $end
$var integer 32 & log_fd [31:0] $end
$var integer 32 ' pattern [31:0] $end
$var integer 32 ( result_fd [31:0] $end
$scope module dut $end
$var wire 1 " btn_in $end
$var wire 1 # clk $end
$var wire 1 $ rst $end
$var wire 1 ! btn_db $end
$var parameter 32 ) N $end
$var reg 3 * shift_reg [2:0] $end
$upscope $end
$scope task check $end
$var reg 1 + expected $end
$var reg 256 , name [255:0] $end
$upscope $end
$scope task step $end
$var reg 1 - v $end
$upscope $end
$upscope $end
$enddefinitions $end
$comment Show the parameter values. $end
$dumpall
b11 )
$end
#0
$dumpvars
x-
bx ,
x+
b0 *
b10000000000000000000000000000100 (
b0 '
b10000000000000000000000000000011 &
b0 %
1$
0#
0"
0!
$end
#5000
1#
#10000
0#
#15000
1#
#20000
0$
0#
#21000
1-
b1 '
0+
b1110010011001010111001101100101011101000010000001110010011001010110110001100101011000010111001101100101 ,
#25000
1#
#30000
1"
0#
#35000
b1 *
1#
#36000
b10 '
b110011001101001011100100111001101110100001000000110100001101001011001110110100000100000011100110110000101101101011100000110110001100101 ,
#40000
0#
#45000
b11 *
1#
#46000
b11 '
b11100110110010101100011011011110110111001100100001000000110100001101001011001110110100000100000011100110110000101101101011100000110110001100101 ,
#50000
0#
#55000
1!
b111 *
1#
#56000
0-
b100 '
1+
b111010001101000011010010111001001100100001000000110100001101001011001110110100000100000011100110110000101101101011100000110110001100101 ,
#60000
0"
0#
#65000
0!
b110 *
1#
#66000
b101 '
0+
b11001000111001001101111011100000010000001100001011001100111010001100101011100100010000001101100011011110111011100100000011100110110000101101101011100000110110001100101 ,
