fpga_lab/Lab01_clk_divN/golden/clk_divN.v
module clk_divN # (
    parameter N = 10
) (
    input  clk_in,
    input  rst,
    output reg clk_out
);
reg [$clog2(N)-1:0] cnt;

always @(posedge clk_in or posedge rst) begin
    if (rst) begin
        cnt <= 0;
        clk_out <= 1'b0;
    end else begin
        if (cnt == (N/2 - 1)) begin
            cnt <= 0;
            clk_out <= ~clk_out;
        end else begin
            cnt <= cnt + 1;
        end
    end
end

endmodule

fpga_lab/Lab01_clk_divN/tb.v
`timescale 1ns/1ps
module tb_clk_divN;
    reg clk_in, rst;
    wire clk_out;
    integer errors, log_fd, result_fd, i, pattern;
    reg expected;

    clk_divN #(.N(4)) dut (.clk_in(clk_in), .rst(rst), .clk_out(clk_out));
    initial begin clk_in = 0; forever #5 clk_in = ~clk_in; end

    task report_error;
        input [8*32-1:0] name;
        input exp;
        begin
            if (errors == 0) $display("[ERROR] pattern %0d (%0s): expected clk_out=%b got=%b", pattern, name, exp, clk_out);
            if (errors == 0) $fdisplay(log_fd, "[ERROR] pattern %0d (%0s): expected clk_out=%b got=%b", pattern, name, exp, clk_out);
            errors = errors + 1;
        end
    endtask

    initial begin
        log_fd=$fopen("sim/log.txt","w"); result_fd=$fopen("sim/result.txt","w");
        $dumpfile("sim/wave.vcd"); $dumpvars(0,tb_clk_divN);
        $display("##SEC_STUDENT_CAN_SEE"); $fdisplay(log_fd,"##SEC_STUDENT_CAN_SEE");
        // GOLDEN_CASE_SUMMARY_BEGIN
        $display("[CASE 1] checks reset release");
        $fdisplay(log_fd,"[CASE 1] checks reset release");
        $display("[CASE 2-9] checks divider toggle timing");
        $fdisplay(log_fd,"[CASE 2-9] checks divider toggle timing");
        // GOLDEN_CASE_SUMMARY_END


        errors=0; pattern=0; rst=1; expected=0;
        repeat(2) @(posedge clk_in); @(negedge clk_in); rst=0; #1;
        pattern=pattern+1; if(clk_out!==0) report_error("reset release", 1'b0);
        for(i=0;i<8;i=i+1) begin
            @(posedge clk_in); #1;
            pattern=pattern+1;
            if(i%2==1) expected=~expected;
            if(clk_out!==expected) report_error("divide-by-4 step", expected);
        end
        if(errors==0) begin $display("[PASS] clk_divN"); $fdisplay(log_fd,"[PASS] clk_divN"); $fdisplay(result_fd,"pass"); end
        else begin $display("[FAIL] clk_divN, errors = %0d",errors); $fdisplay(log_fd,"[FAIL] clk_divN, errors = %0d",errors); $fdisplay(result_fd,"fail"); end
        $display("##END_STUDENT_CAN_SEE"); $fdisplay(log_fd,"##END_STUDENT_CAN_SEE");
        $fclose(log_fd); $fclose(result_fd); $finish;
    end
endmodule

fpga_lab/Lab01_clk_divN/golden/golden_wave.vcd
$date
	Mon May 11 09:39:55 2026
$end
$version
	Icarus Verilog
$end
$timescale
	1ps
$end
$scope module tb_clk_divN $end
$var wire 1 ! clk_out $end
$var reg 1 " clk_in $end
$var reg 1 # expected $end
$var reg 1 $ rst $end
$var integer 32 % errors [31:0] $end
$var integer 32 & i [31:0] $end
$var integer 32 ' log_fd [31:0] $end
$var integer 32 ( pattern [31:0] $end
$var integer 32 ) result_fd [31:0] $end
$scope module dut $end
$var wire 1 " clk_in $end
$var wire 1 $ rst $end
$var parameter 32 * N $end
$var reg 1 ! clk_out $end
$var reg 2 + cnt [1:0] $end
$upscope $end
$scope task report_error $end
$var reg 1 , exp $end
$var reg 256 - name [255:0] $end
$upscope $end
$upscope $end
$enddefinitions $end
$comment Show the parameter values. $end
$dumpall
b100 *
$end
#0
$dumpvars
bx -
x,
b0 +
b10000000000000000000000000000100 )
b0 (
b10000000000000000000000000000011 '
bx &
b0 %
1$
0#
0"
0!
$end
#5000
1"
#10000
0"
#15000
1"
#20000
0$
0"
#21000
b0 &
b1 (
#25000
b1 +
1"
#26000
b1 &
b10 (
#30000
0"
#35000
1!
b0 +
1"
#36000
b10 &
1#
b11 (
#40000
0"
#45000
b1 +
1"
#46000
b11 &
b100 (
#50000
0"
#55000
0!
b0 +
1"
#56000
b100 &
0#
b101 (
#60000
0"
#65000
b1 +
1"
#66000
b101 &
b110 (
#70000
0"
#75000
1!
b0 +
1"
#76000
b110 &
1#
b111 (
#80000
0"
#85000
b1 +
1"
#86000
b111 &
b1000 (
#90000
0"
#95000
0!
b0 +
1"
#96000
b1000 &
0#
b1001 (
