fpga_lab/Lab08_pwm/golden/pwm.v
module pwm (
    input  wire       clk,
    input  wire       rst,
    input  wire [6:0] duty,
    output reg        pwm_out
);

reg [6:0] count;

always @(posedge clk or posedge rst) begin
    if (rst) begin
        count <= 0;
        pwm_out <= 1'b0;
    end else begin
        count <= (count == 99) ? 0 : (count + 1);
        pwm_out <= (count < duty);
    end
end

endmodule

fpga_lab/Lab06_pwm/tb.v
`timescale 1ns/1ps
module tb_pwm;
    reg clk,rst;
    reg [6:0] duty;
    wire pwm_out;
    integer errors,log_fd,result_fd,i,pattern;
    reg expected;

    pwm dut(.clk(clk),.rst(rst),.duty(duty),.pwm_out(pwm_out));
    initial begin clk=0; forever #5 clk=~clk; end

    task check_output;
        input [8*32-1:0] name;
        input expected_value;
        begin
            pattern = pattern + 1;
            #1;
            if(pwm_out!==expected_value) begin
                if (errors == 0) $display("[ERROR] pattern %0d (%0s): duty=%0d expected pwm_out=%b got=%b", pattern, name, duty, expected_value, pwm_out);
                if (errors == 0) $fdisplay(log_fd,"[ERROR] pattern %0d (%0s): duty=%0d expected pwm_out=%b got=%b", pattern, name, duty, expected_value, pwm_out);
                errors=errors+1;
            end
        end
    endtask

    task check_period;
        input [8*32-1:0] name;
        input [6:0] duty_value;
        begin
            for(i=0;i<100;i=i+1) begin
                @(posedge clk);
                expected = (i < duty_value);
                check_output(name, expected);
            end
        end
    endtask

    initial begin
        log_fd=$fopen("sim/log.txt","w"); result_fd=$fopen("sim/result.txt","w");
        $dumpfile("sim/wave.vcd"); $dumpvars(0,tb_pwm);
        $display("##SEC_STUDENT_CAN_SEE"); $fdisplay(log_fd,"##SEC_STUDENT_CAN_SEE");
        // GOLDEN_CASE_SUMMARY_BEGIN
        $display("[CASE 1] checks reset output");
        $fdisplay(log_fd,"[CASE 1] checks reset output");
        $display("[CASE 2-101] checks 30 percent duty cycle");
        $fdisplay(log_fd,"[CASE 2-101] checks 30 percent duty cycle");
        $display("[CASE 102-201] checks dynamic duty update to 75 percent");
        $fdisplay(log_fd,"[CASE 102-201] checks dynamic duty update to 75 percent");
        $display("[CASE 202-301] checks zero percent duty");
        $fdisplay(log_fd,"[CASE 202-301] checks zero percent duty");
        $display("[CASE 302-401] checks 100 percent duty");
        $fdisplay(log_fd,"[CASE 302-401] checks 100 percent duty");
        // GOLDEN_CASE_SUMMARY_END

        errors=0; pattern=0; rst=1; duty=7'd30;
        repeat(2) @(posedge clk); @(negedge clk); rst=0; check_output("reset release", 1'b0);
        check_period("30 percent duty", 7'd30);
        @(negedge clk); duty=7'd75;
        check_period("dynamic 75 percent duty", 7'd75);
        @(negedge clk); duty=7'd0;
        check_period("zero percent duty", 7'd0);
        @(negedge clk); duty=7'd100;
        check_period("100 percent duty", 7'd100);

        if(errors==0) begin $display("[PASS] pwm"); $fdisplay(log_fd,"[PASS] pwm"); $fdisplay(result_fd,"pass"); end
        else begin $display("[FAIL] pwm, errors = %0d",errors); $fdisplay(log_fd,"[FAIL] pwm, errors = %0d",errors); $fdisplay(result_fd,"fail"); end
        $display("##END_STUDENT_CAN_SEE"); $fdisplay(log_fd,"##END_STUDENT_CAN_SEE");
        $fclose(log_fd); $fclose(result_fd); $finish;
    end
endmodule

fpga_lab/Lab08_pwm/golden/golden_wave.vcd
$date
	Fri Jun 26 12:54:48 2026
$end
$version
	Icarus Verilog
$end
$timescale
	1ps
$end
$scope module tb_pwm $end
$var wire 1 ! pwm_out $end
$var reg 1 " clk $end
$var reg 7 # duty [6:0] $end
$var reg 1 $ expected $end
$var reg 1 % rst $end
$var integer 32 & errors [31:0] $end
$var integer 32 ' i [31:0] $end
$var integer 32 ( log_fd [31:0] $end
$var integer 32 ) pattern [31:0] $end
$var integer 32 * result_fd [31:0] $end
$scope module dut $end
$var wire 1 " clk $end
$var wire 7 + duty [6:0] $end
$var wire 1 % rst $end
$var reg 7 , count [6:0] $end
$var reg 1 ! pwm_out $end
$upscope $end
$scope task check_output $end
$var reg 1 - expected_value $end
$var reg 256 . name [255:0] $end
$upscope $end
$scope task check_period $end
$var reg 7 / duty_value [6:0] $end
$var reg 256 0 name [255:0] $end
$upscope $end
$upscope $end
$enddefinitions $end
$comment Show the parameter values. $end
$dumpall
$end
#0
$dumpvars
bx 0
bx /
bx .
x-
b0 ,
b11110 +
b10000000000000000000000000000100 *
b0 )
b10000000000000000000000000000011 (
bx '
b0 &
1%
x$
b11110 #
0"
0!
$end
#5000
1"
#10000
0"
#15000
1"
#20000
b1 )
0-
b1110010011001010111001101100101011101000010000001110010011001010110110001100101011000010111001101100101 .
0%
0"
#21000
b0 '
b11110 /
b1100110011000000100000011100000110010101110010011000110110010101101110011101000010000001100100011101010111010001111001 0
#25000
1!
b1 ,
b10 )
1-
b1100110011000000100000011100000110010101110010011000110110010101101110011101000010000001100100011101010111010001111001 .
1$
1"
#26000
b1 '
#30000
0"
#35000
b10 ,
b11 )
1"
#36000
b10 '
#40000
0"
#45000
b11 ,
b100 )
1"
#46000
b11 '
#50000
0"
#55000
b100 ,
b101 )
1"
#56000
b100 '
#60000
0"
#65000
b101 ,
b110 )
1"
#66000
b101 '
#70000
0"
#75000
b110 ,
b111 )
1"
#76000
b110 '
#80000
0"
#85000
b111 ,
b1000 )
1"
#86000
b111 '
#90000
0"
#95000
b1000 ,
b1001 )
1"
#96000
b1000 '
#100000
0"
#105000
b1001 ,
b1010 )
1"
#106000
b1001 '
#110000
0"
#115000
b1010 ,
b1011 )
1"
#116000
b1010 '
#120000
0"
#125000
b1011 ,
b1100 )
1"
#126000
b1011 '
#130000
0"
#135000
b1100 ,
b1101 )
1"
#136000
b1100 '
#140000
0"
#145000
b1101 ,
b1110 )
1"
#146000
b1101 '
#150000
0"
#155000
b1110 ,
b1111 )
1"
#156000
b1110 '
#160000
0"
#165000
b1111 ,
b10000 )
1"
#166000
b1111 '
#170000
0"
#175000
b10000 ,
b10001 )
1"
#176000
b10000 '
#180000
0"
#185000
b10001 ,
b10010 )
1"
#186000
b10001 '
#190000
0"
#195000
b10010 ,
b10011 )
1"
#196000
b10010 '
#200000
0"
#205000
b10011 ,
b10100 )
1"
#206000
b10011 '
#210000
0"
#215000
b10100 ,
b10101 )
1"
#216000
b10100 '
#220000
0"
#225000
b10101 ,
b10110 )
1"
#226000
b10101 '
#230000
0"
#235000
b10110 ,
b10111 )
1"
#236000
b10110 '
#240000
0"
#245000
b10111 ,
b11000 )
1"
#246000
b10111 '
#250000
0"
#255000
b11000 ,
b11001 )
1"
#256000
b11000 '
#260000
0"
#265000
b11001 ,
b11010 )
1"
#266000
b11001 '
#270000
0"
#275000
b11010 ,
b11011 )
1"
#276000
b11010 '
#280000
0"
#285000
b11011 ,
b11100 )
1"
#286000
b11011 '
#290000
0"
#295000
b11100 ,
b11101 )
1"
#296000
b11100 '
#300000
0"
#305000
b11101 ,
b11110 )
1"
#306000
b11101 '
#310000
0"
#315000
b11110 ,
b11111 )
1"
#316000
b11110 '
#320000
0"
#325000
0!
b11111 ,
b100000 )
0-
0$
1"
#326000
b11111 '
#330000
0"
#335000
b100000 ,
b100001 )
1"
#336000
b100000 '
#340000
0"
#345000
b100001 ,
b100010 )
1"
#346000
b100001 '
#350000
0"
#355000
b100010 ,
b100011 )
1"
#356000
b100010 '
#360000
0"
#365000
b100011 ,
b100100 )
1"
#366000
b100011 '
#370000
0"
#375000
b100100 ,
b100101 )
1"
#376000
b100100 '
#380000
0"
#385000
b100101 ,
b100110 )
1"
#386000
b100101 '
#390000
0"
#395000
b100110 ,
b100111 )
1"
#396000
b100110 '
#400000
0"
#405000
b100111 ,
b101000 )
1"
#406000
b100111 '
#410000
0"
#415000
b101000 ,
b101001 )
1"
#416000
b101000 '
#420000
0"
#425000
b101001 ,
b101010 )
1"
#426000
b101001 '
#430000
0"
#435000
b101010 ,
b101011 )
1"
#436000
b101010 '
#440000
0"
#445000
b101011 ,
b101100 )
1"
#446000
b101011 '
#450000
0"
#455000
b101100 ,
b101101 )
1"
#456000
b101100 '
#460000
0"
#465000
b101101 ,
b101110 )
1"
#466000
b101101 '
#470000
0"
#475000
b101110 ,
b101111 )
1"
#476000
b101110 '
#480000
0"
#485000
b101111 ,
b110000 )
1"
#486000
b101111 '
#490000
0"
#495000
b110000 ,
b110001 )
1"
#496000
b110000 '
#500000
0"
#505000
b110001 ,
b110010 )
1"
#506000
b110001 '
#510000
0"
#515000
b110010 ,
b110011 )
1"
#516000
b110010 '
#520000
0"
#525000
b110011 ,
b110100 )
1"
#526000
b110011 '
#530000
0"
#535000
b110100 ,
b110101 )
1"
#536000
b110100 '
#540000
0"
#545000
b110101 ,
b110110 )
1"
#546000
b110101 '
#550000
0"
#555000
b110110 ,
b110111 )
1"
#556000
b110110 '
#560000
0"
#565000
b110111 ,
b111000 )
1"
#566000
b110111 '
#570000
0"
#575000
b111000 ,
b111001 )
1"
#576000
b111000 '
#580000
0"
#585000
b111001 ,
b111010 )
1"
#586000
b111001 '
#590000
0"
#595000
b111010 ,
b111011 )
1"
#596000
b111010 '
#600000
0"
#605000
b111011 ,
b111100 )
1"
#606000
b111011 '
#610000
0"
#615000
b111100 ,
b111101 )
1"
#616000
b111100 '
#620000
0"
#625000
b111101 ,
b111110 )
1"
#626000
b111101 '
#630000
0"
#635000
b111110 ,
b111111 )
1"
#636000
b111110 '
#640000
0"
#645000
b111111 ,
b1000000 )
1"
#646000
b111111 '
#650000
0"
#655000
b1000000 ,
b1000001 )
1"
#656000
b1000000 '
#660000
0"
#665000
b1000001 ,
b1000010 )
1"
#666000
b1000001 '
#670000
0"
#675000
b1000010 ,
b1000011 )
1"
#676000
b1000010 '
#680000
0"
#685000
b1000011 ,
b1000100 )
1"
#686000
b1000011 '
#690000
0"
#695000
b1000100 ,
b1000101 )
1"
#696000
b1000100 '
#700000
0"
#705000
b1000101 ,
b1000110 )
1"
#706000
b1000101 '
#710000
0"
#715000
b1000110 ,
b1000111 )
1"
#716000
b1000110 '
#720000
0"
#725000
b1000111 ,
b1001000 )
1"
#726000
b1000111 '
#730000
0"
#735000
b1001000 ,
b1001001 )
1"
#736000
b1001000 '
#740000
0"
#745000
b1001001 ,
b1001010 )
1"
#746000
b1001001 '
#750000
0"
#755000
b1001010 ,
b1001011 )
1"
#756000
b1001010 '
#760000
0"
#765000
b1001011 ,
b1001100 )
1"
#766000
b1001011 '
#770000
0"
#775000
b1001100 ,
b1001101 )
1"
#776000
b1001100 '
#780000
0"
#785000
b1001101 ,
b1001110 )
1"
#786000
b1001101 '
#790000
0"
#795000
b1001110 ,
b1001111 )
1"
#796000
b1001110 '
#800000
0"
#805000
b1001111 ,
b1010000 )
1"
#806000
b1001111 '
#810000
0"
#815000
b1010000 ,
b1010001 )
1"
#816000
b1010000 '
#820000
0"
#825000
b1010001 ,
b1010010 )
1"
#826000
b1010001 '
#830000
0"
#835000
b1010010 ,
b1010011 )
1"
#836000
b1010010 '
#840000
0"
#845000
b1010011 ,
b1010100 )
1"
#846000
b1010011 '
#850000
0"
#855000
b1010100 ,
b1010101 )
1"
#856000
b1010100 '
#860000
0"
#865000
b1010101 ,
b1010110 )
1"
#866000
b1010101 '
#870000
0"
#875000
b1010110 ,
b1010111 )
1"
#876000
b1010110 '
#880000
0"
#885000
b1010111 ,
b1011000 )
1"
#886000
b1010111 '
#890000
0"
#895000
b1011000 ,
b1011001 )
1"
#896000
b1011000 '
#900000
0"
#905000
b1011001 ,
b1011010 )
1"
#906000
b1011001 '
#910000
0"
#915000
b1011010 ,
b1011011 )
1"
#916000
b1011010 '
#920000
0"
#925000
b1011011 ,
b1011100 )
1"
#926000
b1011011 '
#930000
0"
#935000
b1011100 ,
b1011101 )
1"
#936000
b1011100 '
#940000
0"
#945000
b1011101 ,
b1011110 )
1"
#946000
b1011101 '
#950000
0"
#955000
b1011110 ,
b1011111 )
1"
#956000
b1011110 '
#960000
0"
#965000
b1011111 ,
b1100000 )
1"
#966000
b1011111 '
#970000
0"
#975000
b1100000 ,
b1100001 )
1"
#976000
b1100000 '
#980000
0"
#985000
b1100001 ,
b1100010 )
1"
#986000
b1100001 '
#990000
0"
#995000
b1100010 ,
b1100011 )
1"
#996000
b1100010 '
#1000000
0"
#1005000
b1100011 ,
b1100100 )
1"
#1006000
b1100011 '
#1010000
0"
#1015000
b0 ,
b1100101 )
1"
#1016000
b1100100 '
#1020000
b0 '
b1001011 /
b110010001111001011011100110000101101101011010010110001100100000001101110011010100100000011100000110010101110010011000110110010101101110011101000010000001100100011101010111010001111001 0
b1001011 #
b1001011 +
0"
#1025000
1!
b1 ,
b1100110 )
1-
b110010001111001011011100110000101101101011010010110001100100000001101110011010100100000011100000110010101110010011000110110010101101110011101000010000001100100011101010111010001111001 .
1$
1"
#1026000
b1 '
#1030000
0"
#1035000
b10 ,
b1100111 )
1"
#1036000
b10 '
#1040000
0"
#1045000
b11 ,
b1101000 )
1"
#1046000
b11 '
#1050000
0"
#1055000
b100 ,
b1101001 )
1"
#1056000
b100 '
#1060000
0"
#1065000
b101 ,
b1101010 )
1"
#1066000
b101 '
#1070000
0"
#1075000
b110 ,
b1101011 )
1"
#1076000
b110 '
#1080000
0"
#1085000
b111 ,
b1101100 )
1"
#1086000
b111 '
#1090000
0"
#1095000
b1000 ,
b1101101 )
1"
#1096000
b1000 '
#1100000
0"
#1105000
b1001 ,
b1101110 )
1"
#1106000
b1001 '
#1110000
0"
#1115000
b1010 ,
b1101111 )
1"
#1116000
b1010 '
#1120000
0"
#1125000
b1011 ,
b1110000 )
1"
#1126000
b1011 '
#1130000
0"
#1135000
b1100 ,
b1110001 )
1"
#1136000
b1100 '
#1140000
0"
#1145000
b1101 ,
b1110010 )
1"
#1146000
b1101 '
#1150000
0"
#1155000
b1110 ,
b1110011 )
1"
#1156000
b1110 '
#1160000
0"
#1165000
b1111 ,
b1110100 )
1"
#1166000
b1111 '
#1170000
0"
#1175000
b10000 ,
b1110101 )
1"
#1176000
b10000 '
#1180000
0"
#1185000
b10001 ,
b1110110 )
1"
#1186000
b10001 '
#1190000
0"
#1195000
b10010 ,
b1110111 )
1"
#1196000
b10010 '
#1200000
0"
#1205000
b10011 ,
b1111000 )
1"
#1206000
b10011 '
#1210000
0"
#1215000
b10100 ,
b1111001 )
1"
#1216000
b10100 '
#1220000
0"
#1225000
b10101 ,
b1111010 )
1"
#1226000
b10101 '
#1230000
0"
#1235000
b10110 ,
b1111011 )
1"
#1236000
b10110 '
#1240000
0"
#1245000
b10111 ,
b1111100 )
1"
#1246000
b10111 '
#1250000
0"
#1255000
b11000 ,
b1111101 )
1"
#1256000
b11000 '
#1260000
0"
#1265000
b11001 ,
b1111110 )
1"
#1266000
b11001 '
#1270000
0"
#1275000
b11010 ,
b1111111 )
1"
#1276000
b11010 '
#1280000
0"
#1285000
b11011 ,
b10000000 )
1"
#1286000
b11011 '
#1290000
0"
#1295000
b11100 ,
b10000001 )
1"
#1296000
b11100 '
#1300000
0"
#1305000
b11101 ,
b10000010 )
1"
#1306000
b11101 '
#1310000
0"
#1315000
b11110 ,
b10000011 )
1"
#1316000
b11110 '
#1320000
0"
#1325000
b11111 ,
b10000100 )
1"
#1326000
b11111 '
#1330000
0"
#1335000
b100000 ,
b10000101 )
1"
#1336000
b100000 '
#1340000
0"
#1345000
b100001 ,
b10000110 )
1"
#1346000
b100001 '
#1350000
0"
#1355000
b100010 ,
b10000111 )
1"
#1356000
b100010 '
#1360000
0"
#1365000
b100011 ,
b10001000 )
1"
#1366000
b100011 '
#1370000
0"
#1375000
b100100 ,
b10001001 )
1"
#1376000
b100100 '
#1380000
0"
#1385000
b100101 ,
b10001010 )
1"
#1386000
b100101 '
#1390000
0"
#1395000
b100110 ,
b10001011 )
1"
#1396000
b100110 '
#1400000
0"
#1405000
b100111 ,
b10001100 )
1"
#1406000
b100111 '
#1410000
0"
#1415000
b101000 ,
b10001101 )
1"
#1416000
b101000 '
#1420000
0"
#1425000
b101001 ,
b10001110 )
1"
#1426000
b101001 '
#1430000
0"
#1435000
b101010 ,
b10001111 )
1"
#1436000
b101010 '
#1440000
0"
#1445000
b101011 ,
b10010000 )
1"
#1446000
b101011 '
#1450000
0"
#1455000
b101100 ,
b10010001 )
1"
#1456000
b101100 '
#1460000
0"
#1465000
b101101 ,
b10010010 )
1"
#1466000
b101101 '
#1470000
0"
#1475000
b101110 ,
b10010011 )
1"
#1476000
b101110 '
#1480000
0"
#1485000
b101111 ,
b10010100 )
1"
#1486000
b101111 '
#1490000
0"
#1495000
b110000 ,
b10010101 )
1"
#1496000
b110000 '
#1500000
0"
#1505000
b110001 ,
b10010110 )
1"
#1506000
b110001 '
#1510000
0"
#1515000
b110010 ,
b10010111 )
1"
#1516000
b110010 '
#1520000
0"
#1525000
b110011 ,
b10011000 )
1"
#1526000
b110011 '
#1530000
0"
#1535000
b110100 ,
b10011001 )
1"
#1536000
b110100 '
#1540000
0"
#1545000
b110101 ,
b10011010 )
1"
#1546000
b110101 '
#1550000
0"
#1555000
b110110 ,
b10011011 )
1"
#1556000
b110110 '
#1560000
0"
#1565000
b110111 ,
b10011100 )
1"
#1566000
b110111 '
#1570000
0"
#1575000
b111000 ,
b10011101 )
1"
#1576000
b111000 '
#1580000
0"
#1585000
b111001 ,
b10011110 )
1"
#1586000
b111001 '
#1590000
0"
#1595000
b111010 ,
b10011111 )
1"
#1596000
b111010 '
#1600000
0"
#1605000
b111011 ,
b10100000 )
1"
#1606000
b111011 '
#1610000
0"
#1615000
b111100 ,
b10100001 )
1"
#1616000
b111100 '
#1620000
0"
#1625000
b111101 ,
b10100010 )
1"
#1626000
b111101 '
#1630000
0"
#1635000
b111110 ,
b10100011 )
1"
#1636000
b111110 '
#1640000
0"
#1645000
b111111 ,
b10100100 )
1"
#1646000
b111111 '
#1650000
0"
#1655000
b1000000 ,
b10100101 )
1"
#1656000
b1000000 '
#1660000
0"
#1665000
b1000001 ,
b10100110 )
1"
#1666000
b1000001 '
#1670000
0"
#1675000
b1000010 ,
b10100111 )
1"
#1676000
b1000010 '
#1680000
0"
#1685000
b1000011 ,
b10101000 )
1"
#1686000
b1000011 '
#1690000
0"
#1695000
b1000100 ,
b10101001 )
1"
#1696000
b1000100 '
#1700000
0"
#1705000
b1000101 ,
b10101010 )
1"
#1706000
b1000101 '
#1710000
0"
#1715000
b1000110 ,
b10101011 )
1"
#1716000
b1000110 '
#1720000
0"
#1725000
b1000111 ,
b10101100 )
1"
#1726000
b1000111 '
#1730000
0"
#1735000
b1001000 ,
b10101101 )
1"
#1736000
b1001000 '
#1740000
0"
#1745000
b1001001 ,
b10101110 )
1"
#1746000
b1001001 '
#1750000
0"
#1755000
b1001010 ,
b10101111 )
1"
#1756000
b1001010 '
#1760000
0"
#1765000
b1001011 ,
b10110000 )
1"
#1766000
b1001011 '
#1770000
0"
#1775000
0!
b1001100 ,
b10110001 )
0-
0$
1"
#1776000
b1001100 '
#1780000
0"
#1785000
b1001101 ,
b10110010 )
1"
#1786000
b1001101 '
#1790000
0"
#1795000
b1001110 ,
b10110011 )
1"
#1796000
b1001110 '
#1800000
0"
#1805000
b1001111 ,
b10110100 )
1"
#1806000
b1001111 '
#1810000
0"
#1815000
b1010000 ,
b10110101 )
1"
#1816000
b1010000 '
#1820000
0"
#1825000
b1010001 ,
b10110110 )
1"
#1826000
b1010001 '
#1830000
0"
#1835000
b1010010 ,
b10110111 )
1"
#1836000
b1010010 '
#1840000
0"
#1845000
b1010011 ,
b10111000 )
1"
#1846000
b1010011 '
#1850000
0"
#1855000
b1010100 ,
b10111001 )
1"
#1856000
b1010100 '
#1860000
0"
#1865000
b1010101 ,
b10111010 )
1"
#1866000
b1010101 '
#1870000
0"
#1875000
b1010110 ,
b10111011 )
1"
#1876000
b1010110 '
#1880000
0"
#1885000
b1010111 ,
b10111100 )
1"
#1886000
b1010111 '
#1890000
0"
#1895000
b1011000 ,
b10111101 )
1"
#1896000
b1011000 '
#1900000
0"
#1905000
b1011001 ,
b10111110 )
1"
#1906000
b1011001 '
#1910000
0"
#1915000
b1011010 ,
b10111111 )
1"
#1916000
b1011010 '
#1920000
0"
#1925000
b1011011 ,
b11000000 )
1"
#1926000
b1011011 '
#1930000
0"
#1935000
b1011100 ,
b11000001 )
1"
#1936000
b1011100 '
#1940000
0"
#1945000
b1011101 ,
b11000010 )
1"
#1946000
b1011101 '
#1950000
0"
#1955000
b1011110 ,
b11000011 )
1"
#1956000
b1011110 '
#1960000
0"
#1965000
b1011111 ,
b11000100 )
1"
#1966000
b1011111 '
#1970000
0"
#1975000
b1100000 ,
b11000101 )
1"
#1976000
b1100000 '
#1980000
0"
#1985000
b1100001 ,
b11000110 )
1"
#1986000
b1100001 '
#1990000
0"
#1995000
b1100010 ,
b11000111 )
1"
#1996000
b1100010 '
#2000000
0"
#2005000
b1100011 ,
b11001000 )
1"
#2006000
b1100011 '
#2010000
0"
#2015000
b0 ,
b11001001 )
1"
#2016000
b1100100 '
#2020000
b0 '
b0 /
b111101001100101011100100110111100100000011100000110010101110010011000110110010101101110011101000010000001100100011101010111010001111001 0
b0 #
b0 +
0"
#2025000
b1 ,
b11001010 )
b111101001100101011100100110111100100000011100000110010101110010011000110110010101101110011101000010000001100100011101010111010001111001 .
1"
#2026000
b1 '
#2030000
0"
#2035000
b10 ,
b11001011 )
1"
#2036000
b10 '
#2040000
0"
#2045000
b11 ,
b11001100 )
1"
#2046000
b11 '
#2050000
0"
#2055000
b100 ,
b11001101 )
1"
#2056000
b100 '
#2060000
0"
#2065000
b101 ,
b11001110 )
1"
#2066000
b101 '
#2070000
0"
#2075000
b110 ,
b11001111 )
1"
#2076000
b110 '
#2080000
0"
#2085000
b111 ,
b11010000 )
1"
#2086000
b111 '
#2090000
0"
#2095000
b1000 ,
b11010001 )
1"
#2096000
b1000 '
#2100000
0"
#2105000
b1001 ,
b11010010 )
1"
#2106000
b1001 '
#2110000
0"
#2115000
b1010 ,
b11010011 )
1"
#2116000
b1010 '
#2120000
0"
#2125000
b1011 ,
b11010100 )
1"
#2126000
b1011 '
#2130000
0"
#2135000
b1100 ,
b11010101 )
1"
#2136000
b1100 '
#2140000
0"
#2145000
b1101 ,
b11010110 )
1"
#2146000
b1101 '
#2150000
0"
#2155000
b1110 ,
b11010111 )
1"
#2156000
b1110 '
#2160000
0"
#2165000
b1111 ,
b11011000 )
1"
#2166000
b1111 '
#2170000
0"
#2175000
b10000 ,
b11011001 )
1"
#2176000
b10000 '
#2180000
0"
#2185000
b10001 ,
b11011010 )
1"
#2186000
b10001 '
#2190000
0"
#2195000
b10010 ,
b11011011 )
1"
#2196000
b10010 '
#2200000
0"
#2205000
b10011 ,
b11011100 )
1"
#2206000
b10011 '
#2210000
0"
#2215000
b10100 ,
b11011101 )
1"
#2216000
b10100 '
#2220000
0"
#2225000
b10101 ,
b11011110 )
1"
#2226000
b10101 '
#2230000
0"
#2235000
b10110 ,
b11011111 )
1"
#2236000
b10110 '
#2240000
0"
#2245000
b10111 ,
b11100000 )
1"
#2246000
b10111 '
#2250000
0"
#2255000
b11000 ,
b11100001 )
1"
#2256000
b11000 '
#2260000
0"
#2265000
b11001 ,
b11100010 )
1"
#2266000
b11001 '
#2270000
0"
#2275000
b11010 ,
b11100011 )
1"
#2276000
b11010 '
#2280000
0"
#2285000
b11011 ,
b11100100 )
1"
#2286000
b11011 '
#2290000
0"
#2295000
b11100 ,
b11100101 )
1"
#2296000
b11100 '
#2300000
0"
#2305000
b11101 ,
b11100110 )
1"
#2306000
b11101 '
#2310000
0"
#2315000
b11110 ,
b11100111 )
1"
#2316000
b11110 '
#2320000
0"
#2325000
b11111 ,
b11101000 )
1"
#2326000
b11111 '
#2330000
0"
#2335000
b100000 ,
b11101001 )
1"
#2336000
b100000 '
#2340000
0"
#2345000
b100001 ,
b11101010 )
1"
#2346000
b100001 '
#2350000
0"
#2355000
b100010 ,
b11101011 )
1"
#2356000
b100010 '
#2360000
0"
#2365000
b100011 ,
b11101100 )
1"
#2366000
b100011 '
#2370000
0"
#2375000
b100100 ,
b11101101 )
1"
#2376000
b100100 '
#2380000
0"
#2385000
b100101 ,
b11101110 )
1"
#2386000
b100101 '
#2390000
0"
#2395000
b100110 ,
b11101111 )
1"
#2396000
b100110 '
#2400000
0"
#2405000
b100111 ,
b11110000 )
1"
#2406000
b100111 '
#2410000
0"
#2415000
b101000 ,
b11110001 )
1"
#2416000
b101000 '
#2420000
0"
#2425000
b101001 ,
b11110010 )
1"
#2426000
b101001 '
#2430000
0"
#2435000
b101010 ,
b11110011 )
1"
#2436000
b101010 '
#2440000
0"
#2445000
b101011 ,
b11110100 )
1"
#2446000
b101011 '
#2450000
0"
#2455000
b101100 ,
b11110101 )
1"
#2456000
b101100 '
#2460000
0"
#2465000
b101101 ,
b11110110 )
1"
#2466000
b101101 '
#2470000
0"
#2475000
b101110 ,
b11110111 )
1"
#2476000
b101110 '
#2480000
0"
#2485000
b101111 ,
b11111000 )
1"
#2486000
b101111 '
#2490000
0"
#2495000
b110000 ,
b11111001 )
1"
#2496000
b110000 '
#2500000
0"
#2505000
b110001 ,
b11111010 )
1"
#2506000
b110001 '
#2510000
0"
#2515000
b110010 ,
b11111011 )
1"
#2516000
b110010 '
#2520000
0"
#2525000
b110011 ,
b11111100 )
1"
#2526000
b110011 '
#2530000
0"
#2535000
b110100 ,
b11111101 )
1"
#2536000
b110100 '
#2540000
0"
#2545000
b110101 ,
b11111110 )
1"
#2546000
b110101 '
#2550000
0"
#2555000
b110110 ,
b11111111 )
1"
#2556000
b110110 '
#2560000
0"
#2565000
b110111 ,
b100000000 )
1"
#2566000
b110111 '
#2570000
0"
#2575000
b111000 ,
b100000001 )
1"
#2576000
b111000 '
#2580000
0"
#2585000
b111001 ,
b100000010 )
1"
#2586000
b111001 '
#2590000
0"
#2595000
b111010 ,
b100000011 )
1"
#2596000
b111010 '
#2600000
0"
#2605000
b111011 ,
b100000100 )
1"
#2606000
b111011 '
#2610000
0"
#2615000
b111100 ,
b100000101 )
1"
#2616000
b111100 '
#2620000
0"
#2625000
b111101 ,
b100000110 )
1"
#2626000
b111101 '
#2630000
0"
#2635000
b111110 ,
b100000111 )
1"
#2636000
b111110 '
#2640000
0"
#2645000
b111111 ,
b100001000 )
1"
#2646000
b111111 '
#2650000
0"
#2655000
b1000000 ,
b100001001 )
1"
#2656000
b1000000 '
#2660000
0"
#2665000
b1000001 ,
b100001010 )
1"
#2666000
b1000001 '
#2670000
0"
#2675000
b1000010 ,
b100001011 )
1"
#2676000
b1000010 '
#2680000
0"
#2685000
b1000011 ,
b100001100 )
1"
#2686000
b1000011 '
#2690000
0"
#2695000
b1000100 ,
b100001101 )
1"
#2696000
b1000100 '
#2700000
0"
#2705000
b1000101 ,
b100001110 )
1"
#2706000
b1000101 '
#2710000
0"
#2715000
b1000110 ,
b100001111 )
1"
#2716000
b1000110 '
#2720000
0"
#2725000
b1000111 ,
b100010000 )
1"
#2726000
b1000111 '
#2730000
0"
#2735000
b1001000 ,
b100010001 )
1"
#2736000
b1001000 '
#2740000
0"
#2745000
b1001001 ,
b100010010 )
1"
#2746000
b1001001 '
#2750000
0"
#2755000
b1001010 ,
b100010011 )
1"
#2756000
b1001010 '
#2760000
0"
#2765000
b1001011 ,
b100010100 )
1"
#2766000
b1001011 '
#2770000
0"
#2775000
b1001100 ,
b100010101 )
1"
#2776000
b1001100 '
#2780000
0"
#2785000
b1001101 ,
b100010110 )
1"
#2786000
b1001101 '
#2790000
0"
#2795000
b1001110 ,
b100010111 )
1"
#2796000
b1001110 '
#2800000
0"
#2805000
b1001111 ,
b100011000 )
1"
#2806000
b1001111 '
#2810000
0"
#2815000
b1010000 ,
b100011001 )
1"
#2816000
b1010000 '
#2820000
0"
#2825000
b1010001 ,
b100011010 )
1"
#2826000
b1010001 '
#2830000
0"
#2835000
b1010010 ,
b100011011 )
1"
#2836000
b1010010 '
#2840000
0"
#2845000
b1010011 ,
b100011100 )
1"
#2846000
b1010011 '
#2850000
0"
#2855000
b1010100 ,
b100011101 )
1"
#2856000
b1010100 '
#2860000
0"
#2865000
b1010101 ,
b100011110 )
1"
#2866000
b1010101 '
#2870000
0"
#2875000
b1010110 ,
b100011111 )
1"
#2876000
b1010110 '
#2880000
0"
#2885000
b1010111 ,
b100100000 )
1"
#2886000
b1010111 '
#2890000
0"
#2895000
b1011000 ,
b100100001 )
1"
#2896000
b1011000 '
#2900000
0"
#2905000
b1011001 ,
b100100010 )
1"
#2906000
b1011001 '
#2910000
0"
#2915000
b1011010 ,
b100100011 )
1"
#2916000
b1011010 '
#2920000
0"
#2925000
b1011011 ,
b100100100 )
1"
#2926000
b1011011 '
#2930000
0"
#2935000
b1011100 ,
b100100101 )
1"
#2936000
b1011100 '
#2940000
0"
#2945000
b1011101 ,
b100100110 )
1"
#2946000
b1011101 '
#2950000
0"
#2955000
b1011110 ,
b100100111 )
1"
#2956000
b1011110 '
#2960000
0"
#2965000
b1011111 ,
b100101000 )
1"
#2966000
b1011111 '
#2970000
0"
#2975000
b1100000 ,
b100101001 )
1"
#2976000
b1100000 '
#2980000
0"
#2985000
b1100001 ,
b100101010 )
1"
#2986000
b1100001 '
#2990000
0"
#2995000
b1100010 ,
b100101011 )
1"
#2996000
b1100010 '
#3000000
0"
#3005000
b1100011 ,
b100101100 )
1"
#3006000
b1100011 '
#3010000
0"
#3015000
b0 ,
b100101101 )
1"
#3016000
b1100100 '
#3020000
b0 '
b1100100 /
b110001001100000011000000100000011100000110010101110010011000110110010101101110011101000010000001100100011101010111010001111001 0
b1100100 #
b1100100 +
0"
#3025000
1!
b1 ,
b100101110 )
1-
b110001001100000011000000100000011100000110010101110010011000110110010101101110011101000010000001100100011101010111010001111001 .
1$
1"
#3026000
b1 '
