advanced/Lab01_sram_mul/sram_mul.v
// ============================================================
// SRAM Matrix Multiplication Accelerator
// ------------------------------------------------------------
// Function:
//   C = A * B
//
// Matrix size:
//   A: 4 x 4
//   B: 4 x 4
//   C: 4 x 4
//
// Data layout:
//   A SRAM:
//     A_addr = i returns one row tile:
//       {A[i][3], A[i][2], A[i][1], A[i][0]}
//
//   B SRAM:
//     B_addr = j returns one column tile:
//       {B[3][j], B[2][j], B[1][j], B[0][j]}
//
//   C SRAM:
//     C_addr = i * 4 + j
//     C_wdata = dot(A row i, B column j)
//
// Notes:
//   - A and B data are signed int8.
//   - Dot-product result uses signed 18-bit.
//   - SRAM control signals are assumed active-low:
//       *_cen = 0 : SRAM enabled
//       C_wen = 0 : write C SRAM
//   - A/B SRAM read latency is assumed to be 1 cycle.
// ============================================================

module sram_mul (
    input  wire clk,
    input  wire rst_n,

    input  wire start,
    output reg  done,

    // -----------------------------
    // A SRAM read port
    // -----------------------------
    output reg  [1:0]  A_addr,
    input  wire [31:0] A_rdata,

    // -----------------------------
    // B SRAM read port
    // -----------------------------
    output reg  [1:0]  B_addr,
    input  wire [31:0] B_rdata,

    // -----------------------------
    // C SRAM write port
    // -----------------------------
    output reg         C_cen,
    output reg         C_wen,
    output reg  [3:0]  C_addr,
    output reg  [17:0] C_wdata
);

// ========================================================
// FSM states
// ========================================================
localparam S_IDLE  = 3'd0;
localparam S_READ  = 3'd1;
localparam S_WAIT  = 3'd2;
localparam S_CALC  = 3'd3;
localparam S_WRITE = 3'd4;
localparam S_NEXT  = 3'd5;
localparam S_DONE  = 3'd6;

reg [2:0] state, next_state;

// Matrix indices
reg [1:0] row_idx;
reg [1:0] col_idx;

// Registered SRAM read data
reg [31:0] A_tile_reg;
reg [31:0] B_tile_reg;

// Dot-product result
wire signed [17:0] dot_result;

// ========================================================
// 4-element int8 dot product
// ========================================================
dot4_int8 u_dot4 (
    .a_vec(A_tile_reg),
    .b_vec(B_tile_reg),
    .result(dot_result)
);

// ========================================================
// FSM state register
// ========================================================
always @(posedge clk or negedge rst_n) begin
    if (!rst_n) begin
        state <= S_IDLE;
    end else begin
        state <= next_state;
    end
end

// ========================================================
// FSM next-state logic
// ========================================================
always @(*) begin
    next_state = state;

    case (state)
        S_IDLE: begin
            if (start) begin
                next_state = S_READ;
            end
        end

        S_READ: begin
            next_state = S_WAIT;
        end

        S_WAIT: begin
            next_state = S_CALC;
        end

        S_CALC: begin
            next_state = S_WRITE;
        end

        S_WRITE: begin
            next_state = S_NEXT;
        end

        S_NEXT: begin
            if ((row_idx == 2'd3) && (col_idx == 2'd3)) begin
                next_state = S_DONE;
            end else begin
                next_state = S_READ;
            end
        end

        S_DONE: begin
            next_state = S_IDLE;
        end

        default: begin
            next_state = S_IDLE;
        end
    endcase
end

// ========================================================
// Datapath and SRAM control
// ========================================================
always @(posedge clk or negedge rst_n) begin
    if (!rst_n) begin
        row_idx    <= 2'd0;
        col_idx    <= 2'd0;

        A_tile_reg <= 32'd0;
        B_tile_reg <= 32'd0;

        A_addr     <= 2'd0;
        B_addr     <= 2'd0;
        C_addr     <= 4'd0;

        C_cen      <= 1'b1;
        C_wen      <= 1'b1;
        C_wdata    <= 18'd0;

        done       <= 1'b0;
    end
    else begin
        // Default inactive values
        C_cen <= 1'b1;
        C_wen <= 1'b1;
        done  <= 1'b0;

        case (state)
            S_IDLE: begin
                if (start) begin
                    row_idx <= 2'd0;
                    col_idx <= 2'd0;
                end
            end

            S_READ: begin
                // Issue read addresses.
                A_addr <= row_idx;
                B_addr <= col_idx;
            end

            S_WAIT: begin
                // Wait for SRAM read data to be available in the next cycle.
            end

            S_CALC: begin
                // Capture SRAM outputs.
                A_tile_reg <= A_rdata;
                B_tile_reg <= B_rdata;
            end

            S_WRITE: begin
                // Write C[row_idx][col_idx].
                C_cen   <= 1'b0;
                C_wen   <= 1'b0;
                C_addr  <= {row_idx, col_idx};  // row_idx * 4 + col_idx
                C_wdata <= dot_result;
            end

            S_NEXT: begin
                if (col_idx == 2'd3) begin
                    col_idx <= 2'd0;
                    row_idx <= row_idx + 2'd1;
                end
                else begin
                    col_idx <= col_idx + 2'd1;
                end
            end

            S_DONE: begin
                done <= 1'b1;
            end

            default: begin
                row_idx <= 2'd0;
                col_idx <= 2'd0;
            end
        endcase
    end
end

endmodule


// ============================================================
// 4-way signed int8 dot product
// ------------------------------------------------------------
// Input packing:
//   a_vec = {a3, a2, a1, a0}
//   b_vec = {b3, b2, b1, b0}
//
// Output:
//   result = a0*b0 + a1*b1 + a2*b2 + a3*b3
// ============================================================
module dot4_int8 (
    input  wire [31:0] a_vec,
    input  wire [31:0] b_vec,
    output wire signed [17:0] result
);

wire signed [17:0] p0;
wire signed [17:0] p1;
wire signed [17:0] p2;
wire signed [17:0] p3;

assign p0 = $signed(a_vec[7:0])   * $signed(b_vec[7:0]);
assign p1 = $signed(a_vec[15:8])  * $signed(b_vec[15:8]);
assign p2 = $signed(a_vec[23:16]) * $signed(b_vec[23:16]);
assign p3 = $signed(a_vec[31:24]) * $signed(b_vec[31:24]);

assign result = p0 + p1 + p2 + p3;

endmodule

advanced/Lab01_sram_mul/tb.v
`timescale 1ns/1ps
module tb_sram_mul;
  reg clk, rst_n, start;
  wire done;
  wire C_cen, C_wen;
  wire [1:0] A_addr, B_addr;
  reg  [31:0] A_rdata, B_rdata;
  wire [3:0] C_addr;
  wire [17:0] C_wdata;

  reg [31:0] A_mem [0:3];
  reg [31:0] B_mem [0:3];
  reg signed [17:0] C_got [0:15];
  reg signed [17:0] C_exp [0:15];
  integer log_fd, result_fd, any_fail, reported_error, i, cycle, done_seen;

  sram_mul dut(
    .clk(clk), .rst_n(rst_n), .start(start), .done(done),
    .A_addr(A_addr), .A_rdata(A_rdata),
    .B_addr(B_addr), .B_rdata(B_rdata),
    .C_cen(C_cen), .C_wen(C_wen), .C_addr(C_addr), .C_wdata(C_wdata)
  );

  always #5 clk = ~clk;
  always @(*) begin
    A_rdata = A_mem[A_addr];
    B_rdata = B_mem[B_addr];
  end

  always @(posedge clk) begin
    #1;
    if (!C_cen && !C_wen) C_got[C_addr] = C_wdata;
  end

  initial begin
    log_fd = $fopen("sim/log.txt", "w");
    result_fd = $fopen("sim/result.txt", "w");
    $dumpfile("sim/wave.vcd");
    $dumpvars(0, tb_sram_mul);
    $display("##SEC_STUDENT_CAN_SEE");
    $fdisplay(log_fd, "##SEC_STUDENT_CAN_SEE");
        // GOLDEN_CASE_SUMMARY_BEGIN
        $display("[CASE 1] checks start/done handshake");
        $fdisplay(log_fd,"[CASE 1] checks start/done handshake");
        $display("[CASE 2] checks all output matrix entries, including signed values");
        $fdisplay(log_fd,"[CASE 2] checks all output matrix entries, including signed values");
        // GOLDEN_CASE_SUMMARY_END



    clk = 0; rst_n = 0; start = 0; any_fail = 0; reported_error = 0;
    for (i = 0; i < 16; i = i + 1) begin C_got[i] = 0; C_exp[i] = 0; end

    A_mem[0] = {8'sd4, 8'sd3, 8'sd2, 8'sd1};
    A_mem[1] = {8'sd8, 8'sd7, 8'sd6, 8'sd5};
    A_mem[2] = {8'sd1, 8'sd1, 8'sd1, 8'sd1};
    A_mem[3] = {8'sd3, -8'sd1, 8'sd0, 8'sd2};

    B_mem[0] = {8'sd2, 8'sd1, 8'sd0, 8'sd1};
    B_mem[1] = {8'sd1, 8'sd0, 8'sd1, 8'sd0};
    B_mem[2] = {8'sd0, 8'sd1, 8'sd2, 8'sd2};
    B_mem[3] = {8'sd4, 8'sd3, 8'sd2, 8'sd1};

    C_exp[0]=18'sd12; C_exp[1]=18'sd6;  C_exp[2]=18'sd9;  C_exp[3]=18'sd30;
    C_exp[4]=18'sd28; C_exp[5]=18'sd14; C_exp[6]=18'sd29; C_exp[7]=18'sd70;
    C_exp[8]=18'sd4;  C_exp[9]=18'sd2;  C_exp[10]=18'sd5; C_exp[11]=18'sd10;
    C_exp[12]=18'sd7; C_exp[13]=18'sd3; C_exp[14]=18'sd3; C_exp[15]=18'sd11;

    repeat (3) @(posedge clk);
    @(negedge clk); rst_n = 1;
    @(negedge clk); start = 1;
    @(posedge clk);
    @(negedge clk); start = 0;

    cycle = 0; done_seen = 0;
    while (!done_seen && cycle < 200) begin
      @(posedge clk);
      #1;
      if (done) done_seen = 1;
      cycle = cycle + 1;
    end

    if (!done_seen) begin
      any_fail = 1;
      if (!reported_error) begin
        reported_error = 1;
        $display("[ERROR] timeout waiting for done after %0d cycles start=%b done=%b", cycle, start, done);
        $fdisplay(log_fd, "[ERROR] timeout waiting for done after %0d cycles start=%b done=%b", cycle, start, done);
      end
    end

    for (i = 0; i < 16; i = i + 1) begin
      if (C_got[i] !== C_exp[i]) begin
        any_fail = 1;
        if (!reported_error) begin
          reported_error = 1;
          $display("[ERROR] C[%0d] row=%0d col=%0d expected=%0d got=%0d", i, i/4, i%4, C_exp[i], C_got[i]);
          $fdisplay(log_fd, "[ERROR] C[%0d] row=%0d col=%0d expected=%0d got=%0d", i, i/4, i%4, C_exp[i], C_got[i]);
        end
      end
    end

    if (!any_fail) begin
      $display("[PASS] sram_mul");
      $fdisplay(log_fd, "[PASS] sram_mul");
    end

    $display("##END_STUDENT_CAN_SEE");
    $fdisplay(log_fd, "##END_STUDENT_CAN_SEE");
    if (any_fail) $fdisplay(result_fd, "fail"); else $fdisplay(result_fd, "pass");
    $fclose(log_fd); $fclose(result_fd); #1; $finish;
  end
endmodule

advanced/Lab01_sram_mul/golden/golden_wave.vcd
$date
	Mon May 11 09:39:55 2026
$end
$version
	Icarus Verilog
$end
$timescale
	1ps
$end
$scope module tb_sram_mul $end
$var wire 1 ! done $end
$var wire 1 " C_wen $end
$var wire 18 # C_wdata [17:0] $end
$var wire 1 $ C_cen $end
$var wire 4 % C_addr [3:0] $end
$var wire 2 & B_addr [1:0] $end
$var wire 2 ' A_addr [1:0] $end
$var reg 32 ( A_rdata [31:0] $end
$var reg 32 ) B_rdata [31:0] $end
$var reg 1 * clk $end
$var reg 1 + rst_n $end
$var reg 1 , start $end
$var integer 32 - any_fail [31:0] $end
$var integer 32 . cycle [31:0] $end
$var integer 32 / done_seen [31:0] $end
$var integer 32 0 i [31:0] $end
$var integer 32 1 log_fd [31:0] $end
$var integer 32 2 reported_error [31:0] $end
$var integer 32 3 result_fd [31:0] $end
$scope module dut $end
$var wire 32 4 A_rdata [31:0] $end
$var wire 32 5 B_rdata [31:0] $end
$var wire 1 * clk $end
$var wire 1 + rst_n $end
$var wire 1 , start $end
$var wire 18 6 dot_result [17:0] $end
$var parameter 3 7 S_CALC $end
$var parameter 3 8 S_DONE $end
$var parameter 3 9 S_IDLE $end
$var parameter 3 : S_NEXT $end
$var parameter 3 ; S_READ $end
$var parameter 3 < S_WAIT $end
$var parameter 3 = S_WRITE $end
$var reg 2 > A_addr [1:0] $end
$var reg 32 ? A_tile_reg [31:0] $end
$var reg 2 @ B_addr [1:0] $end
$var reg 32 A B_tile_reg [31:0] $end
$var reg 4 B C_addr [3:0] $end
$var reg 1 $ C_cen $end
$var reg 18 C C_wdata [17:0] $end
$var reg 1 " C_wen $end
$var reg 2 D col_idx [1:0] $end
$var reg 1 ! done $end
$var reg 3 E next_state [2:0] $end
$var reg 2 F row_idx [1:0] $end
$var reg 3 G state [2:0] $end
$scope module u_dot4 $end
$var wire 32 H a_vec [31:0] $end
$var wire 32 I b_vec [31:0] $end
$var wire 18 J result [17:0] $end
$var wire 18 K p3 [17:0] $end
$var wire 18 L p2 [17:0] $end
$var wire 18 M p1 [17:0] $end
$var wire 18 N p0 [17:0] $end
$upscope $end
$upscope $end
$upscope $end
$enddefinitions $end
$comment Show the parameter values. $end
$dumpall
b100 =
b10 <
b1 ;
b101 :
b0 9
b110 8
b11 7
$end
#0
$dumpvars
b0 N
b0 M
b0 L
b0 K
b0 J
b0 I
b0 H
b0 G
b0 F
b0 E
b0 D
b0 C
b0 B
b0 A
b0 @
b0 ?
b0 >
b0 6
b10000000010000000000000001 5
b100000000110000001000000001 4
b10000000000000000000000000000100 3
b0 2
b10000000000000000000000000000011 1
b10000 0
bx /
bx .
b0 -
0,
0+
0*
b10000000010000000000000001 )
b100000000110000001000000001 (
b0 '
b0 &
b0 %
1$
b0 #
1"
0!
$end
#5000
1*
#10000
0*
#15000
1*
#20000
0*
#25000
1*
#30000
1+
0*
#35000
1*
#40000
b1 E
1,
0*
#45000
b10 E
b1 G
1*
#50000
b10 E
b0 /
b0 .
0,
0*
#55000
b11 E
b10 G
1*
#56000
b1 .
#60000
0*
#65000
b100 E
b11 G
1*
#66000
b10 .
#70000
0*
#75000
b101 E
b1 N
b11 L
b1100 6
b1100 J
b1000 K
b100 G
b10000000010000000000000001 A
b10000000010000000000000001 I
b100000000110000001000000001 ?
b100000000110000001000000001 H
1*
#76000
b11 .
#80000
0*
#85000
b1 E
b1100 #
b1100 C
0"
0$
b101 G
1*
#86000
b100 .
#90000
0*
#95000
b10 E
b1 G
b1 D
1"
1$
1*
#96000
b101 .
#100000
0*
#105000
b1000000000000000100000000 )
b1000000000000000100000000 5
b11 E
b1 &
b1 @
b10 G
1*
#106000
b110 .
#110000
0*
#115000
b100 E
b11 G
1*
#116000
b111 .
#120000
0*
#125000
b0 N
b10 M
b0 L
b110 6
b110 J
b100 K
b101 E
b1000000000000000100000000 A
b1000000000000000100000000 I
b100 G
1*
#126000
b1000 .
#130000
0*
#135000
b1 E
b101 G
b110 #
b110 C
b1 %
b1 B
0"
0$
1*
#136000
b1001 .
#140000
0*
#145000
b10 E
b10 D
1"
1$
b1 G
1*
#146000
b1010 .
#150000
0*
#155000
b11 E
b10000001000000010 )
b10000001000000010 5
b10 G
b10 &
b10 @
1*
#156000
b1011 .
#160000
0*
#165000
b100 E
b11 G
1*
#166000
b1100 .
#170000
0*
#175000
b101 E
b10 N
b100 M
b11 L
b1001 6
b1001 J
b0 K
b100 G
b10000001000000010 A
b10000001000000010 I
1*
#176000
b1101 .
#180000
0*
#185000
b1 E
b1001 #
b1001 C
b10 %
b10 B
0"
0$
b101 G
1*
#186000
b1110 .
#190000
0*
#195000
b10 E
b1 G
b11 D
1"
1$
1*
#196000
b1111 .
#200000
0*
#205000
b100000000110000001000000001 )
b100000000110000001000000001 5
b11 E
b11 &
b11 @
b10 G
1*
#206000
b10000 .
#210000
0*
#215000
b100 E
b11 G
1*
#216000
b10001 .
#220000
0*
#225000
b1 N
b1001 L
b11110 6
b11110 J
b10000 K
b101 E
b100000000110000001000000001 A
b100000000110000001000000001 I
b100 G
1*
#226000
b10010 .
#230000
0*
#235000
b1 E
b101 G
b11110 #
b11110 C
b11 %
b11 B
0"
0$
1*
#236000
b10011 .
#240000
0*
#245000
b10 E
b1 F
b0 D
1"
1$
b1 G
1*
#246000
b10100 .
#250000
0*
#255000
b11 E
b10000000010000000000000001 )
b10000000010000000000000001 5
b1000000001110000011000000101 (
b1000000001110000011000000101 4
b10 G
b0 &
b0 @
b1 '
b1 >
1*
#256000
b10101 .
#260000
0*
#265000
b100 E
b11 G
1*
#266000
b10110 .
#270000
0*
#275000
b101 E
b101 N
b0 M
b111 L
b11100 6
b11100 J
b10000 K
b100 G
b10000000010000000000000001 A
b10000000010000000000000001 I
b1000000001110000011000000101 ?
b1000000001110000011000000101 H
1*
#276000
b10111 .
#280000
0*
#285000
b1 E
b11100 #
b11100 C
b100 %
b100 B
0"
0$
b101 G
1*
#286000
b11000 .
#290000
0*
#295000
b10 E
b1 G
b1 D
1"
1$
1*
#296000
b11001 .
#300000
0*
#305000
b1000000000000000100000000 )
b1000000000000000100000000 5
b11 E
b1 &
b1 @
b10 G
1*
#306000
b11010 .
#310000
0*
#315000
b100 E
b11 G
1*
#316000
b11011 .
#320000
0*
#325000
b0 N
b110 M
b0 L
b1110 6
b1110 J
b1000 K
b101 E
b1000000000000000100000000 A
b1000000000000000100000000 I
b100 G
1*
#326000
b11100 .
#330000
0*
#335000
b1 E
b101 G
b1110 #
b1110 C
b101 %
b101 B
0"
0$
1*
#336000
b11101 .
#340000
0*
#345000
b10 E
b10 D
1"
1$
b1 G
1*
#346000
b11110 .
#350000
0*
#355000
b11 E
b10000001000000010 )
b10000001000000010 5
b10 G
b10 &
b10 @
1*
#356000
b11111 .
#360000
0*
#365000
b100 E
b11 G
1*
#366000
b100000 .
#370000
0*
#375000
b101 E
b1010 N
b1100 M
b111 L
b11101 6
b11101 J
b0 K
b100 G
b10000001000000010 A
b10000001000000010 I
1*
#376000
b100001 .
#380000
0*
#385000
b1 E
b11101 #
b11101 C
b110 %
b110 B
0"
0$
b101 G
1*
#386000
b100010 .
#390000
0*
#395000
b10 E
b1 G
b11 D
1"
1$
1*
#396000
b100011 .
#400000
0*
#405000
b100000000110000001000000001 )
b100000000110000001000000001 5
b11 E
b11 &
b11 @
b10 G
1*
#406000
b100100 .
#410000
0*
#415000
b100 E
b11 G
1*
#416000
b100101 .
#420000
0*
#425000
b101 N
b10101 L
b1000110 6
b1000110 J
b100000 K
b101 E
b100000000110000001000000001 A
b100000000110000001000000001 I
b100 G
1*
#426000
b100110 .
#430000
0*
#435000
b1 E
b101 G
b1000110 #
b1000110 C
b111 %
b111 B
0"
0$
1*
#436000
b100111 .
#440000
0*
#445000
b10 E
b10 F
b0 D
1"
1$
b1 G
1*
#446000
b101000 .
#450000
0*
#455000
b11 E
b10000000010000000000000001 )
b10000000010000000000000001 5
b1000000010000000100000001 (
b1000000010000000100000001 4
b10 G
b0 &
b0 @
b10 '
b10 >
1*
#456000
b101001 .
#460000
0*
#465000
b100 E
b11 G
1*
#466000
b101010 .
#470000
0*
#475000
b101 E
b1 N
b0 M
b1 L
b100 6
b100 J
b10 K
b100 G
b10000000010000000000000001 A
b10000000010000000000000001 I
b1000000010000000100000001 ?
b1000000010000000100000001 H
1*
#476000
b101011 .
#480000
0*
#485000
b1 E
b100 #
b100 C
b1000 %
b1000 B
0"
0$
b101 G
1*
#486000
b101100 .
#490000
0*
#495000
b10 E
b1 G
b1 D
1"
1$
1*
#496000
b101101 .
#500000
0*
#505000
b1000000000000000100000000 )
b1000000000000000100000000 5
b11 E
b1 &
b1 @
b10 G
1*
#506000
b101110 .
#510000
0*
#515000
b100 E
b11 G
1*
#516000
b101111 .
#520000
0*
#525000
b0 N
b1 M
b0 L
b10 6
b10 J
b1 K
b101 E
b1000000000000000100000000 A
b1000000000000000100000000 I
b100 G
1*
#526000
b110000 .
#530000
0*
#535000
b1 E
b101 G
b10 #
b10 C
b1001 %
b1001 B
0"
0$
1*
#536000
b110001 .
#540000
0*
#545000
b10 E
b10 D
1"
1$
b1 G
1*
#546000
b110010 .
#550000
0*
#555000
b11 E
b10000001000000010 )
b10000001000000010 5
b10 G
b10 &
b10 @
1*
#556000
b110011 .
#560000
0*
#565000
b100 E
b11 G
1*
#566000
b110100 .
#570000
0*
#575000
b101 E
b10 N
b10 M
b1 L
b101 6
b101 J
b0 K
b100 G
b10000001000000010 A
b10000001000000010 I
1*
#576000
b110101 .
#580000
0*
#585000
b1 E
b101 #
b101 C
b1010 %
b1010 B
0"
0$
b101 G
1*
#586000
b110110 .
#590000
0*
#595000
b10 E
b1 G
b11 D
1"
1$
1*
#596000
b110111 .
#600000
0*
#605000
b100000000110000001000000001 )
b100000000110000001000000001 5
b11 E
b11 &
b11 @
b10 G
1*
#606000
b111000 .
#610000
0*
#615000
b100 E
b11 G
1*
#616000
b111001 .
#620000
0*
#625000
b1 N
b11 L
b1010 6
b1010 J
b100 K
b101 E
b100000000110000001000000001 A
b100000000110000001000000001 I
b100 G
1*
#626000
b111010 .
#630000
0*
#635000
b1 E
b101 G
b1010 #
b1010 C
b1011 %
b1011 B
0"
0$
1*
#636000
b111011 .
#640000
0*
#645000
b10 E
b11 F
b0 D
1"
1$
b1 G
1*
#646000
b111100 .
#650000
0*
#655000
b11 E
b10000000010000000000000001 )
b10000000010000000000000001 5
b11111111110000000000000010 (
b11111111110000000000000010 4
b10 G
b0 &
b0 @
b11 '
b11 >
1*
#656000
b111101 .
#660000
0*
#665000
b100 E
b11 G
1*
#666000
b111110 .
#670000
0*
#675000
b101 E
b10 N
b0 M
b111111111111111111 L
b111 6
b111 J
b110 K
b100 G
b10000000010000000000000001 A
b10000000010000000000000001 I
b11111111110000000000000010 ?
b11111111110000000000000010 H
1*
#676000
b111111 .
#680000
0*
#685000
b1 E
b111 #
b111 C
b1100 %
b1100 B
0"
0$
b101 G
1*
#686000
b1000000 .
#690000
0*
#695000
b10 E
b1 G
b1 D
1"
1$
1*
#696000
b1000001 .
#700000
0*
#705000
b1000000000000000100000000 )
b1000000000000000100000000 5
b11 E
b1 &
b1 @
b10 G
1*
#706000
b1000010 .
#710000
0*
#715000
b100 E
b11 G
1*
#716000
b1000011 .
#720000
0*
#725000
b0 N
b0 L
b11 6
b11 J
b11 K
b101 E
b1000000000000000100000000 A
b1000000000000000100000000 I
b100 G
1*
#726000
b1000100 .
#730000
0*
#735000
b1 E
b101 G
b11 #
b11 C
b1101 %
b1101 B
0"
0$
1*
#736000
b1000101 .
#740000
0*
#745000
b10 E
b10 D
1"
1$
b1 G
1*
#746000
b1000110 .
#750000
0*
#755000
b11 E
b10000001000000010 )
b10000001000000010 5
b10 G
b10 &
b10 @
1*
#756000
b1000111 .
#760000
0*
#765000
b100 E
b11 G
1*
#766000
b1001000 .
#770000
0*
#775000
b101 E
b100 N
b111111111111111111 L
b11 6
b11 J
b0 K
b100 G
b10000001000000010 A
b10000001000000010 I
1*
#776000
b1001001 .
#780000
0*
#785000
b1 E
b1110 %
b1110 B
0"
0$
b101 G
1*
#786000
b1001010 .
#790000
0*
#795000
b10 E
b1 G
b11 D
1"
1$
1*
#796000
b1001011 .
#800000
0*
#805000
b100000000110000001000000001 )
b100000000110000001000000001 5
b11 E
b11 &
b11 @
b10 G
1*
#806000
b1001100 .
#810000
0*
#815000
b100 E
b11 G
1*
#816000
b1001101 .
#820000
0*
#825000
b10 N
b111111111111111101 L
b1011 6
b1011 J
b1100 K
b101 E
b100000000110000001000000001 A
b100000000110000001000000001 I
b100 G
1*
#826000
b1001110 .
#830000
0*
#835000
b110 E
b101 G
b1011 #
b1011 C
b1111 %
b1111 B
0"
0$
1*
#836000
b1001111 .
#840000
0*
#845000
b0 E
b0 F
b0 D
1"
1$
b110 G
1*
#846000
b1010000 .
#850000
0*
#855000
b0 G
1!
1*
#856000
b10000 0
b1010001 .
b1 /
