fpga_lab/Lab05_blockram/blockram.v
module blockram #(
    parameter ADDR_WIDTH = 15,
    parameter DATA_WIDTH = 12,
    parameter DEPTH      = 160 * 120
)(
    input  wire                    clk,

    // Read port
    input  wire [ADDR_WIDTH-1:0]   raddr,
    output reg  [DATA_WIDTH-1:0]   rdata,

    // Write port
    input  wire                    we,
    input  wire [ADDR_WIDTH-1:0]   waddr,
    input  wire [DATA_WIDTH-1:0]   wdata
);

// TODO: declare the 2D memory array
// Which has DEPTH rows, each row has DATA_WIDTH bits
reg [... : 0] mem [0 : ...]; 

always @(posedge clk) begin
    // Write port
    if (we) begin
        mem[waddr] <= wdata;
    end

    // Read port
    rdata <= mem[raddr];
end

endmodule

fpga_lab/Lab05_blockram/tb.v
`timescale 1ns/1ps

module tb_blockram;

    reg clk;
    reg [3:0] raddr;
    wire [11:0] rdata;
    reg we;
    reg [3:0] waddr;
    reg [11:0] wdata;

    integer errors;
    integer log_fd;
    integer result_fd;
    integer pattern;

    blockram #(
        .ADDR_WIDTH(4),
        .DATA_WIDTH(12),
        .DEPTH(16)
    ) dut (
        .clk(clk),
        .raddr(raddr),
        .rdata(rdata),
        .we(we),
        .waddr(waddr),
        .wdata(wdata)
    );

    initial begin
        clk = 0;
        forever #5 clk = ~clk;
    end

    task write_mem;
        input [3:0] addr;
        input [11:0] data;
        begin
            @(negedge clk);
            waddr = addr;
            wdata = data;
            we = 1'b1;
            @(posedge clk);
            #1;
            @(negedge clk);
            we = 1'b0;
            waddr = 4'd0;
            wdata = 12'd0;
        end
    endtask

    task read_mem_check;
        input [3:0] addr;
        input [11:0] expected;
        begin
            pattern = pattern + 1;
            @(negedge clk);
            raddr = addr;
            @(posedge clk);
            #1;
            if (rdata !== expected) begin
                if (errors == 0) $display("[ERROR] pattern %0d (sync read): addr=%0d expected rdata=%h got=%h", pattern, addr, expected, rdata);
                if (errors == 0) $fdisplay(log_fd, "[ERROR] pattern %0d (sync read): addr=%0d expected rdata=%h got=%h", pattern, addr, expected, rdata);
                errors = errors + 1;
            end
        end
    endtask

    task same_addr_read_write_check;
        input [3:0] addr;
        input [11:0] old_data;
        input [11:0] new_data;
        begin
            pattern = pattern + 1;
            @(negedge clk);
            raddr = addr;
            waddr = addr;
            wdata = new_data;
            we = 1'b1;
            @(posedge clk);
            #1;
            if (rdata !== old_data) begin
                if (errors == 0) $display("[ERROR] pattern %0d (same-address read/write): expected old data got=%h", pattern, rdata);
                if (errors == 0) $fdisplay(log_fd, "[ERROR] pattern %0d (same-address read/write): expected old data got=%h", pattern, rdata);
                errors = errors + 1;
            end
            @(negedge clk);
            we = 1'b0;
            waddr = 4'd0;
            wdata = 12'd0;
            @(posedge clk);
            #1;
            if (rdata !== new_data) begin
                if (errors == 0) $display("[ERROR] pattern %0d (same-address next read): expected new data got=%h", pattern, rdata);
                if (errors == 0) $fdisplay(log_fd, "[ERROR] pattern %0d (same-address next read): expected new data got=%h", pattern, rdata);
                errors = errors + 1;
            end
        end
    endtask

    task diff_addr_read_write_check;
        input [3:0] read_addr;
        input [11:0] read_expected;
        input [3:0] write_addr;
        input [11:0] write_data;
        begin
            pattern = pattern + 1;
            @(negedge clk);
            raddr = read_addr;
            waddr = write_addr;
            wdata = write_data;
            we = 1'b1;
            @(posedge clk);
            #1;
            if (rdata !== read_expected) begin
                if (errors == 0) $display("[ERROR] pattern %0d (different-address read/write): read data changed unexpectedly got=%h", pattern, rdata);
                if (errors == 0) $fdisplay(log_fd, "[ERROR] pattern %0d (different-address read/write): read data changed unexpectedly got=%h", pattern, rdata);
                errors = errors + 1;
            end
            @(negedge clk);
            we = 1'b0;
            waddr = 4'd0;
            wdata = 12'd0;
        end
    endtask

    initial begin
        log_fd = $fopen("sim/log.txt", "w");
        result_fd = $fopen("sim/result.txt", "w");
        $dumpfile("sim/wave.vcd");
        $dumpvars(0, tb_blockram);
        $display("##SEC_STUDENT_CAN_SEE");
        $fdisplay(log_fd, "##SEC_STUDENT_CAN_SEE");
        // GOLDEN_CASE_SUMMARY_BEGIN
        $display("[CASE 1-3] checks synchronous write/readback on multiple addresses");
        $fdisplay(log_fd,"[CASE 1-3] checks synchronous write/readback on multiple addresses");
        $display("[CASE 4] checks overwrite on the same address");
        $fdisplay(log_fd,"[CASE 4] checks overwrite on the same address");
        $display("[CASE 5] checks same-address read/write returns old data first");
        $fdisplay(log_fd,"[CASE 5] checks same-address read/write returns old data first");
        $display("[CASE 6] checks different-address read/write does not disturb read data");
        $fdisplay(log_fd,"[CASE 6] checks different-address read/write does not disturb read data");
        $display("[CASE 7] checks first and last valid depth addresses");
        $fdisplay(log_fd,"[CASE 7] checks first and last valid depth addresses");
        // GOLDEN_CASE_SUMMARY_END

        errors = 0;
        pattern = 0;
        raddr = 0;
        we = 0;
        waddr = 0;
        wdata = 0;

        repeat (2) @(posedge clk);

        write_mem(4'd2, 12'h123);
        write_mem(4'd5, 12'hABC);
        write_mem(4'd9, 12'h789);

        read_mem_check(4'd2, 12'h123);
        read_mem_check(4'd5, 12'hABC);
        read_mem_check(4'd9, 12'h789);

        write_mem(4'd2, 12'h456);
        read_mem_check(4'd2, 12'h456);

        same_addr_read_write_check(4'd5, 12'hABC, 12'h555);
        diff_addr_read_write_check(4'd2, 12'h456, 4'd9, 12'h999);
        read_mem_check(4'd9, 12'h999);

        write_mem(4'd0, 12'h00D);
        write_mem(4'd15, 12'hF15);
        read_mem_check(4'd0, 12'h00D);
        read_mem_check(4'd15, 12'hF15);

        if (errors == 0) begin
            $display("[PASS] blockram");
            $fdisplay(log_fd, "[PASS] blockram");
            $fdisplay(result_fd, "pass");
        end else begin
            $display("[FAIL] blockram, errors = %0d", errors);
            $fdisplay(log_fd, "[FAIL] blockram, errors = %0d", errors);
            $fdisplay(result_fd, "fail");
        end

        $display("##END_STUDENT_CAN_SEE");
        $fdisplay(log_fd, "##END_STUDENT_CAN_SEE");
        $fclose(log_fd);
        $fclose(result_fd);

        $finish;
    end

endmodule

fpga_lab/Lab07_blockram/golden/golden_wave.vcd
$date
	Mon May 11 15:51:23 2026
$end
$version
	Icarus Verilog
$end
$timescale
	1ps
$end
$scope module tb_blockram $end
$var wire 12 ! rdata [11:0] $end
$var reg 1 " clk $end
$var reg 4 # raddr [3:0] $end
$var reg 4 $ waddr [3:0] $end
$var reg 12 % wdata [11:0] $end
$var reg 1 & we $end
$var integer 32 ' errors [31:0] $end
$var integer 32 ( log_fd [31:0] $end
$var integer 32 ) pattern [31:0] $end
$var integer 32 * result_fd [31:0] $end
$scope module dut $end
$var wire 1 " clk $end
$var wire 4 + raddr [3:0] $end
$var wire 4 , waddr [3:0] $end
$var wire 12 - wdata [11:0] $end
$var wire 1 & we $end
$var parameter 32 . ADDR_WIDTH $end
$var parameter 32 / DATA_WIDTH $end
$var parameter 32 0 DEPTH $end
$var reg 12 1 rdata [11:0] $end
$upscope $end
$scope task diff_addr_read_write_check $end
$var reg 4 2 read_addr [3:0] $end
$var reg 12 3 read_expected [11:0] $end
$var reg 4 4 write_addr [3:0] $end
$var reg 12 5 write_data [11:0] $end
$upscope $end
$scope task read_mem_check $end
$var reg 4 6 addr [3:0] $end
$var reg 12 7 expected [11:0] $end
$upscope $end
$scope task same_addr_read_write_check $end
$var reg 4 8 addr [3:0] $end
$var reg 12 9 new_data [11:0] $end
$var reg 12 : old_data [11:0] $end
$upscope $end
$scope task write_mem $end
$var reg 4 ; addr [3:0] $end
$var reg 12 < data [11:0] $end
$upscope $end
$upscope $end
$enddefinitions $end
$comment Show the parameter values. $end
$dumpall
b10000 0
b1100 /
b100 .
$end
#0
$dumpvars
bx <
bx ;
bx :
bx 9
bx 8
bx 7
bx 6
bx 5
bx 4
bx 3
bx 2
bx 1
b0 -
b0 ,
b0 +
b10000000000000000000000000000100 *
b0 )
b10000000000000000000000000000011 (
b0 '
0&
b0 %
b0 $
b0 #
0"
bx !
$end
#5000
1"
#10000
0"
#15000
b100100011 <
b10 ;
1"
#20000
1&
b100100011 %
b100100011 -
b10 $
b10 ,
0"
#25000
1"
#30000
b101010111100 <
b101 ;
b0 %
b0 -
b0 $
b0 ,
0&
0"
#35000
1"
#40000
1&
b101010111100 %
b101010111100 -
b101 $
b101 ,
0"
#45000
1"
#50000
b11110001001 <
b1001 ;
b0 %
b0 -
b0 $
b0 ,
0&
0"
#55000
1"
#60000
1&
b11110001001 %
b11110001001 -
b1001 $
b1001 ,
0"
#65000
1"
#70000
b1 )
b100100011 7
b10 6
b0 %
b0 -
b0 $
b0 ,
0&
0"
#75000
1"
#80000
b10 #
b10 +
0"
#85000
b100100011 !
b100100011 1
1"
#86000
b10 )
b101010111100 7
b101 6
#90000
b101 #
b101 +
0"
#95000
b101010111100 !
b101010111100 1
1"
#96000
b11 )
b11110001001 7
b1001 6
#100000
b1001 #
b1001 +
0"
#105000
b11110001001 !
b11110001001 1
1"
#106000
b10001010110 <
b10 ;
#110000
1&
b10001010110 %
b10001010110 -
b10 $
b10 ,
0"
#115000
1"
#120000
b100 )
b10001010110 7
b10 6
b0 %
b0 -
b0 $
b0 ,
0&
0"
#125000
1"
#130000
b10 #
b10 +
0"
#135000
b10001010110 !
b10001010110 1
1"
#136000
b101 )
b10101010101 9
b101010111100 :
b101 8
#140000
1&
b10101010101 %
b10101010101 -
b101 $
b101 ,
b101 #
b101 +
0"
#145000
b101010111100 !
b101010111100 1
1"
#150000
b0 %
b0 -
b0 $
b0 ,
0&
0"
#155000
b10101010101 !
b10101010101 1
1"
#156000
b110 )
b100110011001 5
b1001 4
b10001010110 3
b10 2
#160000
1&
b100110011001 %
b100110011001 -
b1001 $
b1001 ,
b10 #
b10 +
0"
#165000
b10001010110 !
b10001010110 1
1"
#170000
b111 )
b100110011001 7
b1001 6
b0 %
b0 -
b0 $
b0 ,
0&
0"
#175000
1"
#180000
b1001 #
b1001 +
0"
#185000
b100110011001 !
b100110011001 1
1"
#186000
b1101 <
b0 ;
#190000
1&
b1101 %
b1101 -
0"
#195000
1"
#200000
b111100010101 <
b1111 ;
b0 %
b0 -
0&
0"
#205000
1"
#210000
1&
b111100010101 %
b111100010101 -
b1111 $
b1111 ,
0"
#215000
1"
#220000
b1000 )
b1101 7
b0 6
b0 %
b0 -
b0 $
b0 ,
0&
0"
#225000
1"
#230000
b0 #
b0 +
0"
#235000
b1101 !
b1101 1
1"
#236000
b1001 )
b111100010101 7
b1111 6
#240000
b1111 #
b1111 +
0"
#245000
b111100010101 !
b111100010101 1
1"
