practice/Lab07_gcd/gcd.v
module gcd (
    input        clk,
    input        rst_n,
    input        in_valid,
    input  [7:0] a,
    input  [7:0] b,
    output reg   out_valid,
    output reg [7:0] result
);

localparam IDLE = 2'd0;
localparam BUSY = 2'd1;
localparam DONE = 2'd2;

reg [1:0] S, S_nxt;
reg [7:0] x, x_nxt;
reg [7:0] y, y_nxt;

always @(*) begin
    S_nxt = S;
    x_nxt = x;
    y_nxt = y;

    case (S)
        IDLE: begin
            if (in_valid) begin
                x_nxt = a;
                y_nxt = b;
                S_nxt = BUSY;
            end
        end

        BUSY: begin
            // If either x or y is zero, we are done
            // Otherwise, subtract the smaller from the larger

            // To be completed
            if (...) begin
                ...;
            end else if (x > y) begin
                ...;
            end else begin
                ...;
            end
        end

        DONE: begin
            S_nxt = IDLE;
        end
    endcase
end

always @(posedge clk or negedge rst_n) begin
    if (!rst_n) begin
        S <= IDLE;
        x <= 8'd0;
        y <= 8'd0;
    end
    else begin
        S <= S_nxt;
        x <= x_nxt;
        y <= y_nxt;
    end
end

always @(*) begin
    out_valid = (S == DONE);
    result = (x == 0) ? y : x;
end

endmodule

practice/Lab05_gcd/tb.v
`timescale 1ns/1ps
module tb_gcd;
    reg clk, rst_n, in_valid;
    reg [7:0] a, b;
    wire out_valid;
    wire [7:0] result;
    integer errors, log_fd, result_fd, pattern;

    gcd dut (.clk(clk), .rst_n(rst_n), .in_valid(in_valid), .a(a), .b(b), .out_valid(out_valid), .result(result));
    initial begin clk = 0; forever #5 clk = ~clk; end

    task run_case;
        input [7:0] va, vb, expected;
        integer timeout;
        begin
            pattern = pattern + 1;
            @(negedge clk); a = va; b = vb; in_valid = 1'b1;
            @(posedge clk);
            @(negedge clk); in_valid = 1'b0; a = 8'd0; b = 8'd0;
            timeout = 0;
            while (!out_valid && timeout < 100) begin
                @(posedge clk); #1; timeout = timeout + 1;
            end
            if (!out_valid || result !== expected) begin
                if (errors == 0) $display("[ERROR] pattern %0d: gcd(%0d,%0d) expected=%0d got=%0d out_valid=%b timeout=%0d", pattern, va, vb, expected, result, out_valid, timeout);
                if (errors == 0) $fdisplay(log_fd, "[ERROR] pattern %0d: gcd(%0d,%0d) expected=%0d got=%0d out_valid=%b timeout=%0d", pattern, va, vb, expected, result, out_valid, timeout);
                errors = errors + 1;
            end
            @(posedge clk); #1;
        end
    endtask

    initial begin
        log_fd = $fopen("sim/log.txt", "w");
        result_fd = $fopen("sim/result.txt", "w");
        $dumpfile("sim/wave.vcd");
        $dumpvars(0, tb_gcd);
        $display("##SEC_STUDENT_CAN_SEE");
        $fdisplay(log_fd, "##SEC_STUDENT_CAN_SEE");
        // GOLDEN_CASE_SUMMARY_BEGIN
        $display("[CASE 1-3] checks general GCD inputs");
        $fdisplay(log_fd,"[CASE 1-3] checks general GCD inputs");
        $display("[CASE 4-5] checks zero-input corner cases");
        $fdisplay(log_fd,"[CASE 4-5] checks zero-input corner cases");
        // GOLDEN_CASE_SUMMARY_END


        errors = 0; pattern = 0; rst_n = 0; in_valid = 0; a = 0; b = 0;
        repeat (2) @(posedge clk); @(negedge clk); rst_n = 1;
        run_case(8'd48, 8'd18, 8'd6);
        run_case(8'd27, 8'd15, 8'd3);
        run_case(8'd49, 8'd14, 8'd7);
        run_case(8'd0,  8'd9,  8'd9);
        run_case(8'd12, 8'd0,  8'd12);
        if (errors == 0) begin
            $display("[PASS] gcd");
            $fdisplay(log_fd, "[PASS] gcd");
            $fdisplay(result_fd, "pass");
        end else begin
            $display("[FAIL] gcd, errors = %0d", errors);
            $fdisplay(log_fd, "[FAIL] gcd, errors = %0d", errors);
            $fdisplay(result_fd, "fail");
        end
        $display("##END_STUDENT_CAN_SEE");
        $fdisplay(log_fd, "##END_STUDENT_CAN_SEE");
        $fclose(log_fd); $fclose(result_fd);
        $finish;
    end
endmodule

practice/Lab05_gcd/golden/golden_wave.vcd
$date
	Mon May 11 15:57:59 2026
$end
$version
	Icarus Verilog
$end
$timescale
	1ps
$end
$scope module tb_gcd $end
$var wire 8 ! result [7:0] $end
$var wire 1 " out_valid $end
$var reg 8 # a [7:0] $end
$var reg 8 $ b [7:0] $end
$var reg 1 % clk $end
$var reg 1 & in_valid $end
$var reg 1 ' rst_n $end
$var integer 32 ( errors [31:0] $end
$var integer 32 ) log_fd [31:0] $end
$var integer 32 * pattern [31:0] $end
$var integer 32 + result_fd [31:0] $end
$scope module dut $end
$var wire 8 , a [7:0] $end
$var wire 8 - b [7:0] $end
$var wire 1 % clk $end
$var wire 1 & in_valid $end
$var wire 1 ' rst_n $end
$var parameter 2 . BUSY $end
$var parameter 2 / DONE $end
$var parameter 2 0 IDLE $end
$var reg 2 1 S [1:0] $end
$var reg 2 2 S_nxt [1:0] $end
$var reg 1 " out_valid $end
$var reg 8 3 result [7:0] $end
$var reg 8 4 x [7:0] $end
$var reg 8 5 x_nxt [7:0] $end
$var reg 8 6 y [7:0] $end
$var reg 8 7 y_nxt [7:0] $end
$upscope $end
$scope task run_case $end
$var reg 8 8 expected [7:0] $end
$var reg 8 9 va [7:0] $end
$var reg 8 : vb [7:0] $end
$var integer 32 ; timeout [31:0] $end
$upscope $end
$upscope $end
$enddefinitions $end
$comment Show the parameter values. $end
$dumpall
b0 0
b10 /
b1 .
$end
#0
$dumpvars
bx ;
bx :
bx 9
bx 8
b0 7
b0 6
b0 5
b0 4
b0 3
b0 2
b0 1
b0 -
b0 ,
b10000000000000000000000000000100 +
b0 *
b10000000000000000000000000000011 )
b0 (
0'
0&
0%
b0 $
b0 #
0"
b0 !
$end
#5000
1%
#10000
0%
#15000
1%
#20000
b1 *
b110 8
b10010 :
b110000 9
1'
0%
#25000
1%
#30000
b1 2
b10010 7
b110000 5
1&
b10010 $
b10010 -
b110000 #
b110000 ,
0%
#35000
b110000 !
b110000 3
b11110 5
b10010 6
b110000 4
b1 1
1%
#40000
b11110 5
b0 ;
b0 $
b0 -
b0 #
b0 ,
0&
0%
#45000
b11110 !
b11110 3
b1100 5
b11110 4
1%
#46000
b1 ;
#50000
0%
#55000
b1100 !
b1100 3
b110 7
b1100 4
1%
#56000
b10 ;
#60000
0%
#65000
b110 5
b110 6
1%
#66000
b11 ;
#70000
0%
#75000
b110 !
b110 3
b0 7
b110 4
1%
#76000
b100 ;
#80000
0%
#85000
b10 2
b0 6
1%
#86000
b101 ;
#90000
0%
#95000
1"
b0 2
b10 1
1%
#96000
b110 ;
#100000
0%
#105000
0"
b0 1
1%
#106000
b10 *
b11 8
b1111 :
b11011 9
#110000
b1 2
b1111 7
b11011 5
1&
b1111 $
b1111 -
b11011 #
b11011 ,
0%
#115000
b11011 !
b11011 3
b1100 5
b1111 6
b11011 4
b1 1
1%
#120000
b1100 5
b0 ;
b0 $
b0 -
b0 #
b0 ,
0&
0%
#125000
b1100 !
b1100 3
b11 7
b1100 4
1%
#126000
b1 ;
#130000
0%
#135000
b1001 5
b11 6
1%
#136000
b10 ;
#140000
0%
#145000
b1001 !
b1001 3
b110 5
b1001 4
1%
#146000
b11 ;
#150000
0%
#155000
b110 !
b110 3
b11 5
b110 4
1%
#156000
b100 ;
#160000
0%
#165000
b11 !
b11 3
b0 7
b11 4
1%
#166000
b101 ;
#170000
0%
#175000
b10 2
b0 6
1%
#176000
b110 ;
#180000
0%
#185000
1"
b0 2
b10 1
1%
#186000
b111 ;
#190000
0%
#195000
0"
b0 1
1%
#196000
b11 *
b111 8
b1110 :
b110001 9
#200000
b1 2
b1110 7
b110001 5
1&
b1110 $
b1110 -
b110001 #
b110001 ,
0%
#205000
b110001 !
b110001 3
b100011 5
b1110 6
b110001 4
b1 1
1%
#210000
b100011 5
b0 ;
b0 $
b0 -
b0 #
b0 ,
0&
0%
#215000
b100011 !
b100011 3
b10101 5
b100011 4
1%
#216000
b1 ;
#220000
0%
#225000
b10101 !
b10101 3
b111 5
b10101 4
1%
#226000
b10 ;
#230000
0%
#235000
b111 !
b111 3
b111 7
b111 4
1%
#236000
b11 ;
#240000
0%
#245000
b0 7
b111 6
1%
#246000
b100 ;
#250000
0%
#255000
b10 2
b0 6
1%
#256000
b101 ;
#260000
0%
#265000
1"
b0 2
b10 1
1%
#266000
b110 ;
#270000
0%
#275000
0"
b0 1
1%
#276000
b100 *
b1001 8
b1001 :
b0 9
#280000
b1 2
b1001 7
b0 5
1&
b1001 $
b1001 -
0%
#285000
b1001 !
b1001 3
b10 2
b1001 6
b0 4
b1 1
1%
#290000
b10 2
b0 ;
b0 $
b0 -
0&
0%
#295000
1"
b0 2
b10 1
1%
#296000
b1 ;
#300000
0%
#305000
0"
b0 1
1%
#306000
b101 *
b1100 8
b0 :
b1100 9
#310000
b1 2
b0 7
b1100 5
1&
b1100 #
b1100 ,
0%
#315000
b1100 !
b1100 3
b10 2
b0 6
b1100 4
b1 1
1%
#320000
b10 2
b0 ;
b0 #
b0 ,
0&
0%
#325000
1"
b0 2
b10 1
1%
#326000
b1 ;
#330000
0%
#335000
0"
b0 1
1%
