tutorial/Ex05_swap_gate/golden/swap_gate.v
module swap_gate (
    input  [1:0] a,
    input  [1:0] b,
    output [1:0] lo,
    output [1:0] hi,
    output       swap
);

wire a_gt_b;

cmp2_gate u_cmp (
    .a(a),
    .b(b),
    .gt(a_gt_b)
);

// If a > b, swap them so lo=b and hi=a.
assign swap = a_gt_b;
mux2_gate u_lo (
    .sel(swap),
    .in0(a),
    .in1(b),
    .y(lo)
);

mux2_gate u_hi (
    .sel(swap),
    .in0(b),
    .in1(a),
    .y(hi)
);

endmodule

module cmp2_gate (
    input  [1:0] a,
    input  [1:0] b,
    output       gt
);

wire not_b1;
wire not_b0;
wire a1_gt_b1;
wire a1_xnor_b1;
wire a0_gt_b0_when_equal_msb;

not g0 (not_b1, b[1]);
not g1 (not_b0, b[0]);
and g2 (a1_gt_b1, a[1], not_b1);
xnor g3 (a1_xnor_b1, a[1], b[1]);
and g4 (a0_gt_b0_when_equal_msb, a1_xnor_b1, a[0], not_b0);
or  g5 (gt, a1_gt_b1, a0_gt_b0_when_equal_msb);

endmodule

module mux2_gate (
    input        sel,
    input  [1:0] in0,
    input  [1:0] in1,
    output [1:0] y
);

wire not_sel;
wire in0_bit0;
wire in1_bit0;
wire in0_bit1;
wire in1_bit1;

not g0 (not_sel, sel);
and g1 (in0_bit0, in0[0], not_sel);
and g2 (in1_bit0, in1[0], sel);
or  g3 (y[0], in0_bit0, in1_bit0);

and g4 (in0_bit1, in0[1], not_sel);
and g5 (in1_bit1, in1[1], sel);
or  g6 (y[1], in0_bit1, in1_bit1);

endmodule

practice/Lab02_swap_gate/tb.v
`timescale 1ns/1ps
module tb_swap_gate;
    reg [1:0] a, b;
    wire [1:0] lo, hi;
    wire swap;
    integer errors, log_fd, result_fd, pattern;

    swap_gate dut (.a(a), .b(b), .lo(lo), .hi(hi), .swap(swap));

    task check;
        input [1:0] va;
        input [1:0] vb;
        input [1:0] exp_lo;
        input [1:0] exp_hi;
        input       exp_swap;
        begin
            pattern = pattern + 1;
            a = va;
            b = vb;
            #1;
            if (lo !== exp_lo || hi !== exp_hi || swap !== exp_swap) begin
                if (errors == 0) $display("[ERROR] pattern %0d: a=%0d b=%0d expected lo=%0d hi=%0d swap=%b got lo=%0d hi=%0d swap=%b", pattern, va, vb, exp_lo, exp_hi, exp_swap, lo, hi, swap);
                if (errors == 0) $fdisplay(log_fd, "[ERROR] pattern %0d: a=%0d b=%0d expected lo=%0d hi=%0d swap=%b got lo=%0d hi=%0d swap=%b", pattern, va, vb, exp_lo, exp_hi, exp_swap, lo, hi, swap);
                errors = errors + 1;
            end
        end
    endtask

    initial begin
        log_fd = $fopen("sim/log.txt", "w");
        result_fd = $fopen("sim/result.txt", "w");
        $dumpfile("sim/wave.vcd");
        $dumpvars(0, tb_swap_gate);
        $display("##SEC_STUDENT_CAN_SEE");
        $fdisplay(log_fd, "##SEC_STUDENT_CAN_SEE");
        // GOLDEN_CASE_SUMMARY_BEGIN
        $display("[CASE 1-4] checks no-swap cases");
        $fdisplay(log_fd,"[CASE 1-4] checks no-swap cases");
        $display("[CASE 5-8] checks swap cases");
        $fdisplay(log_fd,"[CASE 5-8] checks swap cases");
        $display("[CASE 9-12] checks equal-value cases");
        $fdisplay(log_fd,"[CASE 9-12] checks equal-value cases");
        // GOLDEN_CASE_SUMMARY_END

        errors = 0;
        pattern = 0;
        check(2'd0, 2'd1, 2'd0, 2'd1, 1'b0);
        check(2'd1, 2'd2, 2'd1, 2'd2, 1'b0);
        check(2'd2, 2'd3, 2'd2, 2'd3, 1'b0);
        check(2'd0, 2'd3, 2'd0, 2'd3, 1'b0);
        check(2'd1, 2'd0, 2'd0, 2'd1, 1'b1);
        check(2'd2, 2'd1, 2'd1, 2'd2, 1'b1);
        check(2'd3, 2'd2, 2'd2, 2'd3, 1'b1);
        check(2'd3, 2'd0, 2'd0, 2'd3, 1'b1);
        check(2'd0, 2'd0, 2'd0, 2'd0, 1'b0);
        check(2'd1, 2'd1, 2'd1, 2'd1, 1'b0);
        check(2'd2, 2'd2, 2'd2, 2'd2, 1'b0);
        check(2'd3, 2'd3, 2'd3, 2'd3, 1'b0);

        if (errors == 0) begin
            $display("[PASS] swap_gate");
            $fdisplay(log_fd, "[PASS] swap_gate");
            $fdisplay(result_fd, "pass");
        end else begin
            $display("[FAIL] swap_gate, errors = %0d", errors);
            $fdisplay(log_fd, "[FAIL] swap_gate, errors = %0d", errors);
            $fdisplay(result_fd, "fail");
        end
        $display("##END_STUDENT_CAN_SEE");
        $fdisplay(log_fd, "##END_STUDENT_CAN_SEE");
        $fclose(log_fd); $fclose(result_fd);
        $finish;
    end
endmodule

tutorial/Ex05_swap_gate/golden/golden_wave.vcd
$date
	Mon May 11 15:57:58 2026
$end
$version
	Icarus Verilog
$end
$timescale
	1ps
$end
$scope module tb_swap_gate $end
$var wire 1 ! swap $end
$var wire 2 " lo [1:0] $end
$var wire 2 # hi [1:0] $end
$var reg 2 $ a [1:0] $end
$var reg 2 % b [1:0] $end
$var integer 32 & errors [31:0] $end
$var integer 32 ' log_fd [31:0] $end
$var integer 32 ( pattern [31:0] $end
$var integer 32 ) result_fd [31:0] $end
$scope module dut $end
$var wire 2 * a [1:0] $end
$var wire 2 + b [1:0] $end
$var wire 1 ! swap $end
$var wire 2 , lo [1:0] $end
$var wire 2 - hi [1:0] $end
$var wire 1 . a_gt_b $end
$scope module u_cmp $end
$var wire 2 / a [1:0] $end
$var wire 1 0 a0_gt_b0_when_equal_msb $end
$var wire 1 1 a1_gt_b1 $end
$var wire 1 2 a1_xnor_b1 $end
$var wire 2 3 b [1:0] $end
$var wire 1 . gt $end
$var wire 1 4 not_b0 $end
$var wire 1 5 not_b1 $end
$upscope $end
$scope module u_hi $end
$var wire 2 6 in0 [1:0] $end
$var wire 1 7 in0_bit0 $end
$var wire 1 8 in0_bit1 $end
$var wire 2 9 in1 [1:0] $end
$var wire 1 : in1_bit0 $end
$var wire 1 ; in1_bit1 $end
$var wire 1 < not_sel $end
$var wire 1 ! sel $end
$var wire 2 = y [1:0] $end
$upscope $end
$scope module u_lo $end
$var wire 2 > in0 [1:0] $end
$var wire 1 ? in0_bit0 $end
$var wire 1 @ in0_bit1 $end
$var wire 2 A in1 [1:0] $end
$var wire 1 B in1_bit0 $end
$var wire 1 C in1_bit1 $end
$var wire 1 D not_sel $end
$var wire 1 ! sel $end
$var wire 2 E y [1:0] $end
$upscope $end
$upscope $end
$scope task check $end
$var reg 2 F exp_hi [1:0] $end
$var reg 2 G exp_lo [1:0] $end
$var reg 1 H exp_swap $end
$var reg 2 I va [1:0] $end
$var reg 2 J vb [1:0] $end
$upscope $end
$upscope $end
$enddefinitions $end
$comment Show the parameter values. $end
$dumpall
$end
#0
$dumpvars
b1 J
b0 I
0H
b0 G
b1 F
b0 E
1D
0C
0B
b1 A
0@
0?
b0 >
b1 =
1<
0;
0:
b0 9
08
17
b1 6
15
04
b1 3
12
01
00
b0 /
0.
b1 -
b0 ,
b1 +
b0 *
b10000000000000000000000000000100 )
b1 (
b10000000000000000000000000000011 '
b0 &
b1 %
b0 $
b1 #
b0 "
0!
$end
#1000
b10 #
b10 -
b10 =
b1 "
b1 ,
b1 E
05
14
02
07
18
1?
b10 %
b10 +
b10 3
b10 6
b10 A
b1 $
b1 *
b1 /
b1 9
b1 >
b10 (
b10 F
b1 G
b10 J
b1 I
#2000
b11 #
b11 -
b11 =
b10 "
b10 ,
b10 E
04
17
12
0?
1@
b11 %
b11 +
b11 3
b11 6
b11 A
b10 $
b10 *
b10 /
b10 9
b10 >
b11 (
b11 F
b10 G
b11 J
b10 I
#3000
b0 "
b0 ,
b0 E
02
0@
b0 $
b0 *
b0 /
b0 9
b0 >
b100 (
b0 G
b0 I
#4000
0<
1:
0D
1!
1.
10
b1 #
b1 -
b1 =
b0 "
b0 ,
b0 E
15
14
12
07
08
0?
b0 %
b0 +
b0 3
b0 6
b0 A
b1 $
b1 *
b1 /
b1 9
b1 >
b101 (
1H
b1 F
b0 J
b1 I
#5000
b1 "
b1 ,
b1 E
b10 #
b10 -
b10 =
04
1B
11
02
00
0:
1;
b1 %
b1 +
b1 3
b1 6
b1 A
b10 $
b10 *
b10 /
b10 9
b10 >
b110 (
b10 F
b1 G
b1 J
b10 I
#6000
01
10
b10 "
b10 ,
b10 E
b11 #
b11 -
b11 =
05
14
12
0B
1C
1:
b10 %
b10 +
b10 3
b10 6
b10 A
b11 $
b11 *
b11 /
b11 9
b11 >
b111 (
b11 F
b10 G
b10 J
b11 I
#7000
11
00
b0 "
b0 ,
b0 E
15
02
0C
b0 %
b0 +
b0 3
b0 6
b0 A
b1000 (
b0 G
b0 J
#8000
1<
1D
0!
0.
b0 #
b0 -
b0 =
01
12
0:
0;
b0 $
b0 *
b0 /
b0 9
b0 >
b1001 (
0H
b0 F
b0 I
#9000
1<
0:
1D
0B
b1 #
b1 -
b1 =
0!
0.
b1 "
b1 ,
b1 E
04
17
00
1?
b1 %
b1 +
b1 3
b1 6
b1 A
b1 $
b1 *
b1 /
b1 9
b1 >
b1010 (
b1 F
b1 G
b1 J
b1 I
#10000
1<
0;
1D
0C
b10 #
b10 -
b10 =
0!
0.
b10 "
b10 ,
b10 E
05
14
07
18
01
0?
1@
b10 %
b10 +
b10 3
b10 6
b10 A
b10 $
b10 *
b10 /
b10 9
b10 >
b1011 (
b10 F
b10 G
b10 J
b10 I
#11000
18
1@
1<
0:
0;
1D
0B
0C
b11 #
b11 -
b11 =
0!
0.
b11 "
b11 ,
b11 E
04
17
00
1?
b11 %
b11 +
b11 3
b11 6
b11 A
b11 $
b11 *
b11 /
b11 9
b11 >
b1100 (
b11 F
b11 G
b11 J
b11 I
