advanced/fsm_calc/golden/fsm_calc.v
module fsm_calc (
    input         clk,
    input         rst_n,

    input         btn_valid,
    input  [3:0]  btn,

    output reg [15:0] out
);

// ------------------------------
// Button encoding
// ------------------------------
localparam BTN_ADD = 4'd11;
localparam BTN_SUB = 4'd12;
localparam BTN_MUL = 4'd13;
localparam BTN_EQ  = 4'd14;
localparam BTN_AC  = 4'd15;

// ------------------------------
// FSM states
// ------------------------------
localparam S_FIRST  = 2'd0; // entering first number
localparam S_WAIT   = 2'd1; // operator pressed, waiting for second number
localparam S_SECOND = 2'd2; // entering second number
localparam S_RESULT = 2'd3; // result shown

// ------------------------------
// Operator encoding
// No OP_NONE needed.
// Whether an operator is pending is represented by state.
// ------------------------------
localparam OP_ADD = 2'd0;
localparam OP_SUB = 2'd1;
localparam OP_MUL = 2'd2;

reg [1:0] S, S_nxt;

reg [15:0] acc, acc_nxt; // left-hand operand / accumulated result
reg [1:0]  op, op_nxt;
reg [15:0] out_nxt;

// ------------------------------
// Registers
// ------------------------------
always @(posedge clk or negedge rst_n) begin
    if (!rst_n) begin
        S   <= S_FIRST;
        acc <= 0;
        op  <= OP_ADD;
        out <= 0;
    end else begin
        S   <= S_nxt;
        acc <= acc_nxt;
        op  <= op_nxt;
        out <= out_nxt;
    end
end

// ------------------------------
// Button decode
// ------------------------------
wire is_digit = (btn < 10);
wire is_op = (btn == BTN_ADD) || (btn == BTN_SUB) || (btn == BTN_MUL);
wire is_eq = (btn == BTN_EQ);

reg [1:0] btn_op;
always @(*) begin
    case (btn)
        BTN_ADD: btn_op = OP_ADD;
        BTN_SUB: btn_op = OP_SUB;
        BTN_MUL: btn_op = OP_MUL;
        default: btn_op = OP_ADD;
    endcase
end

// ------------------------------
// Datapath: acc op out
// ------------------------------
reg [15:0] alu_result;

always @(*) begin
    case (op)
        OP_ADD:  alu_result = acc + out;
        OP_SUB:  alu_result = acc - out;
        OP_MUL:  alu_result = acc * out;
        default: alu_result = acc + out;
    endcase
end

// ------------------------------
// Next-state and datapath logic
// ------------------------------
always @(*) begin
    S_nxt   = S;
    acc_nxt = acc;
    op_nxt  = op;
    out_nxt = out;

    if (btn_valid) begin
        if (btn == BTN_AC) begin
            S_nxt   = S_FIRST;
            acc_nxt = 0;
            op_nxt  = OP_ADD;
            out_nxt = 0;
        end else begin
            case (S)
                // ----------------------------------
                // Entering first number
                // ----------------------------------
                S_FIRST: begin
                    if (is_digit) begin
                        out_nxt = out * 10 + btn;
                    end else if (is_op) begin
                        acc_nxt = out;
                        op_nxt  = btn_op;
                        S_nxt   = S_WAIT;
                    end else if (is_eq) begin
                        S_nxt = S_RESULT;
                    end
                end

                // ----------------------------------
                // Operator pressed, waiting for RHS
                // ----------------------------------
                S_WAIT: begin
                    if (is_digit) begin
                        out_nxt = btn;
                        S_nxt   = S_SECOND;
                    end else if (is_op) begin
                        // allow changing operator before entering RHS
                        op_nxt = btn_op;
                    end else if (is_eq) begin
                        // no RHS entered, just keep current display
                        S_nxt = S_RESULT;
                    end
                end

                // ----------------------------------
                // Entering second number
                // ----------------------------------
                S_SECOND: begin
                    if (is_digit) begin
                        out_nxt = out * 10 + btn;
                    end else if (is_op) begin
                        acc_nxt = alu_result;
                        out_nxt = alu_result;
                        op_nxt  = btn_op;
                        S_nxt   = S_WAIT;
                    end else if (is_eq) begin
                        acc_nxt = alu_result;
                        out_nxt = alu_result;
                        S_nxt   = S_RESULT;
                    end
                end

                // ----------------------------------
                // Result shown
                // ----------------------------------
                S_RESULT: begin
                    if (is_digit) begin
                        acc_nxt = 0;
                        out_nxt = btn;
                        S_nxt   = S_FIRST;
                    end else if (is_op) begin
                        acc_nxt = out;
                        op_nxt  = btn_op;
                        S_nxt   = S_WAIT;
                    end else if (is_eq) begin
                        S_nxt = S_RESULT;
                    end
                end

                default: begin
                    S_nxt   = S_FIRST;
                    acc_nxt = 0;
                    op_nxt  = OP_ADD;
                    out_nxt = 0;
                end
            endcase
        end
    end
end

endmodule

advanced/fsm_calc/tb.v
`timescale 1ns/1ps
module tb_fsm_calc;
    reg clk, rst_n, btn_valid;
    reg [3:0] btn;
    wire [15:0] out;
    integer errors, log_fd, result_fd, pattern;
    reg [3:0] last_key;

    localparam BTN_ADD = 4'd11;
    localparam BTN_SUB = 4'd12;
    localparam BTN_MUL = 4'd13;
    localparam BTN_EQ  = 4'd14;
    localparam BTN_AC  = 4'd15;

    fsm_calc dut (.clk(clk), .rst_n(rst_n), .btn_valid(btn_valid), .btn(btn), .out(out));
    initial begin clk = 0; forever #5 clk = ~clk; end

    task press;
        input [3:0] key;
        begin
            pattern = pattern + 1;
            last_key = key;
            @(negedge clk); btn = key; btn_valid = 1'b1;
            @(posedge clk);
            @(negedge clk); btn_valid = 1'b0; btn = 4'd0;
            #1;
        end
    endtask

    task check_out;
        input [15:0] expected;
        begin
            #1;
            if (out !== expected) begin
                if (errors == 0) $display("[ERROR] pattern %0d after key=%0d: expected out=%0d got=%0d", pattern, last_key, expected, out);
                if (errors == 0) $fdisplay(log_fd, "[ERROR] pattern %0d after key=%0d: expected out=%0d got=%0d", pattern, last_key, expected, out);
                errors = errors + 1;
            end
        end
    endtask

    initial begin
        log_fd = $fopen("sim/log.txt", "w");
        result_fd = $fopen("sim/result.txt", "w");
        $dumpfile("sim/wave.vcd");
        $dumpvars(0, tb_fsm_calc);
        $display("##SEC_STUDENT_CAN_SEE");
        $fdisplay(log_fd, "##SEC_STUDENT_CAN_SEE");
        // GOLDEN_CASE_SUMMARY_BEGIN
        $display("[CASE 1-15] checks add, subtract, multiply flows");
        $fdisplay(log_fd,"[CASE 1-15] checks add, subtract, multiply flows");
        $display("[CASE 16-26] checks result, operator-change, repeated-equals flows");
        $fdisplay(log_fd,"[CASE 16-26] checks result, operator-change, repeated-equals flows");
        $display("[CASE 27-33] checks chained operation flow");
        $fdisplay(log_fd,"[CASE 27-33] checks chained operation flow");
        // GOLDEN_CASE_SUMMARY_END


        errors = 0; pattern = 0; last_key = 0; rst_n = 0; btn_valid = 0; btn = 0;
        repeat (2) @(posedge clk); @(negedge clk); rst_n = 1; #1;

        press(4'd1); check_out(16'd1);
        press(4'd2); check_out(16'd12);
        press(BTN_ADD); check_out(16'd12);
        press(4'd3); check_out(16'd3);
        press(BTN_EQ); check_out(16'd15);

        press(BTN_AC); check_out(16'd0);
        press(4'd8); check_out(16'd8);
        press(BTN_SUB); check_out(16'd8);
        press(4'd5); check_out(16'd5);
        press(BTN_EQ); check_out(16'd3);

        press(BTN_AC); check_out(16'd0);
        press(4'd6); check_out(16'd6);
        press(BTN_MUL); check_out(16'd6);
        press(4'd7); check_out(16'd7);
        press(BTN_EQ); check_out(16'd42);

        press(4'd9); check_out(16'd9);
        press(BTN_EQ); check_out(16'd9);

        press(BTN_AC); check_out(16'd0);
        press(4'd9); check_out(16'd9);
        press(BTN_ADD); check_out(16'd9);
        press(BTN_SUB); check_out(16'd9);
        press(BTN_EQ); check_out(16'd9);
        press(BTN_MUL); check_out(16'd9);
        press(4'd2); check_out(16'd2);
        press(BTN_EQ); check_out(16'd18);
        press(BTN_EQ); check_out(16'd18);

        press(BTN_AC); check_out(16'd0);
        press(4'd2); check_out(16'd2);
        press(BTN_ADD); check_out(16'd2);
        press(4'd3); check_out(16'd3);
        press(BTN_MUL); check_out(16'd5);
        press(4'd4); check_out(16'd4);
        press(BTN_EQ); check_out(16'd20);

        if (errors == 0) begin
            $display("[PASS] fsm_calc");
            $fdisplay(log_fd, "[PASS] fsm_calc");
            $fdisplay(result_fd, "pass");
        end else begin
            $display("[FAIL] fsm_calc, errors = %0d", errors);
            $fdisplay(log_fd, "[FAIL] fsm_calc, errors = %0d", errors);
            $fdisplay(result_fd, "fail");
        end
        $display("##END_STUDENT_CAN_SEE");
        $fdisplay(log_fd, "##END_STUDENT_CAN_SEE");
        $fclose(log_fd); $fclose(result_fd);
        $finish;
    end
endmodule

advanced/fsm_calc/golden/golden_wave.vcd
$date
	Mon May 11 09:39:55 2026
$end
$version
	Icarus Verilog
$end
$timescale
	1ps
$end
$scope module tb_fsm_calc $end
$var wire 16 ! out [15:0] $end
$var parameter 4 " BTN_AC $end
$var parameter 4 # BTN_ADD $end
$var parameter 4 $ BTN_EQ $end
$var parameter 4 % BTN_MUL $end
$var parameter 4 & BTN_SUB $end
$var reg 4 ' btn [3:0] $end
$var reg 1 ( btn_valid $end
$var reg 1 ) clk $end
$var reg 4 * last_key [3:0] $end
$var reg 1 + rst_n $end
$var integer 32 , errors [31:0] $end
$var integer 32 - log_fd [31:0] $end
$var integer 32 . pattern [31:0] $end
$var integer 32 / result_fd [31:0] $end
$scope module dut $end
$var wire 4 0 btn [3:0] $end
$var wire 1 ( btn_valid $end
$var wire 1 ) clk $end
$var wire 1 1 is_op $end
$var wire 1 + rst_n $end
$var wire 1 2 is_eq $end
$var wire 1 3 is_digit $end
$var parameter 4 4 BTN_AC $end
$var parameter 4 5 BTN_ADD $end
$var parameter 4 6 BTN_EQ $end
$var parameter 4 7 BTN_MUL $end
$var parameter 4 8 BTN_SUB $end
$var parameter 2 9 OP_ADD $end
$var parameter 2 : OP_MUL $end
$var parameter 2 ; OP_SUB $end
$var parameter 2 < S_FIRST $end
$var parameter 2 = S_RESULT $end
$var parameter 2 > S_SECOND $end
$var parameter 2 ? S_WAIT $end
$var reg 2 @ S [1:0] $end
$var reg 2 A S_nxt [1:0] $end
$var reg 16 B acc [15:0] $end
$var reg 16 C acc_nxt [15:0] $end
$var reg 16 D alu_result [15:0] $end
$var reg 2 E btn_op [1:0] $end
$var reg 2 F op [1:0] $end
$var reg 2 G op_nxt [1:0] $end
$var reg 16 H out [15:0] $end
$var reg 16 I out_nxt [15:0] $end
$upscope $end
$scope task check_out $end
$var reg 16 J expected [15:0] $end
$upscope $end
$scope task press $end
$var reg 4 K key [3:0] $end
$upscope $end
$upscope $end
$enddefinitions $end
$comment Show the parameter values. $end
$dumpall
b1 ?
b10 >
b11 =
b0 <
b1 ;
b10 :
b0 9
b1100 8
b1101 7
b1110 6
b1011 5
b1111 4
b1100 &
b1101 %
b1110 $
b1011 #
b1111 "
$end
#0
$dumpvars
bx K
bx J
b0 I
b0 H
b0 G
b0 F
b0 E
b0 D
b0 C
b0 B
b0 A
b0 @
13
02
01
b0 0
b10000000000000000000000000000100 /
b0 .
b10000000000000000000000000000011 -
b0 ,
0+
b0 *
0)
0(
b0 '
b0 !
$end
#5000
1)
#10000
0)
#15000
1)
#20000
1+
0)
#21000
b1 *
b1 .
b1 K
#25000
1)
#30000
b1 I
1(
b1 '
b1 0
0)
#35000
b1011 I
b1 D
b1 !
b1 H
1)
#40000
b1 I
b0 '
b0 0
0(
0)
#41000
b1 J
#42000
b10 *
b10 .
b10 K
#45000
1)
#50000
b1100 I
1(
b10 '
b10 0
0)
#55000
b1111010 I
b1100 D
b1100 !
b1100 H
1)
#60000
b1100 I
b0 '
b0 0
0(
0)
#61000
b1100 J
#62000
b1011 *
b11 .
b1011 K
#65000
1)
#70000
b1 A
b1100 C
11
1(
03
b1011 '
b1011 0
0)
#75000
b11000 D
b1100 B
b1 @
1)
#80000
01
13
b0 '
b0 0
0(
0)
#82000
b11 *
b100 .
b11 K
#85000
1)
#90000
b10 A
b11 I
1(
b11 '
b11 0
0)
#95000
b1111 D
b100001 I
b11 !
b11 H
b10 @
1)
#100000
b11 I
b0 '
b0 0
0(
0)
#101000
b11 J
#102000
b1110 *
b101 .
b1110 K
#105000
1)
#110000
b11 A
b1111 I
b1111 C
1(
03
12
b1110 '
b1110 0
0)
#115000
b11110 D
b1111 !
b1111 H
b1111 B
b11 @
1)
#120000
13
02
b0 '
b0 0
0(
0)
#121000
b1111 J
#122000
b1111 *
b110 .
b1111 K
#125000
1)
#130000
b0 I
b0 C
b0 A
1(
03
b1111 '
b1111 0
0)
#135000
b0 D
b0 !
b0 H
b0 B
b0 @
1)
#140000
13
b0 '
b0 0
0(
0)
#141000
b0 J
#142000
b1000 *
b111 .
b1000 K
#145000
1)
#150000
b1000 I
1(
b1000 '
b1000 0
0)
#155000
b1011000 I
b1000 D
b1000 !
b1000 H
1)
#160000
b1000 I
b0 '
b0 0
0(
0)
#161000
b1000 J
#162000
b1100 *
b1000 .
b1100 K
#165000
1)
#170000
b1 A
b1 G
b1000 C
11
b1 E
1(
03
b1100 '
b1100 0
0)
#175000
b0 D
b1 F
b1000 B
b1 @
1)
#180000
01
b0 E
13
b0 '
b0 0
0(
0)
#182000
b101 *
b1001 .
b101 K
#185000
1)
#190000
b10 A
b101 I
1(
b101 '
b101 0
0)
#195000
b11 D
b110111 I
b101 !
b101 H
b10 @
1)
#200000
b101 I
b0 '
b0 0
0(
0)
#201000
b101 J
#202000
b1110 *
b1010 .
b1110 K
#205000
1)
#210000
b11 A
b11 I
b11 C
1(
03
12
b1110 '
b1110 0
0)
#215000
b0 D
b11 !
b11 H
b11 B
b11 @
1)
#220000
13
02
b0 '
b0 0
0(
0)
#221000
b11 J
#222000
b1111 *
b1011 .
b1111 K
#225000
1)
#230000
b0 I
b0 G
b0 C
b0 A
1(
03
b1111 '
b1111 0
0)
#235000
b0 !
b0 H
b0 F
b0 B
b0 @
1)
#240000
13
b0 '
b0 0
0(
0)
#241000
b0 J
#242000
b110 *
b1100 .
b110 K
#245000
1)
#250000
b110 I
1(
b110 '
b110 0
0)
#255000
b1000010 I
b110 D
b110 !
b110 H
1)
#260000
b110 I
b0 '
b0 0
0(
0)
#261000
b110 J
#262000
b1101 *
b1101 .
b1101 K
#265000
1)
#270000
b10 G
b10 E
b1 A
b110 C
11
1(
03
b1101 '
b1101 0
0)
#275000
b100100 D
b10 F
b110 B
b1 @
1)
#280000
b0 E
01
13
b0 '
b0 0
0(
0)
#282000
b111 *
b1110 .
b111 K
#285000
1)
#290000
b10 A
b111 I
1(
b111 '
b111 0
0)
#295000
b101010 D
b1001101 I
b111 !
b111 H
b10 @
1)
#300000
b111 I
b0 '
b0 0
0(
0)
#301000
b111 J
#302000
b1110 *
b1111 .
b1110 K
#305000
1)
#310000
b11 A
b101010 I
b101010 C
1(
03
12
b1110 '
b1110 0
0)
#315000
b11011100100 D
b101010 !
b101010 H
b101010 B
b11 @
1)
#320000
13
02
b0 '
b0 0
0(
0)
#321000
b101010 J
#322000
b1001 *
b10000 .
b1001 K
#325000
1)
#330000
b0 A
b1001 I
b0 C
1(
b1001 '
b1001 0
0)
#335000
b0 D
b1100011 I
b1001 !
b1001 H
b0 B
b0 @
1)
#340000
b1001 I
b0 '
b0 0
0(
0)
#341000
b1001 J
#342000
b1110 *
b10001 .
b1110 K
#345000
1)
#350000
b11 A
1(
03
12
b1110 '
b1110 0
0)
#355000
b11 @
1)
#360000
13
02
b0 '
b0 0
0(
0)
#362000
b1111 *
b10010 .
b1111 K
#365000
1)
#370000
b0 I
b0 G
b0 A
1(
03
b1111 '
b1111 0
0)
#375000
b0 !
b0 H
b0 F
b0 @
1)
#380000
13
b0 '
b0 0
0(
0)
#381000
b0 J
#382000
b1001 *
b10011 .
b1001 K
#385000
1)
#390000
b1001 I
1(
b1001 '
b1001 0
0)
#395000
b1100011 I
b1001 D
b1001 !
b1001 H
1)
#400000
b1001 I
b0 '
b0 0
0(
0)
#401000
b1001 J
#402000
b1011 *
b10100 .
b1011 K
#405000
1)
#410000
b1 A
b1001 C
11
1(
03
b1011 '
b1011 0
0)
#415000
b10010 D
b1001 B
b1 @
1)
#420000
01
13
b0 '
b0 0
0(
0)
#422000
b1100 *
b10101 .
b1100 K
#425000
1)
#430000
b1 G
11
b1 E
1(
03
b1100 '
b1100 0
0)
#435000
b0 D
b1 F
1)
#440000
01
b0 E
13
b0 '
b0 0
0(
0)
#442000
b1110 *
b10110 .
b1110 K
#445000
1)
#450000
b11 A
1(
03
12
b1110 '
b1110 0
0)
#455000
b11 @
1)
#460000
13
02
b0 '
b0 0
0(
0)
#462000
b1101 *
b10111 .
b1101 K
#465000
1)
#470000
b10 E
b1 A
b10 G
11
1(
03
b1101 '
b1101 0
0)
#475000
b1010001 D
b10 F
b1 @
1)
#480000
b0 E
01
13
b0 '
b0 0
0(
0)
#482000
b10 *
b11000 .
b10 K
#485000
1)
#490000
b10 A
b10 I
1(
b10 '
b10 0
0)
#495000
b10010 D
b10110 I
b10 !
b10 H
b10 @
1)
#500000
b10 I
b0 '
b0 0
0(
0)
#501000
b10 J
#502000
b1110 *
b11001 .
b1110 K
#505000
1)
#510000
b11 A
b10010 I
b10010 C
1(
03
12
b1110 '
b1110 0
0)
#515000
b101000100 D
b10010 !
b10010 H
b10010 B
b11 @
1)
#520000
13
02
b0 '
b0 0
0(
0)
#521000
b10010 J
#522000
b11010 .
#525000
1)
#530000
1(
03
12
b1110 '
b1110 0
0)
#535000
1)
#540000
13
02
b0 '
b0 0
0(
0)
#542000
b1111 *
b11011 .
b1111 K
#545000
1)
#550000
b0 I
b0 G
b0 C
b0 A
1(
03
b1111 '
b1111 0
0)
#555000
b0 D
b0 !
b0 H
b0 F
b0 B
b0 @
1)
#560000
13
b0 '
b0 0
0(
0)
#561000
b0 J
#562000
b10 *
b11100 .
b10 K
#565000
1)
#570000
b10 I
1(
b10 '
b10 0
0)
#575000
b10110 I
b10 D
b10 !
b10 H
1)
#580000
b10 I
b0 '
b0 0
0(
0)
#581000
b10 J
#582000
b1011 *
b11101 .
b1011 K
#585000
1)
#590000
b1 A
b10 C
11
1(
03
b1011 '
b1011 0
0)
#595000
b100 D
b10 B
b1 @
1)
#600000
01
13
b0 '
b0 0
0(
0)
#602000
b11 *
b11110 .
b11 K
#605000
1)
#610000
b10 A
b11 I
1(
b11 '
b11 0
0)
#615000
b101 D
b100001 I
b11 !
b11 H
b10 @
1)
#620000
b11 I
b0 '
b0 0
0(
0)
#621000
b11 J
#622000
b1101 *
b11111 .
b1101 K
#625000
1)
#630000
b10 G
b10 E
b1 A
b101 I
b101 C
11
1(
03
b1101 '
b1101 0
0)
#635000
b11001 D
b101 !
b101 H
b10 F
b101 B
b1 @
1)
#640000
b0 E
01
13
b0 '
b0 0
0(
0)
#641000
b101 J
#642000
b100 *
b100000 .
b100 K
#645000
1)
#650000
b10 A
b100 I
1(
b100 '
b100 0
0)
#655000
b10100 D
b101100 I
b100 !
b100 H
b10 @
1)
#660000
b100 I
b0 '
b0 0
0(
0)
#661000
b100 J
#662000
b1110 *
b100001 .
b1110 K
#665000
1)
#670000
b11 A
b10100 I
b10100 C
1(
03
12
b1110 '
b1110 0
0)
#675000
b110010000 D
b10100 !
b10100 H
b10100 B
b11 @
1)
#680000
13
02
b0 '
b0 0
0(
0)
#681000
b10100 J
