tutorial/Ex06_sequential/shift_register.v
module Ex06_ShiftRegister (
    input        clk,
    input        rst_n,
    input        en,
    input        serial_in,
    output       serial_out,
    output reg [7:0] data
);

// ** shift register **
// When en is 1, data shifts left by one bit every clock cycle.
// serial_in enters from bit 0, and the old bit 7 becomes serial_out.
always @(posedge clk or negedge rst_n) begin
    if (!rst_n) begin
        data <= 8'd0;
    end else if (en) begin
        data <= {data[6:0], serial_in};
    end else begin
        data <= data;
    end
end

assign serial_out = data[7];

endmodule

tutorial/Ex06_sequential/jkff.v
module Ex06_JKFF (
    input  clk,
    input  rst_n,
    input  j,
    input  k,
    output reg q,
    output     q_b
);

reg q_nxt;

always @(posedge clk or negedge rst_n) begin
    if (!rst_n) begin
        q <= 1'b0;
    end else begin
        q <= q_nxt;
    end
end

// ** JK flip-flop truth table **
// j k | next q
// 0 0 | hold
// 0 1 | reset to 0
// 1 0 | set to 1
// 1 1 | toggle
always @(*) begin
    case ({j, k})
        2'b00: q_nxt = q;
        2'b01: q_nxt = 1'b0;
        2'b10: q_nxt = 1'b1;
        2'b11: q_nxt = ~q;
        default: q_nxt = q;
    endcase
end

assign q_b = ~q;

endmodule

tutorial/Ex06_sequential/dff.v
module Ex06_DFF (
    input      clk,
    input      rst_n,
    input      d,
    output reg q,
    output     q_b
);

// ** D flip-flop **
// q samples d on every rising clock edge.
always @(posedge clk or negedge rst_n) begin
    if (!rst_n) begin
        q <= 1'b0;
    end else begin
        q <= d;
    end
end

assign q_b = ~q;

endmodule

tutorial/Ex06_sequential/counter.v
module Ex06_Counter (
    input        clk,
    input        rst_n,
    input        en,
    input        clear,
    output reg [3:0] cnt,
    output       rollover
);

reg [3:0] cnt_nxt;

// ** state transition **
always @(posedge clk or negedge rst_n) begin
    if (!rst_n) begin
        cnt <= 4'd0;
    end else begin
        cnt <= cnt_nxt;
    end
end

// ** next state logic **
always @(*) begin
    if (clear) begin
        cnt_nxt = 4'd0;
    end else if (en) begin
        cnt_nxt = cnt + 4'd1;
    end else begin
        cnt_nxt = cnt;
    end
end

// ** output logic **
assign rollover = en && (cnt == 4'hf);

endmodule

tutorial/Ex06_sequential/tb.v
`timescale 1ns/1ps
module tb_ex05_sequential;
    reg clk, rst_n;
    reg en, clear, d, j, k, serial_in;
    wire [3:0] cnt;
    wire rollover;
    wire dff_q, dff_q_b, jk_q, jk_q_b;
    wire serial_out;
    wire [7:0] shift_data;
    integer errors, log_fd, result_fd, pattern, i;
    reg [7:0] expected_shift;

    Ex06_Counter u_counter(.clk(clk), .rst_n(rst_n), .en(en), .clear(clear), .cnt(cnt), .rollover(rollover));
    Ex06_DFF u_dff(.clk(clk), .rst_n(rst_n), .d(d), .q(dff_q), .q_b(dff_q_b));
    Ex06_JKFF u_jk(.clk(clk), .rst_n(rst_n), .j(j), .k(k), .q(jk_q), .q_b(jk_q_b));
    Ex06_ShiftRegister u_shift(.clk(clk), .rst_n(rst_n), .en(en), .serial_in(serial_in), .serial_out(serial_out), .data(shift_data));

    initial begin clk = 0; forever #5 clk = ~clk; end

    task check;
        input [8*32-1:0] name;
        input [3:0] exp_cnt;
        input exp_rollover;
        input exp_dff_q;
        input exp_jk_q;
        input [7:0] exp_shift_value;
        begin
            pattern = pattern + 1;
            #1;
            if (cnt !== exp_cnt || rollover !== exp_rollover || dff_q !== exp_dff_q || jk_q !== exp_jk_q || shift_data !== exp_shift_value) begin
                $display("[ERROR] pattern %0d (%0s): cnt=%0d/%0d rollover=%b/%b dff=%b/%b jk=%b/%b shift=%b/%b", pattern, name, exp_cnt, cnt, exp_rollover, rollover, exp_dff_q, dff_q, exp_jk_q, jk_q, exp_shift_value, shift_data);
                $fdisplay(log_fd,"[ERROR] pattern %0d (%0s): cnt=%0d/%0d rollover=%b/%b dff=%b/%b jk=%b/%b shift=%b/%b", pattern, name, exp_cnt, cnt, exp_rollover, rollover, exp_dff_q, dff_q, exp_jk_q, jk_q, exp_shift_value, shift_data);
                errors = errors + 1;
            end
        end
    endtask

    initial begin
        log_fd=$fopen("sim/log.txt","w"); result_fd=$fopen("sim/result.txt","w");
        $dumpfile("sim/wave.vcd"); $dumpvars(0,tb_ex05_sequential);
        $display("##SEC_STUDENT_CAN_SEE"); $fdisplay(log_fd,"##SEC_STUDENT_CAN_SEE");
        errors=0; pattern=0; rst_n=0; en=0; clear=0; d=0; j=0; k=0; serial_in=0; expected_shift=8'b0000_0000;
        repeat(2) @(posedge clk); @(negedge clk); rst_n=1; @(posedge clk); check("reset release", 4'd0, 1'b0, 1'b0, 1'b0, 8'b0000_0000);

        @(negedge clk); en=1; d=1; j=1; k=0; serial_in=1;
        expected_shift = {expected_shift[6:0], 1'b1};
        @(posedge clk); check("set and shift 1", 4'd1, 1'b0, 1'b1, 1'b1, expected_shift);

        @(negedge clk); d=0; j=0; k=0; serial_in=0;
        expected_shift = {expected_shift[6:0], 1'b0};
        @(posedge clk); check("hold jk and shift 0", 4'd2, 1'b0, 1'b0, 1'b1, expected_shift);

        @(negedge clk); j=1; k=1; serial_in=1;
        expected_shift = {expected_shift[6:0], 1'b1};
        @(posedge clk); check("toggle jk", 4'd3, 1'b0, 1'b0, 1'b0, expected_shift);

        @(negedge clk); clear=1; en=1; j=0; k=1; serial_in=1;
        expected_shift = {expected_shift[6:0], 1'b1};
        @(posedge clk); check("clear counter and reset jk", 4'd0, 1'b0, 1'b0, 1'b0, expected_shift);

        @(negedge clk); clear=0; en=0; serial_in=0;
        @(posedge clk); check("hold counter and shift", 4'd0, 1'b0, 1'b0, 1'b0, expected_shift);

        @(negedge clk); en=1; d=0; j=0; k=0; serial_in=0;
        for (i = 1; i <= 14; i = i + 1) begin
            expected_shift = {expected_shift[6:0], 1'b0};
            @(posedge clk); check("count toward rollover", i[3:0], 1'b0, 1'b0, 1'b0, expected_shift);
        end
        expected_shift = {expected_shift[6:0], 1'b0};
        @(posedge clk); check("rollover asserted at 15", 4'd15, 1'b1, 1'b0, 1'b0, expected_shift);
        expected_shift = {expected_shift[6:0], 1'b0};
        @(posedge clk); check("wrap after rollover", 4'd0, 1'b0, 1'b0, 1'b0, expected_shift);

        if(errors==0) begin $display("[PASS] Ex06_sequential"); $fdisplay(log_fd,"[PASS] Ex06_sequential"); $fdisplay(result_fd,"pass"); end
        else begin $display("[FAIL] Ex06_sequential, errors = %0d", errors); $fdisplay(log_fd,"[FAIL] Ex06_sequential, errors = %0d", errors); $fdisplay(result_fd,"fail"); end
        $display("##END_STUDENT_CAN_SEE"); $fdisplay(log_fd,"##END_STUDENT_CAN_SEE");
        $fclose(log_fd); $fclose(result_fd); $finish;
    end
endmodule

tutorial/Ex06_sequential/sim/wave.vcd
$date
	Mon May 11 16:48:39 2026
$end
$version
	Icarus Verilog
$end
$timescale
	1ps
$end
$scope module tb_ex05_sequential $end
$var wire 8 ! shift_data [7:0] $end
$var wire 1 " serial_out $end
$var wire 1 # rollover $end
$var wire 1 $ jk_q_b $end
$var wire 1 % jk_q $end
$var wire 1 & dff_q_b $end
$var wire 1 ' dff_q $end
$var wire 4 ( cnt [3:0] $end
$var reg 1 ) clear $end
$var reg 1 * clk $end
$var reg 1 + d $end
$var reg 1 , en $end
$var reg 8 - expected_shift [7:0] $end
$var reg 1 . j $end
$var reg 1 / k $end
$var reg 1 0 rst_n $end
$var reg 1 1 serial_in $end
$var integer 32 2 errors [31:0] $end
$var integer 32 3 i [31:0] $end
$var integer 32 4 log_fd [31:0] $end
$var integer 32 5 pattern [31:0] $end
$var integer 32 6 result_fd [31:0] $end
$scope module u_counter $end
$var wire 1 ) clear $end
$var wire 1 * clk $end
$var wire 1 , en $end
$var wire 1 # rollover $end
$var wire 1 0 rst_n $end
$var reg 4 7 cnt [3:0] $end
$var reg 4 8 cnt_nxt [3:0] $end
$upscope $end
$scope module u_dff $end
$var wire 1 * clk $end
$var wire 1 + d $end
$var wire 1 & q_b $end
$var wire 1 0 rst_n $end
$var reg 1 ' q $end
$upscope $end
$scope module u_jk $end
$var wire 1 * clk $end
$var wire 1 . j $end
$var wire 1 / k $end
$var wire 1 $ q_b $end
$var wire 1 0 rst_n $end
$var reg 1 % q $end
$var reg 1 9 q_nxt $end
$upscope $end
$scope module u_shift $end
$var wire 1 * clk $end
$var wire 1 , en $end
$var wire 1 0 rst_n $end
$var wire 1 1 serial_in $end
$var wire 1 " serial_out $end
$var reg 8 : data [7:0] $end
$upscope $end
$scope task check $end
$var reg 4 ; exp_cnt [3:0] $end
$var reg 1 < exp_dff_q $end
$var reg 1 = exp_jk_q $end
$var reg 1 > exp_rollover $end
$var reg 8 ? exp_shift_value [7:0] $end
$var reg 256 @ name [255:0] $end
$upscope $end
$upscope $end
$enddefinitions $end
$comment Show the parameter values. $end
$dumpall
$end
#0
$dumpvars
bx @
bx ?
x>
x=
x<
bx ;
b0 :
09
b0 8
b0 7
b10000000000000000000000000000100 6
b0 5
b10000000000000000000000000000011 4
bx 3
b0 2
01
00
0/
0.
b0 -
0,
0+
0*
0)
b0 (
0'
1&
0%
1$
0#
0"
b0 !
$end
#5000
1*
#10000
0*
#15000
1*
#20000
10
0*
#25000
b1 5
b0 ?
0=
0<
0>
b0 ;
b1110010011001010111001101100101011101000010000001110010011001010110110001100101011000010111001101100101 @
1*
#30000
19
b1 8
b1 -
11
1.
1+
1,
0*
#35000
b10 8
0&
0$
b1 (
b1 7
1'
1%
b1 !
b1 :
b10 5
b1 ?
1=
1<
b1 ;
b11100110110010101110100001000000110000101101110011001000010000001110011011010000110100101100110011101000010000000110001 @
1*
#40000
b10 -
01
0.
0+
0*
#45000
1&
b11 8
b10 !
b10 :
0'
b10 (
b10 7
b11 5
b10 ?
0<
b10 ;
b1101000011011110110110001100100001000000110101001101011001000000110000101101110011001000010000001110011011010000110100101100110011101000010000000110000 @
1*
#50000
09
b101 -
11
1/
1.
0*
#55000
b100 8
19
1$
b11 (
b11 7
0%
b101 !
b101 :
b100 5
b101 ?
0=
b11 ;
b11101000110111101100111011001110110110001100101001000000110101001101011 @
1*
#60000
09
b0 8
b1011 -
0.
1)
0*
#65000
b1011 !
b1011 :
b0 (
b0 7
b101 5
b1011 ?
b0 ;
b110001101101100011001010110000101110010001000000110001101101111011101010110111001110100011001010111001000100000011000010110111001100100001000000111001001100101011100110110010101110100001000000110101001101011 @
1*
#70000
01
0,
0)
0*
#75000
b110 5
b1101000011011110110110001100100001000000110001101101111011101010110111001110100011001010111001000100000011000010110111001100100001000000111001101101000011010010110011001110100 @
1*
#80000
b1 8
b10110 -
b1 3
0/
1,
0*
#85000
b10 8
b10110 !
b10110 :
b1 (
b1 7
b111 5
b10110 ?
b1 ;
b11000110110111101110101011011100111010000100000011101000110111101110111011000010111001001100100001000000111001001101111011011000110110001101111011101100110010101110010 @
1*
#86000
b101100 -
b10 3
#90000
0*
#95000
b11 8
b10 (
b10 7
b101100 !
b101100 :
b1000 5
b101100 ?
b10 ;
1*
#96000
b1011000 -
b11 3
#100000
0*
#105000
b100 8
b1011000 !
b1011000 :
b11 (
b11 7
b1001 5
b1011000 ?
b11 ;
1*
#106000
b10110000 -
b100 3
#110000
0*
#115000
b101 8
1"
b100 (
b100 7
b10110000 !
b10110000 :
b1010 5
b10110000 ?
b100 ;
1*
#116000
b1100000 -
b101 3
#120000
0*
#125000
0"
b110 8
b1100000 !
b1100000 :
b101 (
b101 7
b1011 5
b1100000 ?
b101 ;
1*
#126000
b11000000 -
b110 3
#130000
0*
#135000
b111 8
1"
b110 (
b110 7
b11000000 !
b11000000 :
b1100 5
b11000000 ?
b110 ;
1*
#136000
b10000000 -
b111 3
#140000
0*
#145000
b1000 8
b10000000 !
b10000000 :
b111 (
b111 7
b1101 5
b10000000 ?
b111 ;
1*
#146000
b0 -
b1000 3
#150000
0*
#155000
b1001 8
0"
b1000 (
b1000 7
b0 !
b0 :
b1110 5
b0 ?
b1000 ;
1*
#156000
b1001 3
#160000
0*
#165000
b1010 8
b1001 (
b1001 7
b1111 5
b1001 ;
1*
#166000
b1010 3
#170000
0*
#175000
b1011 8
b1010 (
b1010 7
b10000 5
b1010 ;
1*
#176000
b1011 3
#180000
0*
#185000
b1100 8
b1011 (
b1011 7
b10001 5
b1011 ;
1*
#186000
b1100 3
#190000
0*
#195000
b1101 8
b1100 (
b1100 7
b10010 5
b1100 ;
1*
#196000
b1101 3
#200000
0*
#205000
b1110 8
b1101 (
b1101 7
b10011 5
b1101 ;
1*
#206000
b1110 3
#210000
0*
#215000
b1111 8
b1110 (
b1110 7
b10100 5
b1110 ;
1*
#216000
b1111 3
#220000
0*
#225000
b0 8
1#
b1111 (
b1111 7
b10101 5
1>
b1111 ;
b111001001101111011011000110110001101111011101100110010101110010001000000110000101110011011100110110010101110010011101000110010101100100001000000110000101110100001000000011000100110101 @
1*
#230000
0*
#235000
b1 8
0#
b0 (
b0 7
b10110 5
0>
b0 ;
b1110111011100100110000101110000001000000110000101100110011101000110010101110010001000000111001001101111011011000110110001101111011101100110010101110010 @
1*
