tutorial/Ex06_sequential/shift_register.v
module Ex06_ShiftRegister (
    input        clk,
    input        rst_n,
    input        en,
    input        serial_in,
    output       serial_out,
    output reg [7:0] data
);

// ** shift register **
// When en is 1, data shifts left by one bit every clock cycle.
// serial_in enters from bit 0, and the old bit 7 becomes serial_out.
always @(posedge clk or negedge rst_n) begin
    if (!rst_n) begin
        data <= 8'd0;
    end else if (en) begin
        data <= {data[6:0], serial_in};
    end else begin
        data <= data;
    end
end

assign serial_out = data[7];

endmodule

tutorial/Ex06_sequential/dff.v
module Ex06_DFF (
    input      clk,
    input      rst_n,
    input      d,
    output reg q
);

// ** D flip-flop **
// q samples d on every rising clock edge.
always @(posedge clk or negedge rst_n) begin
    if (!rst_n) begin
        q <= 1'b0;
    end else begin
        q <= d;
    end
end

endmodule

tutorial/Ex06_sequential/counter.v
module Ex06_Counter (
    input        clk,
    input        rst_n,
    input        en,
    input        clear,
    output reg [3:0] cnt,
    output       rollover
);

reg [3:0] cnt_nxt;

// ** state transition **
always @(posedge clk or negedge rst_n) begin
    if (!rst_n) begin
        cnt <= 4'd0;
    end else begin
        cnt <= cnt_nxt;
    end
end

// ** next state logic **
always @(*) begin
    if (clear) begin
        cnt_nxt = 4'd0;
    end else if (en) begin
        cnt_nxt = cnt + 4'd1;
    end else begin
        cnt_nxt = cnt;
    end
end

// ** output logic **
assign rollover = en && (cnt == 4'hf);

endmodule

tutorial/Ex06_sequential/tb.v
`timescale 1ns/1ps
module tb_ex05_sequential;
    reg clk, rst_n;
    reg en, clear, d, serial_in;
    wire [3:0] cnt;
    wire rollover;
    wire dff_q;
    wire serial_out;
    wire [7:0] shift_data;
    integer errors, log_fd, result_fd, pattern, i;
    reg [7:0] expected_shift;

    Ex06_Counter u_counter(.clk(clk), .rst_n(rst_n), .en(en), .clear(clear), .cnt(cnt), .rollover(rollover));
    Ex06_DFF u_dff(.clk(clk), .rst_n(rst_n), .d(d), .q(dff_q));
    Ex06_ShiftRegister u_shift(.clk(clk), .rst_n(rst_n), .en(en), .serial_in(serial_in), .serial_out(serial_out), .data(shift_data));

    initial begin clk = 0; forever #5 clk = ~clk; end

    task check;
        input [8*32-1:0] name;
        input [3:0] exp_cnt;
        input exp_rollover;
        input exp_dff_q;
        input [7:0] exp_shift_value;
        begin
            pattern = pattern + 1;
            #1;
            if (cnt !== exp_cnt || rollover !== exp_rollover || dff_q !== exp_dff_q || shift_data !== exp_shift_value) begin
                $display("[ERROR] pattern %0d (%0s): cnt=%0d/%0d rollover=%b/%b dff=%b/%b shift=%b/%b", pattern, name, exp_cnt, cnt, exp_rollover, rollover, exp_dff_q, dff_q, exp_shift_value, shift_data);
                $fdisplay(log_fd,"[ERROR] pattern %0d (%0s): cnt=%0d/%0d rollover=%b/%b dff=%b/%b shift=%b/%b", pattern, name, exp_cnt, cnt, exp_rollover, rollover, exp_dff_q, dff_q, exp_shift_value, shift_data);
                errors = errors + 1;
            end
        end
    endtask

    initial begin
        log_fd=$fopen("sim/log.txt","w"); result_fd=$fopen("sim/result.txt","w");
        $dumpfile("sim/wave.vcd"); $dumpvars(0,tb_ex05_sequential);
        $display("##SEC_STUDENT_CAN_SEE"); $fdisplay(log_fd,"##SEC_STUDENT_CAN_SEE");
        errors=0; pattern=0; rst_n=0; en=0; clear=0; d=0; serial_in=0; expected_shift=8'b0000_0000;
        repeat(2) @(posedge clk); @(negedge clk); rst_n=1; @(posedge clk); check("reset release", 4'd0, 1'b0, 1'b0, 8'b0000_0000);

        @(negedge clk); en=1; d=1; serial_in=1;
        expected_shift = {expected_shift[6:0], 1'b1};
        @(posedge clk); check("set and shift 1", 4'd1, 1'b0, 1'b1, expected_shift);

        @(negedge clk); d=0; serial_in=0;
        expected_shift = {expected_shift[6:0], 1'b0};
        @(posedge clk); check("shift 0", 4'd2, 1'b0, 1'b0, expected_shift);

        @(negedge clk); serial_in=1;
        expected_shift = {expected_shift[6:0], 1'b1};
        @(posedge clk); check("shift 1", 4'd3, 1'b0, 1'b0, expected_shift);

        @(negedge clk); clear=1; en=1; serial_in=1;
        expected_shift = {expected_shift[6:0], 1'b1};
        @(posedge clk); check("clear counter", 4'd0, 1'b0, 1'b0, expected_shift);

        @(negedge clk); clear=0; en=0; serial_in=0;
        @(posedge clk); check("hold counter and shift", 4'd0, 1'b0, 1'b0, expected_shift);

        @(negedge clk); en=1; d=0; serial_in=0;
        for (i = 1; i <= 14; i = i + 1) begin
            expected_shift = {expected_shift[6:0], 1'b0};
            @(posedge clk); check("count toward rollover", i[3:0], 1'b0, 1'b0, expected_shift);
        end
        expected_shift = {expected_shift[6:0], 1'b0};
        @(posedge clk); check("rollover asserted at 15", 4'd15, 1'b1, 1'b0, expected_shift);
        expected_shift = {expected_shift[6:0], 1'b0};
        @(posedge clk); check("wrap after rollover", 4'd0, 1'b0, 1'b0, expected_shift);

        if(errors==0) begin $display("[PASS] Ex06_sequential"); $fdisplay(log_fd,"[PASS] Ex06_sequential"); $fdisplay(result_fd,"pass"); end
        else begin $display("[FAIL] Ex06_sequential, errors = %0d", errors); $fdisplay(log_fd,"[FAIL] Ex06_sequential, errors = %0d", errors); $fdisplay(result_fd,"fail"); end
        $display("##END_STUDENT_CAN_SEE"); $fdisplay(log_fd,"##END_STUDENT_CAN_SEE");
        $fclose(log_fd); $fclose(result_fd); $finish;
    end
endmodule

tutorial/Ex06_sequential/sim/wave.vcd
$date
	Thu Jul 02 00:47:46 2026
$end
$version
	Icarus Verilog
$end
$timescale
	1ps
$end
$scope module tb_ex05_sequential $end
$var wire 8 ! shift_data [7:0] $end
$var wire 1 " serial_out $end
$var wire 1 # rollover $end
$var wire 1 $ dff_q $end
$var wire 4 % cnt [3:0] $end
$var reg 1 & clear $end
$var reg 1 ' clk $end
$var reg 1 ( d $end
$var reg 1 ) en $end
$var reg 8 * expected_shift [7:0] $end
$var reg 1 + rst_n $end
$var reg 1 , serial_in $end
$var integer 32 - errors [31:0] $end
$var integer 32 . i [31:0] $end
$var integer 32 / log_fd [31:0] $end
$var integer 32 0 pattern [31:0] $end
$var integer 32 1 result_fd [31:0] $end
$scope module u_counter $end
$var wire 1 & clear $end
$var wire 1 ' clk $end
$var wire 1 ) en $end
$var wire 1 # rollover $end
$var wire 1 + rst_n $end
$var reg 4 2 cnt [3:0] $end
$var reg 4 3 cnt_nxt [3:0] $end
$upscope $end
$scope module u_dff $end
$var wire 1 ' clk $end
$var wire 1 ( d $end
$var wire 1 + rst_n $end
$var reg 1 $ q $end
$upscope $end
$scope module u_shift $end
$var wire 1 ' clk $end
$var wire 1 ) en $end
$var wire 1 + rst_n $end
$var wire 1 , serial_in $end
$var wire 1 " serial_out $end
$var reg 8 4 data [7:0] $end
$upscope $end
$scope task check $end
$var reg 4 5 exp_cnt [3:0] $end
$var reg 1 6 exp_dff_q $end
$var reg 1 7 exp_rollover $end
$var reg 8 8 exp_shift_value [7:0] $end
$var reg 256 9 name [255:0] $end
$upscope $end
$upscope $end
$enddefinitions $end
$comment Show the parameter values. $end
$dumpall
$end
#0
$dumpvars
bx 9
bx 8
x7
x6
bx 5
b0 4
b0 3
b0 2
b10000000000000000000000000000100 1
b0 0
b10000000000000000000000000000011 /
bx .
b0 -
0,
0+
b0 *
0)
0(
0'
0&
b0 %
0$
0#
0"
b0 !
$end
#5000
1'
#10000
0'
#15000
1'
#20000
1+
0'
#25000
b1 0
b0 8
06
07
b0 5
b1110010011001010111001101100101011101000010000001110010011001010110110001100101011000010111001101100101 9
1'
#30000
b1 3
b1 *
1,
1(
1)
0'
#35000
b10 3
b1 %
b1 2
1$
b1 !
b1 4
b10 0
b1 8
16
b1 5
b11100110110010101110100001000000110000101101110011001000010000001110011011010000110100101100110011101000010000000110001 9
1'
#40000
b10 *
0,
0(
0'
#45000
b11 3
b10 !
b10 4
0$
b10 %
b10 2
b11 0
b10 8
06
b10 5
b1110011011010000110100101100110011101000010000000110000 9
1'
#50000
b101 *
1,
0'
#55000
b100 3
b11 %
b11 2
b101 !
b101 4
b100 0
b101 8
b11 5
b1110011011010000110100101100110011101000010000000110001 9
1'
#60000
b0 3
b1011 *
1&
0'
#65000
b1011 !
b1011 4
b0 %
b0 2
b101 0
b1011 8
b0 5
b1100011011011000110010101100001011100100010000001100011011011110111010101101110011101000110010101110010 9
1'
#70000
0,
0)
0&
0'
#75000
b110 0
b1101000011011110110110001100100001000000110001101101111011101010110111001110100011001010111001000100000011000010110111001100100001000000111001101101000011010010110011001110100 9
1'
#80000
b1 3
b10110 *
b1 .
1)
0'
#85000
b10 3
b10110 !
b10110 4
b1 %
b1 2
b111 0
b10110 8
b1 5
b11000110110111101110101011011100111010000100000011101000110111101110111011000010111001001100100001000000111001001101111011011000110110001101111011101100110010101110010 9
1'
#86000
b101100 *
b10 .
#90000
0'
#95000
b11 3
b10 %
b10 2
b101100 !
b101100 4
b1000 0
b101100 8
b10 5
1'
#96000
b1011000 *
b11 .
#100000
0'
#105000
b100 3
b1011000 !
b1011000 4
b11 %
b11 2
b1001 0
b1011000 8
b11 5
1'
#106000
b10110000 *
b100 .
#110000
0'
#115000
b101 3
1"
b100 %
b100 2
b10110000 !
b10110000 4
b1010 0
b10110000 8
b100 5
1'
#116000
b1100000 *
b101 .
#120000
0'
#125000
0"
b110 3
b1100000 !
b1100000 4
b101 %
b101 2
b1011 0
b1100000 8
b101 5
1'
#126000
b11000000 *
b110 .
#130000
0'
#135000
b111 3
1"
b110 %
b110 2
b11000000 !
b11000000 4
b1100 0
b11000000 8
b110 5
1'
#136000
b10000000 *
b111 .
#140000
0'
#145000
b1000 3
b10000000 !
b10000000 4
b111 %
b111 2
b1101 0
b10000000 8
b111 5
1'
#146000
b0 *
b1000 .
#150000
0'
#155000
b1001 3
0"
b1000 %
b1000 2
b0 !
b0 4
b1110 0
b0 8
b1000 5
1'
#156000
b1001 .
#160000
0'
#165000
b1010 3
b1001 %
b1001 2
b1111 0
b1001 5
1'
#166000
b1010 .
#170000
0'
#175000
b1011 3
b1010 %
b1010 2
b10000 0
b1010 5
1'
#176000
b1011 .
#180000
0'
#185000
b1100 3
b1011 %
b1011 2
b10001 0
b1011 5
1'
#186000
b1100 .
#190000
0'
#195000
b1101 3
b1100 %
b1100 2
b10010 0
b1100 5
1'
#196000
b1101 .
#200000
0'
#205000
b1110 3
b1101 %
b1101 2
b10011 0
b1101 5
1'
#206000
b1110 .
#210000
0'
#215000
b1111 3
b1110 %
b1110 2
b10100 0
b1110 5
1'
#216000
b1111 .
#220000
0'
#225000
b0 3
1#
b1111 %
b1111 2
b10101 0
17
b1111 5
b111001001101111011011000110110001101111011101100110010101110010001000000110000101110011011100110110010101110010011101000110010101100100001000000110000101110100001000000011000100110101 9
1'
#230000
0'
#235000
b1 3
0#
b0 %
b0 2
b10110 0
07
b0 5
b1110111011100100110000101110000001000000110000101100110011101000110010101110010001000000111001001101111011011000110110001101111011101100110010101110010 9
1'
